Workbook
Name Beginning: #REF!
Name BudgetPercentage: #REF!
Name BudgetThreshold: #REF!
Name Client: #REF!
Name Current: #REF!
Name QBCANSUPPORTUPDATE: TRUE
Name QBCANSUPPORTUPDATE: TRUE
Name QBCANSUPPORTUPDATE: TRUE
Name QBCOMPANYFILENAME: "I:\Jewish Family Services.QBW"
Name QBCOMPANYFILENAME: "C:\ElCentroWorkingArchive\libertad.qbw"
Name QBCOMPANYFILENAME: "C:\ElCentroWorkingArchive\libertad.qbw"
Name QBENDDATE: 20240630
Name QBENDDATE: 20220630
Name QBENDDATE: 20220630
Name QBHEADERSONSCREEN: FALSE
Name QBHEADERSONSCREEN: FALSE
Name QBHEADERSONSCREEN: FALSE
Name QBMETADATASIZE: 5931
Name QBMETADATASIZE: 5924
Name QBMETADATASIZE: 5924
Name QBPRESERVECOLOR: TRUE
Name QBPRESERVECOLOR: TRUE
Name QBPRESERVECOLOR: TRUE
Name QBPRESERVEFONT: TRUE
Name QBPRESERVEFONT: TRUE
Name QBPRESERVEFONT: TRUE
Name QBPRESERVEROWHEIGHT: TRUE
Name QBPRESERVEROWHEIGHT: TRUE
Name QBPRESERVEROWHEIGHT: TRUE
Name QBPRESERVESPACE: TRUE
Name QBPRESERVESPACE: FALSE
Name QBPRESERVESPACE: FALSE
Name QBREPORTCOLAXIS: 19
Name QBREPORTCOLAXIS: 8
Name QBREPORTCOLAXIS: 0
Name QBREPORTCOMPANYID: "1299d3132f084724aff0cb21db4a24c4"
Name QBREPORTCOMPANYID: "865a3afdace341f0871aaf9656bcdc8e"
Name QBREPORTCOMPANYID: "865a3afdace341f0871aaf9656bcdc8e"
Name QBREPORTCOMPARECOL_ANNUALBUDGET: FALSE
Name QBREPORTCOMPARECOL_ANNUALBUDGET: FALSE
Name QBREPORTCOMPARECOL_ANNUALBUDGET: FALSE
Name QBREPORTCOMPARECOL_AVGCOGS: FALSE
Name QBREPORTCOMPARECOL_AVGCOGS: FALSE
Name QBREPORTCOMPARECOL_AVGCOGS: FALSE
Name QBREPORTCOMPARECOL_AVGPRICE: FALSE
Name QBREPORTCOMPARECOL_AVGPRICE: FALSE
Name QBREPORTCOMPARECOL_AVGPRICE: FALSE
Name QBREPORTCOMPARECOL_BUDDIFF: FALSE
Name QBREPORTCOMPARECOL_BUDDIFF: FALSE
Name QBREPORTCOMPARECOL_BUDDIFF: FALSE
Name QBREPORTCOMPARECOL_BUDGET: FALSE
Name QBREPORTCOMPARECOL_BUDGET: FALSE
Name QBREPORTCOMPARECOL_BUDGET: FALSE
Name QBREPORTCOMPARECOL_BUDPCT: FALSE
Name QBREPORTCOMPARECOL_BUDPCT: FALSE
Name QBREPORTCOMPARECOL_BUDPCT: FALSE
Name QBREPORTCOMPARECOL_COGS: FALSE
Name QBREPORTCOMPARECOL_COGS: FALSE
Name QBREPORTCOMPARECOL_COGS: FALSE
Name QBREPORTCOMPARECOL_EXCLUDEAMOUNT: FALSE

Sheet Review-Checkpoints
B2: Checklist for Review Exempt Org Tax Return
B4: Revenue - Checks
B5: S No | C5: Check Points | D5: Verification Check | E5: Review Points | F5: Compliance Check
B6: 1 | C6: Is there any Govt Grant | D6: =IF('Part VIII - Revenue'!D8>0,"Yes","No") -> Yes | E6: Is Contributed list updated in Schedule B and RRF-1
B7: 2 | C7: Is there any other contribution | D7: =IF('Part VIII - Revenue'!D9>0,"Yes","No") -> Yes | E7: Is Contributed list updated in Schedule B
B8: 3 | C8: Is there any Non cash contribution more than $25000 | D8: =IF('Part VIII - Revenue'!D10>25000,"Yes","No") -> No | E8: Are details updated in Schedule M
B9: 4 | C9: Is there any donated services / In-Kind service | D9: =IF(ISNUMBER(MATCH("Adj-DS",SOR!F:F, 0)), "Yes", "No") -> Yes | E9: Is it part of reconciliation on page -12 and schedule D
B10: 5 | C10: Is there any Unrealized Gain / Loss | D10: =IF(ISNUMBER(MATCH("Adj-UG",SOR!F:F, 0)), "Yes", "No") -> Yes | E10: Is it part of reconciliation on page -12 and schedule D
B11: 6 | C11: Is there any Program Service Revenue | D11: =IF('Part VIII - Revenue'!E19>0,"Yes","No") -> Yes | E11: Is it reconciled with Page 2
B12: 7 | C12: Is there any Investment Income | D12: =IF('Part VIII - Revenue'!E20>0,"Yes","No") -> Yes | E12: It should be Gross income without effect of Unrealized gain and Investment Exp
B13: 8 | C13: Is there any Investment Management Exp | D13: =IF('Part IX - Expenses'!C19>0,"Yes","No") -> Yes | E13: Is it showing in Line 11f of part IX
B14: 9 | C14: Is there Fundraising Income More Than $15000 | D14: =+IF(('Part VIII - Revenue'!D6+'Part VIII - Revenue'!D33)>15000,"Yes","No") -> Yes | E14: Is Schedule G Filled properly
B17: Expenses - Checks
B18: S No | C18: Check Points | D18: Verification Check | E18: Review Points | F18: Compliance Check
B19: 1 | C19: Is there any Grants and Other Assistance paid more than $5000 | D19: =IF(OR('Part IX - Expenses'!C4>5000, 'Part IX - Expenses'!C5>5000), "Yes", "No") -> Yes | E19: Is Schedule I Filled Properly
B20: 2 | C20: Is there Professional Fundraising Services More Than $15000 | D20: =+IF('Part IX - Expenses'!C18>15000,"Yes","No") -> No | E20: Is Schedule G Filled properly
B21: 3 | C21: Is there any Depreciation expenses | D21: =+IF('Part IX - Expenses'!C31>0,"Yes","No") -> Yes | E21: Is Form 3885 or 3885F Filled properly
B22: 4 | C22: Is Total of Program Service Expenses Reconciled with page 2
B25: Balance Sheet - Checks
B26: S No | C26: Check Points | D26: Verification Check | E26: Review Points | F26: Compliance Check
B27: 1 | C27: Is there any receivable from or payable to disqualified person | D27: =+IF(('Part X - Balance Sheet'!E8+'Part X - Balance Sheet'!E27)>0,"Yes","No") -> No | E27: Is Schedule L filled properly and Line 1 of RRF-1 marked yes
B28: 2 | C28: Is there any other transaction with disqualified person | D28: No | E28: Is Schedule L filled properly and Line 1 of RRF-1 marked yes
B29: 3 | C29: Is there any Escrow and Custodial Arrangements | D29: =+IF('Part X - Balance Sheet'!E26>0,"Yes","No") -> No | E29: Is Part IV of Schedule D filled properly
B30: 4 | C30: Is there any fixed assets | D30: =IF('Part X - Balance Sheet'!E15>0,"Yes","No") -> Yes | E30: Is Part VI of schedule D matched with Audit Report
B31: 5 | C31: Is organization hold assets in donor-restricted endowments | D31: No | E31: Is Part V of Schedule D filled properly
B32: 6 | C32: Is there any related party (See Note in Audit Report) | D32: No | E32: Is Schedule R filled properly
B35: Other - Checks
B36: S No | C36: Check Points | D36: Verification Check | E36: Review Points | F36: Compliance Check
B37: 1 | C37: Is all revenue figures updated in schedule A | D37: No
B38: 2 | C38: Is Form-199 figures matched with Audit Report or Books | D38: Yes
B39: 3 | C39: Are figures updated in Form RRF-1 | D39: No
B40: 4 | C40: Is it being submitted per Final Audit Report figures | D40: No | E40: Are these lines marked "✔" (Part IV Line 12a/b, Part XII Line 2a,b,c, RRF-1 Line 8)
B41: 5 | C41: Is there any footnote regarding the uncertain income tax position in the Final Audit Report | D41: No | E41: Is it stated in Schedule D Supplemental Information
B42: 6 | C42: Is single audit applicable in Audit Report (SEFA) | D42: No | E42: Are these lines marked "✔" (Part XII Line 3a and 3b)
B43: 7 | C43: Is the FY ending other than December | D43: No | E43: Is CA copy made and compensation statement generated in form 199.

Sheet Part VIII - Revenue
A2: Part VIII - Statement of Revenue
A3: Line | B3: Particulars | E3: Total Revenue | F3: Related or Exempt Function Income | G3: Unrelated Business Revenue | H3: Revenue excluded from tax under $512, 513 or 514 | I3: Last Year
A4: 1a | B4: Federated Campaigns | D4: =+SUMIF(SOR!$F:$F,'Part VIII - Revenue'!$A4,SOR!$B:$B) -> 0 | I4: =+SUMIF(SOR!$H:$H,'Part VIII - Revenue'!$A4,SOR!$G:$G) -> 0
A5: 1b | B5: Membership Dues | D5: =+SUMIF(SOR!$F:$F,'Part VIII - Revenue'!$A5,SOR!$B:$B) -> 0 | I5: =+SUMIF(SOR!$H:$H,'Part VIII - Revenue'!$A5,SOR!$G:$G) -> 0
A6: 1c | B6: Fundraising Events | D6: =+SUMIF(SOR!$F:$F,'Part VIII - Revenue'!$A6,SOR!$B:$B) -> 152678 | I6: =+SUMIF(SOR!$H:$H,'Part VIII - Revenue'!$A6,SOR!$G:$G) -> 145827
A7: 1d | B7: Related Organisations | D7: =+SUMIF(SOR!$F:$F,'Part VIII - Revenue'!$A7,SOR!$B:$B) -> 0 | I7: =+SUMIF(SOR!$H:$H,'Part VIII - Revenue'!$A7,SOR!$G:$G) -> 0
A8: 1e | B8: Government Grants/ Contributions | D8: =+SUMIF(SOR!$F:$F,'Part VIII - Revenue'!$A8,SOR!$B:$B) -> 2083067 | I8: =+SUMIF(SOR!$H:$H,'Part VIII - Revenue'!$A8,SOR!$G:$G) -> 5311998
A9: 1f | B9: All Other contributions, gifts, grants and similar amounts not listed above | D9: =+SUMIF(SOR!$F:$F,'Part VIII - Revenue'!$A9,SOR!$B:$B)+SUMIF(SOR!$F:$F,'Part VIII - Revenue'!$A10,SOR!$B:$B) -> 8057976 | I9: =+SUMIF(SOR!$H:$H,'Part VIII - Revenue'!$A9,SOR!$G:$G) -> 2829753
A10: 1g | B10: Noncash Contributions included in lines 1a-1f | D10: =+SUMIF(SOR!$F:$F,'Part VIII - Revenue'!$A10,SOR!$B:$B) -> 0 | I10: =+SUMIF(SOR!$H:$H,'Part VIII - Revenue'!$A10,SOR!$G:$G) -> 87636
A11: 1h | B11: Total. Add Lines 1a-1f | E11: =+SUM(D4:D9) -> 10293721 | I11: =SUM(I4:I10) -> 8375214
A12: 2 | B12: Program Service Revenue | D12: Business Code
A13: 2a | B13: =IFERROR(+INDEX(SOR!A:F,MATCH('Part VIII - Revenue'!A13,SOR!F:F,0),1),"") -> Program fees | E13: =SUM(F13:H13) -> 12254 | F13: =+SUMIF(SOR!$F:$F,'Part VIII - Revenue'!$A:$A,SOR!C:C) -> 12254 | G13: =+SUMIF(SOR!$F:$F,'Part VIII - Revenue'!$A:$A,SOR!D:D) -> 0 | H13: =+SUMIF(SOR!$F:$F,'Part VIII - Revenue'!$A:$A,SOR!E:E) -> 0 | I13: =+SUMIF(SOR!$H:$H,'Part VIII - Revenue'!$A13,SOR!$G:$G) -> 42558
A14: 2b | B14: =IFERROR(+INDEX(SOR!A:F,MATCH('Part VIII - Revenue'!A14,SOR!F:F,0),1),"") | E14: =SUM(F14:H14) -> 0 | F14: =+SUMIF(SOR!$F:$F,'Part VIII - Revenue'!$A:$A,SOR!C:C) -> 0 | G14: =+SUMIF(SOR!$F:$F,'Part VIII - Revenue'!$A:$A,SOR!D:D) -> 0 | H14: =+SUMIF(SOR!$F:$F,'Part VIII - Revenue'!$A:$A,SOR!E:E) -> 0 | I14: =+SUMIF(SOR!$H:$H,'Part VIII - Revenue'!$A14,SOR!$G:$G) -> 0
A15: 2c | B15: =IFERROR(+INDEX(SOR!A:F,MATCH('Part VIII - Revenue'!A15,SOR!F:F,0),1),"") | E15: =SUM(F15:H15) -> 0 | F15: =+SUMIF(SOR!$F:$F,'Part VIII - Revenue'!$A:$A,SOR!C:C) -> 0 | G15: =+SUMIF(SOR!$F:$F,'Part VIII - Revenue'!$A:$A,SOR!D:D) -> 0 | H15: =+SUMIF(SOR!$F:$F,'Part VIII - Revenue'!$A:$A,SOR!E:E) -> 0 | I15: =+SUMIF(SOR!$H:$H,'Part VIII - Revenue'!$A15,SOR!$G:$G) -> 0
A16: 2d | B16: =IFERROR(+INDEX(SOR!A:F,MATCH('Part VIII - Revenue'!A16,SOR!F:F,0),1),"") | E16: =SUM(F16:H16) -> 0 | F16: =+SUMIF(SOR!$F:$F,'Part VIII - Revenue'!$A:$A,SOR!C:C) -> 0 | G16: =+SUMIF(SOR!$F:$F,'Part VIII - Revenue'!$A:$A,SOR!D:D) -> 0 | H16: =+SUMIF(SOR!$F:$F,'Part VIII - Revenue'!$A:$A,SOR!E:E) -> 0 | I16: =+SUMIF(SOR!$H:$H,'Part VIII - Revenue'!$A16,SOR!$G:$G) -> 0
A17: 2e | B17: =IFERROR(+INDEX(SOR!A:F,MATCH('Part VIII - Revenue'!A17,SOR!F:F,0),1),"") | E17: =SUM(F17:H17) -> 0 | F17: =+SUMIF(SOR!$F:$F,'Part VIII - Revenue'!$A:$A,SOR!C:C) -> 0 | G17: =+SUMIF(SOR!$F:$F,'Part VIII - Revenue'!$A:$A,SOR!D:D) -> 0 | H17: =+SUMIF(SOR!$F:$F,'Part VIII - Revenue'!$A:$A,SOR!E:E) -> 0 | I17: =+SUMIF(SOR!$H:$H,'Part VIII - Revenue'!$A17,SOR!$G:$G) -> 0
A18: 2f | B18: All other program service revenue | E18: =SUM(F18:H18) -> 0 | F18: =+SUMIF(SOR!$F:$F,'Part VIII - Revenue'!$A:$A,SOR!C:C) -> 0 | G18: =+SUMIF(SOR!$F:$F,'Part VIII - Revenue'!$A:$A,SOR!D:D) -> 0 | H18: =+SUMIF(SOR!$F:$F,'Part VIII - Revenue'!$A:$A,SOR!E:E) -> 0 | I18: =+SUMIF(SOR!$H:$H,'Part VIII - Revenue'!$A18,SOR!$G:$G) -> 0
A19: 2g | B19: Total. Add Lines 2a-2f | E19: =+SUM(E13:E18) -> 12254 | I19: =SUM(I13:I18) -> 42558
A20: 3 | B20: Investment Income (dividends, interest and other similar amounts) | E20: =+SUM(F20:H20) -> 24774 | F20: =+SUMIF(SOR!$F:$F,'Part VIII - Revenue'!$A:$A,SOR!C:C) -> 0 | G20: =+SUMIF(SOR!$F:$F,'Part VIII - Revenue'!$A:$A,SOR!D:D) -> 0 | H20: =+SUMIF(SOR!$F:$F,'Part VIII - Revenue'!$A:$A,SOR!E:E) -> 24774 | I20: =+SUMIF(SOR!$H:$H,'Part VIII - Revenue'!$A20,SOR!$G:$G) -> 29358
A21: 4 | B21: Income from Investment of tax-exempt bond proceeds | E21: =SUM(F21:H21) -> 0 | F21: =+SUMIF(SOR!$F:$F,'Part VIII - Revenue'!$A:$A,SOR!C:C) -> 0 | G21: =+SUMIF(SOR!$F:$F,'Part VIII - Revenue'!$A:$A,SOR!D:D) -> 0 | H21: =+SUMIF(SOR!$F:$F,'Part VIII - Revenue'!$A:$A,SOR!E:E) -> 0 | I21: =+SUMIF(SOR!$H:$H,'Part VIII - Revenue'!$A21,SOR!$G:$G) -> 0
A22: 5 | B22: Royalties | E22: =SUM(F22:H22) -> 0 | F22: =+SUMIF(SOR!$F:$F,'Part VIII - Revenue'!$A:$A,SOR!C:C) -> 0 | G22: =+SUMIF(SOR!$F:$F,'Part VIII - Revenue'!$A:$A,SOR!D:D) -> 0 | H22: =+SUMIF(SOR!$F:$F,'Part VIII - Revenue'!$A:$A,SOR!E:E) -> 0 | I22: =+SUMIF(SOR!$H:$H,'Part VIII - Revenue'!$A22,SOR!$G:$G) -> 0
C23: Real | D23: Personal
A24: 6a | B24: Gross Rents | C24: =+SUMIF(SOR!F:F,"6a-R",SOR!B:B) -> 0 | D24: =+SUMIF(SOR!F:F,"6a-P",SOR!B:B) -> 0 | I24: =+SUMIF(SOR!H:H,"6a-R",SOR!G:G)+SUMIF(SOR!H:H,"6a-P",SOR!G:G) -> 0
A25: 6b | B25: Less: Rental Expenses | C25: =+SUMIF(SOR!F:F,"6b-R",SOR!B:B) -> 0 | D25: =+SUMIF(SOR!F:F,"6b-P",SOR!B:B) -> 0 | I25: =+SUMIF(SOR!H:H,"6b-R",SOR!G:G)+SUMIF(SOR!H:H,"6b-P",SOR!G:G) -> 0
A26: 6c | B26: Rental Income or (Loss) | C26: =+C24-C25 -> 0 | D26: =D24-D25 -> 0 | I26: =+I24-I25 -> 0
A27: 6d | B27: Net Rental Income or (Loss) | E27: =+SUM(F27:H27) -> 0 | F27: =+SUMIF(SOR!F:F,"6a-R",SOR!C:C)-SUMIF(SOR!F:F,"6b-R",SOR!C:C)+SUMIF(SOR!F:F,"6a-P",SOR!C:C)-SUMIF(SOR!F:F,"6b-P",SOR!C:C) -> 0 | G27: =+SUMIF(SOR!F:F,"6a-R",SOR!D:D)-SUMIF(SOR!F:F,"6b-R",SOR!D:D)+SUMIF(SOR!F:F,"6a-P",SOR!D:D)-SUMIF(SOR!F:F,"6b-P",SOR!D:D) -> 0 | H27: =+SUMIF(SOR!F:F,"6a-R",SOR!E:E)-SUMIF(SOR!F:F,"6b-R",SOR!E:E)+SUMIF(SOR!F:F,"6a-P",SOR!E:E)-SUMIF(SOR!F:F,"6b-P",SOR!E:E) -> 0 | I27: =+I26 -> 0
C28: Securities | D28: Other
A29: 7a | B29: Gross Amounts from Sales of Assets other than Inventory | C29: =+SUMIF(SOR!F:F,"7a-S",SOR!B:B) -> 0 | D29: =+SUMIF(SOR!F:F,"7a-O",SOR!B:B) -> 0 | I29: =+SUMIF(SOR!H:H,"7a-S",SOR!G:G)+SUMIF(SOR!H:H,"7a-O",SOR!G:G) -> 103637
A30: 7b | B30: Less: Cost or Other Basis and sales expenses | C30: =+SUMIF(SOR!F:F,"7b-S",SOR!B:B) -> 0 | D30: =+SUMIF(SOR!F:F,"7b-o",SOR!B:B) -> 0 | I30: =+SUMIF(SOR!H:H,"7b-S",SOR!G:G)+SUMIF(SOR!H:H,"7b-O",SOR!G:G) -> 103801
A31: 7c | B31: Gain or (Loss) | C31: =+C29-C30 -> 0 | D31: =+D29-D30 -> 0 | I31: =+I29-I30 -> -164
A32: 7d | B32: Net Gain or (Loss) | E32: =SUM(F32:H32) -> 0 | F32: =+SUMIF(SOR!F:F,"7a-S",SOR!C:C)-SUMIF(SOR!F:F,"7b-S",SOR!C:C)+SUMIF(SOR!F:F,"7a-O",SOR!C:C)-SUMIF(SOR!F:F,"7b-O",SOR!C:C) -> 0 | G32: =+SUMIF(SOR!F:F,"7a-S",SOR!D:D)-SUMIF(SOR!F:F,"7b-S",SOR!D:D)+SUMIF(SOR!F:F,"7a-O",SOR!D:D)-SUMIF(SOR!F:F,"7b-O",SOR!D:D) -> 0 | H32: =+SUMIF(SOR!F:F,"7a-S",SOR!E:E)-SUMIF(SOR!F:F,"7b-S",SOR!E:E)+SUMIF(SOR!F:F,"7a-O",SOR!E:E)-SUMIF(SOR!F:F,"7b-O",SOR!E:E) -> 0 | I32: =+I31 -> -164
A33: 8a | B33: Gross Income from fundraising activities (not including contributions on line 1c) | D33: =+SUMIF(SOR!F:F,A33,SOR!B:B) -> 48164 | I33: =+SUMIF(SOR!$H:$H,'Part VIII - Revenue'!$A33,SOR!$G:$G) -> 33930
A34: 8b | B34: Less: Direct Expenses | D34: =+SUMIF(SOR!F:F,A34,SOR!B:B) -> 48164 | I34: =+SUMIF(SOR!$H:$H,'Part VIII - Revenue'!$A34,SOR!$G:$G) -> 33930
A35: 8c | B35: Net Income or (loss) from fund raising activities | E35: =+D33-D34 -> 0 | I35: =+I33-I34 -> 0
A36: 9a | B36: Gross Income from Gaming Activities | D36: =+SUMIF(SOR!F:F,A36,SOR!B:B) -> 0 | I36: =+SUMIF(SOR!$H:$H,'Part VIII - Revenue'!$A36,SOR!$G:$G) -> 0
A37: 9b | B37: Less: Direct Expenses | D37: =+SUMIF(SOR!F:F,A37,SOR!B:B) -> 0 | I37: =+SUMIF(SOR!$H:$H,'Part VIII - Revenue'!$A37,SOR!$G:$G) -> 0
A38: 9c | B38: Net Income or (loss) from gaming activities | E38: =SUM(F38:H38) -> 0 | F38: =+SUMIF(SOR!F:F,"9a",SOR!C:C)-SUMIF(SOR!F:F,"9b",SOR!C:C) -> 0 | G38: =+SUMIF(SOR!F:F,"9a",SOR!D:D)-SUMIF(SOR!F:F,"9b",SOR!D:D) -> 0 | H38: =+SUMIF(SOR!F:F,"9a",SOR!E:E)-SUMIF(SOR!F:F,"9b",SOR!E:E) -> 0 | I38: =+I36-I37 -> 0
A39: 10a | B39: Gross Sales of Inventory, less returns and allowances | D39: =+SUMIF(SOR!F:F,A39,SOR!B:B) -> 0 | I39: =+SUMIF(SOR!$H:$H,'Part VIII - Revenue'!$A39,SOR!$G:$G) -> 0
A40: 10b | B40: Less: COGS | D40: =+SUMIF(SOR!F:F,A40,SOR!B:B) -> 0 | I40: =+SUMIF(SOR!$H:$H,'Part VIII - Revenue'!$A40,SOR!$G:$G) -> 0
A41: 10c | B41: Net Income or (loss) from Sales of Inventory | E41: =SUM(F41:H41) -> 0 | F41: =+SUMIF(SOR!F:F,"10a",SOR!C:C)-SUMIF(SOR!F:F,"10b",SOR!C:C) -> 0 | G41: =+SUMIF(SOR!F:F,"10a",SOR!D:D)-SUMIF(SOR!F:F,"10b",SOR!D:D) -> 0 | H41: =+SUMIF(SOR!F:F,"10a",SOR!E:E)-SUMIF(SOR!F:F,"10b",SOR!E:E) -> 0 | I41: =+I39-I40 -> 0
A42: 11 | B42: Miscellaneous revenue | D42: Business Code
A43: 11a | B43: =IFERROR(+INDEX(SOR!A:F,MATCH('Part VIII - Revenue'!A43,SOR!F:F,0),1),"") -> Other Income | E43: =+SUM(F43:H43) -> 127757 | F43: =+SUMIF(SOR!$F:$F,'Part VIII - Revenue'!$A:$A,SOR!C:C) -> 127757 | G43: =+SUMIF(SOR!$F:$F,'Part VIII - Revenue'!$A:$A,SOR!D:D) -> 0 | H43: =+SUMIF(SOR!$F:$F,'Part VIII - Revenue'!$A:$A,SOR!E:E) -> 0 | I43: =+SUMIF(SOR!$H:$H,'Part VIII - Revenue'!$A43,SOR!$G:$G) -> 0
A44: 11b | B44: =IFERROR(+INDEX(SOR!A:F,MATCH('Part VIII - Revenue'!A44,SOR!F:F,0),1),"") | E44: =+SUM(F44:H44) -> 0 | F44: =+SUMIF(SOR!$F:$F,'Part VIII - Revenue'!$A:$A,SOR!C:C) -> 0 | G44: =+SUMIF(SOR!$F:$F,'Part VIII - Revenue'!$A:$A,SOR!D:D) -> 0 | H44: =+SUMIF(SOR!$F:$F,'Part VIII - Revenue'!$A:$A,SOR!E:E) -> 0 | I44: =+SUMIF(SOR!$H:$H,'Part VIII - Revenue'!$A44,SOR!$G:$G) -> 0
A45: 11c | B45: =IFERROR(+INDEX(SOR!A:F,MATCH('Part VIII - Revenue'!A45,SOR!F:F,0),1),"") | E45: =+SUM(F45:H45) -> 0 | F45: =+SUMIF(SOR!$F:$F,'Part VIII - Revenue'!$A:$A,SOR!C:C) -> 0 | G45: =+SUMIF(SOR!$F:$F,'Part VIII - Revenue'!$A:$A,SOR!D:D) -> 0 | H45: =+SUMIF(SOR!$F:$F,'Part VIII - Revenue'!$A:$A,SOR!E:E) -> 0 | I45: =+SUMIF(SOR!$H:$H,'Part VIII - Revenue'!$A45,SOR!$G:$G) -> 0
A46: 11d | B46: All other revenue | E46: =+SUM(F46:H46) -> 0 | F46: =+SUMIF(SOR!$F:$F,'Part VIII - Revenue'!$A:$A,SOR!C:C) -> 0 | G46: =+SUMIF(SOR!$F:$F,'Part VIII - Revenue'!$A:$A,SOR!D:D) -> 0 | H46: =+SUMIF(SOR!$F:$F,'Part VIII - Revenue'!$A:$A,SOR!E:E) -> 0 | I46: =+SUMIF(SOR!$H:$H,'Part VIII - Revenue'!$A46,SOR!$G:$G) -> 0
A47: 11e | B47: Total. (Line 11a-11d) | E47: =+SUM(E43:E46) -> 127757 | I47: =SUM(I43:I46) -> 0
A48: 12 | B48: Total Revenue | E48: =SUM(F48:H48)+E11+E35 -> 10458506 | F48: =SUM(F13:F22,F27,F32,F38,F41,F43:F46) -> 140011 | G48: =SUM(G13:G22,G27,G32,G38,G41,G43:G46) -> 0 | H48: =SUM(H13:H22,H27,H32,H38,H41,H43:H46) -> 24774 | I48: =+I47+I41+I38+I35+I32+I27+I22+I21+I20+I19+I11 -> 8446966

Sheet Part IX - Expenses
A2: Part IX: Statement of Functional Expenses
A3: Line | B3: Particulars | C3: Total | D3: Program Service | E3: Management | F3: Fundraising | G3: Last Year
A4: 1 | B4: Grants and other assistance to domestic governments and domestic organisations | C4: =SUM(D4:F4) -> 0 | D4: =+SUMIF(SOFE!$J:$J,'Part IX - Expenses'!$A4,SOFE!E:E) -> 0 | G4: =+SUMIF(SOFE!K:K,'Part IX - Expenses'!A4,SOFE!I:I) -> 0
A5: 2 | B5: Grants and other assistance to domestic individuals | C5: =SUM(D5:F5) -> 6682083 | D5: =+SUMIF(SOFE!$J:$J,'Part IX - Expenses'!$A5,SOFE!E:E) -> 6682083 | G5: =+SUMIF(SOFE!K:K,'Part IX - Expenses'!A5,SOFE!I:I) -> 2346370
A6: 3 | B6: Grants and other assistance foreign organizations, foreign governments and foreign individuals | C6: =SUM(D6:F6) -> 0 | D6: =+SUMIF(SOFE!$J:$J,'Part IX - Expenses'!$A6,SOFE!E:E) -> 0 | G6: =+SUMIF(SOFE!K:K,'Part IX - Expenses'!A6,SOFE!I:I) -> 0
A7: 4 | B7: Benefits paid to or for members | C7: =SUM(D7:F7) -> 0 | D7: =+SUMIF(SOFE!$J:$J,'Part IX - Expenses'!$A7,SOFE!E:E) -> 0 | G7: =+SUMIF(SOFE!K:K,'Part IX - Expenses'!A7,SOFE!I:I) -> 0
A8: 5 | B8: Compensation of Current officers, directors, trustees and key employees | C8: =SUM(D8:F8) -> 222753.79 | D8: =+SUMIF(SOFE!$J:$J,'Part IX - Expenses'!$A8,SOFE!E:E) -> 186012.93 | E8: =+SUMIF(SOFE!$J:$J,'Part IX - Expenses'!$A8,SOFE!F:F) -> 24663.458 | F8: =+SUMIF(SOFE!$J:$J,'Part IX - Expenses'!$A8,SOFE!G:G) -> 12077.404 | G8: =+SUMIF(SOFE!K:K,'Part IX - Expenses'!A8,SOFE!I:I) -> 330716
A9: 6 | B9: Compensations not included above to disqualified persons | C9: =SUM(D9:F9) -> 0 | D9: =+SUMIF(SOFE!$J:$J,'Part IX - Expenses'!$A9,SOFE!E:E) -> 0 | E9: =+SUMIF(SOFE!$J:$J,'Part IX - Expenses'!$A9,SOFE!F:F) -> 0 | F9: =+SUMIF(SOFE!$J:$J,'Part IX - Expenses'!$A9,SOFE!G:G) -> 0 | G9: =+SUMIF(SOFE!K:K,'Part IX - Expenses'!A9,SOFE!I:I) -> 0
A10: 7 | B10: Other Salaries and wages | C10: =SUM(D10:F10) -> 3192052.2 | D10: =+SUMIF(SOFE!$J:$J,'Part IX - Expenses'!$A10,SOFE!E:E) -> 2669445.2 | E10: =+SUMIF(SOFE!$J:$J,'Part IX - Expenses'!$A10,SOFE!F:F) -> 332455.69 | F10: =+SUMIF(SOFE!$J:$J,'Part IX - Expenses'!$A10,SOFE!G:G) -> 190151.27 | G10: =+SUMIF(SOFE!K:K,'Part IX - Expenses'!A10,SOFE!I:I) -> 2245736
A11: 8 | B11: Pension plam accruals & contributions (incl. 401(k) and 403(b) employer contr.) | C11: =SUM(D11:F11) -> 83460.25 | D11: =+SUMIF(SOFE!$J:$J,'Part IX - Expenses'!$A11,SOFE!E:E) -> 69453.697 | E11: =+SUMIF(SOFE!$J:$J,'Part IX - Expenses'!$A11,SOFE!F:F) -> 12373.591 | F11: =+SUMIF(SOFE!$J:$J,'Part IX - Expenses'!$A11,SOFE!G:G) -> 1632.9621 | G11: =+SUMIF(SOFE!K:K,'Part IX - Expenses'!A11,SOFE!I:I) -> 15873
A12: 9 | B12: Other Employee Benefits | C12: =SUM(D12:F12) -> 430582.8 | D12: =+SUMIF(SOFE!$J:$J,'Part IX - Expenses'!$A12,SOFE!E:E) -> 356024.94 | E12: =+SUMIF(SOFE!$J:$J,'Part IX - Expenses'!$A12,SOFE!F:F) -> 63164.242 | F12: =+SUMIF(SOFE!$J:$J,'Part IX - Expenses'!$A12,SOFE!G:G) -> 11393.617 | G12: =+SUMIF(SOFE!K:K,'Part IX - Expenses'!A12,SOFE!I:I) -> 225403
A13: 10 | B13: Payroll taxes | C13: =SUM(D13:F13) -> 272241 | D13: =+SUMIF(SOFE!$J:$J,'Part IX - Expenses'!$A13,SOFE!E:E) -> 252343 | E13: =+SUMIF(SOFE!$J:$J,'Part IX - Expenses'!$A13,SOFE!F:F) -> 12636 | F13: =+SUMIF(SOFE!$J:$J,'Part IX - Expenses'!$A13,SOFE!G:G) -> 7262 | G13: =+SUMIF(SOFE!K:K,'Part IX - Expenses'!A13,SOFE!I:I) -> 197666
A14: 11a | B14: Management | C14: =SUM(D14:F14) -> 0 | D14: =+SUMIF(SOFE!$J:$J,'Part IX - Expenses'!$A14,SOFE!E:E) -> 0 | E14: =+SUMIF(SOFE!$J:$J,'Part IX - Expenses'!$A14,SOFE!F:F) -> 0 | F14: =+SUMIF(SOFE!$J:$J,'Part IX - Expenses'!$A14,SOFE!G:G) -> 0 | G14: =+SUMIF(SOFE!K:K,'Part IX - Expenses'!A14,SOFE!I:I) -> 0
A15: 11b | B15: Legal | C15: =SUM(D15:F15) -> 64263 | D15: =+SUMIF(SOFE!$J:$J,'Part IX - Expenses'!$A15,SOFE!E:E) -> 60483 | E15: =+SUMIF(SOFE!$J:$J,'Part IX - Expenses'!$A15,SOFE!F:F) -> 3780 | F15: =+SUMIF(SOFE!$J:$J,'Part IX - Expenses'!$A15,SOFE!G:G) -> 0 | G15: =+SUMIF(SOFE!K:K,'Part IX - Expenses'!A15,SOFE!I:I) -> 29969.5
A16: 11c | B16: Accounting | C16: =SUM(D16:F16) -> 307745 | D16: =+SUMIF(SOFE!$J:$J,'Part IX - Expenses'!$A16,SOFE!E:E) -> 9990.3298 | E16: =+SUMIF(SOFE!$J:$J,'Part IX - Expenses'!$A16,SOFE!F:F) -> 287545.31 | F16: =+SUMIF(SOFE!$J:$J,'Part IX - Expenses'!$A16,SOFE!G:G) -> 10209.357 | G16: =+SUMIF(SOFE!K:K,'Part IX - Expenses'!A16,SOFE!I:I) -> 150800
A17: 11d | B17: Lobbying | C17: =SUM(D17:F17) -> 0 | D17: =+SUMIF(SOFE!$J:$J,'Part IX - Expenses'!$A17,SOFE!E:E) -> 0 | E17: =+SUMIF(SOFE!$J:$J,'Part IX - Expenses'!$A17,SOFE!F:F) -> 0 | F17: =+SUMIF(SOFE!$J:$J,'Part IX - Expenses'!$A17,SOFE!G:G) -> 0 | G17: =+SUMIF(SOFE!K:K,'Part IX - Expenses'!A17,SOFE!I:I) -> 0
A18: 11e | B18: Professional Fundraising services | C18: =SUM(D18:F18) -> 0 | F18: =+SUMIF(SOFE!$J:$J,'Part IX - Expenses'!$A18,SOFE!G:G) -> 0 | G18: =+SUMIF(SOFE!K:K,'Part IX - Expenses'!A18,SOFE!I:I) -> 0
A19: 11f | B19: Investment Management Fees | C19: =SUM(D19:F19) -> 2167 | D19: =+SUMIF(SOFE!$J:$J,'Part IX - Expenses'!$A19,SOFE!E:E) -> 77.953685 | E19: =+SUMIF(SOFE!$J:$J,'Part IX - Expenses'!$A19,SOFE!F:F) -> 1187.023 | F19: =+SUMIF(SOFE!$J:$J,'Part IX - Expenses'!$A19,SOFE!G:G) -> 902.02329 | G19: =+SUMIF(SOFE!K:K,'Part IX - Expenses'!A19,SOFE!I:I) -> 2070
A20: 11g | B20: Other Fees for service | C20: =SUM(D20:F20) -> 125143 | D20: =+SUMIF(SOFE!$J:$J,'Part IX - Expenses'!$A20,SOFE!E:E) -> 35498.67 | E20: =+SUMIF(SOFE!$J:$J,'Part IX - Expenses'!$A20,SOFE!F:F) -> 67171.687 | F20: =+SUMIF(SOFE!$J:$J,'Part IX - Expenses'!$A20,SOFE!G:G) -> 22472.643 | G20: =+SUMIF(SOFE!K:K,'Part IX - Expenses'!A20,SOFE!I:I) -> 194682.58
A21: 12 | B21: Advertising and promotion | C21: =SUM(D21:F21) -> 2909 | D21: =+SUMIF(SOFE!$J:$J,'Part IX - Expenses'!$A21,SOFE!E:E) -> 1650 | E21: =+SUMIF(SOFE!$J:$J,'Part IX - Expenses'!$A21,SOFE!F:F) -> 1074 | F21: =+SUMIF(SOFE!$J:$J,'Part IX - Expenses'!$A21,SOFE!G:G) -> 185 | G21: =+SUMIF(SOFE!K:K,'Part IX - Expenses'!A21,SOFE!I:I) -> 5810
A22: 13 | B22: Office Expenses | C22: =SUM(D22:F22) -> 250596 | D22: =+SUMIF(SOFE!$J:$J,'Part IX - Expenses'!$A22,SOFE!E:E) -> 135715.05 | E22: =+SUMIF(SOFE!$J:$J,'Part IX - Expenses'!$A22,SOFE!F:F) -> 92446.977 | F22: =+SUMIF(SOFE!$J:$J,'Part IX - Expenses'!$A22,SOFE!G:G) -> 22433.977 | G22: =+SUMIF(SOFE!K:K,'Part IX - Expenses'!A22,SOFE!I:I) -> 137506
A23: 14 | B23: Information technology | C23: =SUM(D23:F23) -> 104996 | D23: =+SUMIF(SOFE!$J:$J,'Part IX - Expenses'!$A23,SOFE!E:E) -> 46484 | E23: =+SUMIF(SOFE!$J:$J,'Part IX - Expenses'!$A23,SOFE!F:F) -> 56404 | F23: =+SUMIF(SOFE!$J:$J,'Part IX - Expenses'!$A23,SOFE!G:G) -> 2108 | G23: =+SUMIF(SOFE!K:K,'Part IX - Expenses'!A23,SOFE!I:I) -> 37237
A24: 15 | B24: Royalties | C24: =SUM(D24:F24) -> 0 | D24: =+SUMIF(SOFE!$J:$J,'Part IX - Expenses'!$A24,SOFE!E:E) -> 0 | E24: =+SUMIF(SOFE!$J:$J,'Part IX - Expenses'!$A24,SOFE!F:F) -> 0 | F24: =+SUMIF(SOFE!$J:$J,'Part IX - Expenses'!$A24,SOFE!G:G) -> 0 | G24: =+SUMIF(SOFE!K:K,'Part IX - Expenses'!A24,SOFE!I:I) -> 0
A25: 16 | B25: Occupancy | C25: =SUM(D25:F25) -> 84206 | D25: =+SUMIF(SOFE!$J:$J,'Part IX - Expenses'!$A25,SOFE!E:E) -> 84666 | E25: =+SUMIF(SOFE!$J:$J,'Part IX - Expenses'!$A25,SOFE!F:F) -> -2758 | F25: =+SUMIF(SOFE!$J:$J,'Part IX - Expenses'!$A25,SOFE!G:G) -> 2298 | G25: =+SUMIF(SOFE!K:K,'Part IX - Expenses'!A25,SOFE!I:I) -> 108136
A26: 17 | B26: Travel | C26: =SUM(D26:F26) -> 15877.14 | D26: =+SUMIF(SOFE!$J:$J,'Part IX - Expenses'!$A26,SOFE!E:E) -> 15531 | E26: =+SUMIF(SOFE!$J:$J,'Part IX - Expenses'!$A26,SOFE!F:F) -> 292.14 | F26: =+SUMIF(SOFE!$J:$J,'Part IX - Expenses'!$A26,SOFE!G:G) -> 54 | G26: =+SUMIF(SOFE!K:K,'Part IX - Expenses'!A26,SOFE!I:I) -> 8526.18
A27: 18 | B27: Travel/ Entertainment for any federal, state, or local public officials | C27: =SUM(D27:F27) -> 0 | D27: =+SUMIF(SOFE!$J:$J,'Part IX - Expenses'!$A27,SOFE!E:E) -> 0 | E27: =+SUMIF(SOFE!$J:$J,'Part IX - Expenses'!$A27,SOFE!F:F) -> 0 | F27: =+SUMIF(SOFE!$J:$J,'Part IX - Expenses'!$A27,SOFE!G:G) -> 0 | G27: =+SUMIF(SOFE!K:K,'Part IX - Expenses'!A27,SOFE!I:I) -> 0
A28: 19 | B28: Conferences, conventions and meetings | C28: =SUM(D28:F28) -> 30788.27 | D28: =+SUMIF(SOFE!$J:$J,'Part IX - Expenses'!$A28,SOFE!E:E) -> 8554.1 | E28: =+SUMIF(SOFE!$J:$J,'Part IX - Expenses'!$A28,SOFE!F:F) -> 12479.17 | F28: =+SUMIF(SOFE!$J:$J,'Part IX - Expenses'!$A28,SOFE!G:G) -> 9755 | G28: =+SUMIF(SOFE!K:K,'Part IX - Expenses'!A28,SOFE!I:I) -> 11590.21
A29: 20 | B29: Interest | C29: =SUM(D29:F29) -> 16850 | D29: =+SUMIF(SOFE!$J:$J,'Part IX - Expenses'!$A29,SOFE!E:E) -> 15014 | E29: =+SUMIF(SOFE!$J:$J,'Part IX - Expenses'!$A29,SOFE!F:F) -> 1391 | F29: =+SUMIF(SOFE!$J:$J,'Part IX - Expenses'!$A29,SOFE!G:G) -> 445 | G29: =+SUMIF(SOFE!K:K,'Part IX - Expenses'!A29,SOFE!I:I) -> 2345
A30: 21 | B30: Payments to affiliates | C30: =SUM(D30:F30) -> 0 | D30: =+SUMIF(SOFE!$J:$J,'Part IX - Expenses'!$A30,SOFE!E:E) -> 0 | E30: =+SUMIF(SOFE!$J:$J,'Part IX - Expenses'!$A30,SOFE!F:F) -> 0 | F30: =+SUMIF(SOFE!$J:$J,'Part IX - Expenses'!$A30,SOFE!G:G) -> 0 | G30: =+SUMIF(SOFE!K:K,'Part IX - Expenses'!A30,SOFE!I:I) -> 0
A31: 22 | B31: Depreciation, depletion and amortization | C31: =SUM(D31:F31) -> 183313 | D31: =+SUMIF(SOFE!$J:$J,'Part IX - Expenses'!$A31,SOFE!E:E) -> 160413 | E31: =+SUMIF(SOFE!$J:$J,'Part IX - Expenses'!$A31,SOFE!F:F) -> 18147 | F31: =+SUMIF(SOFE!$J:$J,'Part IX - Expenses'!$A31,SOFE!G:G) -> 4753 | G31: =+SUMIF(SOFE!K:K,'Part IX - Expenses'!A31,SOFE!I:I) -> 29684
A32: 23 | B32: Insurance | C32: =SUM(D32:F32) -> 9450 | D32: =+SUMIF(SOFE!$J:$J,'Part IX - Expenses'!$A32,SOFE!E:E) -> 7992 | E32: =+SUMIF(SOFE!$J:$J,'Part IX - Expenses'!$A32,SOFE!F:F) -> 882 | F32: =+SUMIF(SOFE!$J:$J,'Part IX - Expenses'!$A32,SOFE!G:G) -> 576 | G32: =+SUMIF(SOFE!K:K,'Part IX - Expenses'!A32,SOFE!I:I) -> 8374
A33: 24 | B33: Other Expenses. Itemize expenses not covered above (List Misc. expenses on 24e and not on lines 24a-d. If line 24e amount exceeds 10% of line 25, column(A) amouont, list line 24e expenses on schedule O) | G33: =+SUMIF(SOFE!K:K,'Part IX - Expenses'!A33,SOFE!I:I) -> 0
A34: 24a | B34: =IFERROR(INDEX(SOFE!$A:$J,MATCH('Part IX - Expenses'!A34,SOFE!$J:$J,0),1),"") -> Other Grants | C34: =SUM(D34:F34) -> 1586 | D34: =+SUMIF(SOFE!$J:$J,'Part IX - Expenses'!$A34,SOFE!E:E) -> 0 | E34: =+SUMIF(SOFE!$J:$J,'Part IX - Expenses'!$A34,SOFE!F:F) -> 1586 | F34: =+SUMIF(SOFE!$J:$J,'Part IX - Expenses'!$A34,SOFE!G:G) -> 0 | G34: =+SUMIF(SOFE!K:K,'Part IX - Expenses'!A34,SOFE!I:I) -> 66193
A35: 24b | B35: =IFERROR(INDEX(SOFE!$A:$J,MATCH('Part IX - Expenses'!A35,SOFE!$J:$J,0),1),"") | C35: =SUM(D35:F35) -> 0 | D35: =+SUMIF(SOFE!$J:$J,'Part IX - Expenses'!$A35,SOFE!E:E) -> 0 | E35: =+SUMIF(SOFE!$J:$J,'Part IX - Expenses'!$A35,SOFE!F:F) -> 0 | F35: =+SUMIF(SOFE!$J:$J,'Part IX - Expenses'!$A35,SOFE!G:G) -> 0 | G35: =+SUMIF(SOFE!K:K,'Part IX - Expenses'!A35,SOFE!I:I) -> 0
A36: 24c | B36: =IFERROR(INDEX(SOFE!$A:$J,MATCH('Part IX - Expenses'!A36,SOFE!$J:$J,0),1),"") | C36: =SUM(D36:F36) -> 0 | D36: =+SUMIF(SOFE!$J:$J,'Part IX - Expenses'!$A36,SOFE!E:E) -> 0 | E36: =+SUMIF(SOFE!$J:$J,'Part IX - Expenses'!$A36,SOFE!F:F) -> 0 | F36: =+SUMIF(SOFE!$J:$J,'Part IX - Expenses'!$A36,SOFE!G:G) -> 0 | G36: =+SUMIF(SOFE!K:K,'Part IX - Expenses'!A36,SOFE!I:I) -> 0
A37: 24d | B37: =IFERROR(INDEX(SOFE!$A:$J,MATCH('Part IX - Expenses'!A37,SOFE!$J:$J,0),1),"") | C37: =SUM(D37:F37) -> 0 | D37: =+SUMIF(SOFE!$J:$J,'Part IX - Expenses'!$A37,SOFE!E:E) -> 0 | E37: =+SUMIF(SOFE!$J:$J,'Part IX - Expenses'!$A37,SOFE!F:F) -> 0 | F37: =+SUMIF(SOFE!$J:$J,'Part IX - Expenses'!$A37,SOFE!G:G) -> 0 | G37: =+SUMIF(SOFE!K:K,'Part IX - Expenses'!A37,SOFE!I:I) -> 0
A38: 24e | B38: All Other | C38: =SUM(D38:F38) -> 0 | D38: =+SUMIF(SOFE!$J:$J,'Part IX - Expenses'!$A38,SOFE!E:E) -> 0 | E38: =+SUMIF(SOFE!$J:$J,'Part IX - Expenses'!$A38,SOFE!F:F) -> 0 | F38: =+SUMIF(SOFE!$J:$J,'Part IX - Expenses'!$A38,SOFE!G:G) -> 0 | G38: =+SUMIF(SOFE!K:K,'Part IX - Expenses'!A38,SOFE!I:I) -> 0
A39: 25 | B39: Total Functional Expenses | C39: =SUM(C4:C38) -> 12083062 | D39: =SUM(D4:D38) -> 10797432 | E39: =SUM(E4:E38) -> 986921.29 | F39: =SUM(F4:F38) -> 298709.25 | G39: =SUM(G4:G38) -> 6154687.5

Sheet Part X - Balance Sheet
A2: Part X - Balance Sheet
B3: Line | C3: Particulars | D3: Beginning of year | E3: End of Year
A4: Assets | B4: 1 | C4: Cash - Non Interest Bearing | D4: =+SUMIF(SOFP!$E:$E,'Part X - Balance Sheet'!B4,SOFP!$C:$C) -> 809592.71 | E4: =+SUMIF(SOFP!$F:$F,'Part X - Balance Sheet'!B4,SOFP!$D:$D) -> 1118499
B5: 2 | C5: Saving and Temporary Cash Investments | D5: =+SUMIF(SOFP!$E:$E,'Part X - Balance Sheet'!B5,SOFP!$C:$C) -> 2070590.3 | E5: =+SUMIF(SOFP!$F:$F,'Part X - Balance Sheet'!B5,SOFP!$D:$D) -> 0
B6: 3 | C6: Pledges and grants receivable, net | D6: =+SUMIF(SOFP!$E:$E,'Part X - Balance Sheet'!B6,SOFP!$C:$C) -> 1000625 | E6: =+SUMIF(SOFP!$F:$F,'Part X - Balance Sheet'!B6,SOFP!$D:$D) -> 2599240
B7: 4 | C7: Accounts Receivable, net | D7: =+SUMIF(SOFP!$E:$E,'Part X - Balance Sheet'!B7,SOFP!$C:$C) -> 3706 | E7: =+SUMIF(SOFP!$F:$F,'Part X - Balance Sheet'!B7,SOFP!$D:$D) -> 0
B8: 5 | C8: Receivables from Current and Former Officers, Directors, Trustees, Key Employees, creator or founder, substantial contributor, or 35% controlled entity or family member of any of these persons (Sch. L) | D8: =+SUMIF(SOFP!$E:$E,'Part X - Balance Sheet'!B8,SOFP!$C:$C) -> 0 | E8: =+SUMIF(SOFP!$F:$F,'Part X - Balance Sheet'!B8,SOFP!$D:$D) -> 0
B9: 6 | C9: Receivables from other Disqulified Persons | D9: =+SUMIF(SOFP!$E:$E,'Part X - Balance Sheet'!B9,SOFP!$C:$C) -> 0 | E9: =+SUMIF(SOFP!$F:$F,'Part X - Balance Sheet'!B9,SOFP!$D:$D) -> 0
B10: 7 | C10: Notes and Loans Receivable, net | D10: =+SUMIF(SOFP!$E:$E,'Part X - Balance Sheet'!B10,SOFP!$C:$C) -> 0 | E10: =+SUMIF(SOFP!$F:$F,'Part X - Balance Sheet'!B10,SOFP!$D:$D) -> 0
B11: 8 | C11: Inventories for sale or use | D11: =+SUMIF(SOFP!$E:$E,'Part X - Balance Sheet'!B11,SOFP!$C:$C) -> 3210 | E11: =+SUMIF(SOFP!$F:$F,'Part X - Balance Sheet'!B11,SOFP!$D:$D) -> 2361
B12: 9 | C12: Prepaid Expenses and Deferred Charges | D12: =+SUMIF(SOFP!$E:$E,'Part X - Balance Sheet'!B12,SOFP!$C:$C) -> 63626 | E12: =+SUMIF(SOFP!$F:$F,'Part X - Balance Sheet'!B12,SOFP!$D:$D) -> 45259
B13: 10a | C13: Land, Buildings and Equipment | D13: =+SUMIF(SOFP!$E:$E,'Part X - Balance Sheet'!B13,SOFP!$C:$C) -> 40391 | E13: =+SUMIF(SOFP!$F:$F,'Part X - Balance Sheet'!B13,SOFP!$D:$D) -> 40391
B14: 10b | C14: Less: Accumulated Depriciation | D14: =+SUMIF(SOFP!$E:$E,'Part X - Balance Sheet'!B14,SOFP!$C:$C) -> 30667 | E14: =+SUMIF(SOFP!$F:$F,'Part X - Balance Sheet'!B14,SOFP!$D:$D) -> 33952
C15: Land, Buildings and Equipment - Net | D15: =+D13-D14 -> 9724 | E15: =+E13-E14 -> 6439
B16: 11 | C16: Investments - Publicly Traded Securities | D16: =+SUMIF(SOFP!$E:$E,'Part X - Balance Sheet'!B16,SOFP!$C:$C) -> 0 | E16: =+SUMIF(SOFP!$F:$F,'Part X - Balance Sheet'!B16,SOFP!$D:$D) -> 0
B17: 12 | C17: Investments - OtherSecurities | D17: =+SUMIF(SOFP!$E:$E,'Part X - Balance Sheet'!B17,SOFP!$C:$C) -> 412460 | E17: =+SUMIF(SOFP!$F:$F,'Part X - Balance Sheet'!B17,SOFP!$D:$D) -> 975077
B18: 13 | C18: Investments - Program related | D18: =+SUMIF(SOFP!$E:$E,'Part X - Balance Sheet'!B18,SOFP!$C:$C) -> 0 | E18: =+SUMIF(SOFP!$F:$F,'Part X - Balance Sheet'!B18,SOFP!$D:$D) -> 0
B19: 14 | C19: Intangible Assets | D19: =+SUMIF(SOFP!$E:$E,'Part X - Balance Sheet'!B19,SOFP!$C:$C) -> 342890 | E19: =+SUMIF(SOFP!$F:$F,'Part X - Balance Sheet'!B19,SOFP!$D:$D) -> 556564
B20: 15 | C20: Other assets | D20: =+SUMIF(SOFP!$E:$E,'Part X - Balance Sheet'!B20,SOFP!$C:$C) -> 29175 | E20: =+SUMIF(SOFP!$F:$F,'Part X - Balance Sheet'!B20,SOFP!$D:$D) -> 29175
B21: 16 | C21: Total Assets | D21: =SUM(D4:D12,D15:D20) -> 4745599 | E21: =SUM(E4:E12,E15:E20) -> 5332614
A22: Liabilities | B22: 17 | C22: Accounts Payable and Accrued Expenses | D22: =+SUMIF(SOFP!$E:$E,'Part X - Balance Sheet'!B22,SOFP!$C:$C) -> 361056 | E22: =+SUMIF(SOFP!$F:$F,'Part X - Balance Sheet'!B22,SOFP!$D:$D) -> 1278580
B23: 18 | C23: Grants Payable | D23: =+SUMIF(SOFP!$E:$E,'Part X - Balance Sheet'!B23,SOFP!$C:$C) -> 0 | E23: =+SUMIF(SOFP!$F:$F,'Part X - Balance Sheet'!B23,SOFP!$D:$D) -> 0
B24: 19 | C24: Deferred Revenue | D24: =+SUMIF(SOFP!$E:$E,'Part X - Balance Sheet'!B24,SOFP!$C:$C) -> 0 | E24: =+SUMIF(SOFP!$F:$F,'Part X - Balance Sheet'!B24,SOFP!$D:$D) -> 1054229
B25: 20 | C25: Tax-Exempt Bond Liabilities | D25: =+SUMIF(SOFP!$E:$E,'Part X - Balance Sheet'!B25,SOFP!$C:$C) -> 0 | E25: =+SUMIF(SOFP!$F:$F,'Part X - Balance Sheet'!B25,SOFP!$D:$D) -> 0
B26: 21 | C26: Escrow or custodial account liability | D26: =+SUMIF(SOFP!$E:$E,'Part X - Balance Sheet'!B26,SOFP!$C:$C) -> 0 | E26: =+SUMIF(SOFP!$F:$F,'Part X - Balance Sheet'!B26,SOFP!$D:$D) -> 0
B27: 22 | C27: Payables to current or former Officers, Directors, Trustees and Key Employees, Highest compensated employees and disqualified persons | D27: =+SUMIF(SOFP!$E:$E,'Part X - Balance Sheet'!B27,SOFP!$C:$C) -> 0 | E27: =+SUMIF(SOFP!$F:$F,'Part X - Balance Sheet'!B27,SOFP!$D:$D) -> 0
B28: 23 | C28: Secured Mortgages and Notes Payable to unrelated third parties | D28: =+SUMIF(SOFP!$E:$E,'Part X - Balance Sheet'!B28,SOFP!$C:$C) -> 0 | E28: =+SUMIF(SOFP!$F:$F,'Part X - Balance Sheet'!B28,SOFP!$D:$D) -> 0
B29: 24 | C29: Unsecured notes and loans payable to unrelated third parties | D29: =+SUMIF(SOFP!$E:$E,'Part X - Balance Sheet'!B29,SOFP!$C:$C) -> 0 | E29: =+SUMIF(SOFP!$F:$F,'Part X - Balance Sheet'!B29,SOFP!$D:$D) -> 0
B30: 25 | C30: Other Liabilities (incl. federal income tax, payables to related thord parties and other liabilities not included above) | D30: =+SUMIF(SOFP!$E:$E,'Part X - Balance Sheet'!B30,SOFP!$C:$C) -> 342890 | E30: =+SUMIF(SOFP!$F:$F,'Part X - Balance Sheet'!B30,SOFP!$D:$D) -> 559692
B31: 26 | C31: Total Liabilities | D31: =+SUM(D22:D30) -> 703946 | E31: =+SUM(E22:E30) -> 2892501
A32: Net Assets or fund balances | C32: Organizations that follow FASB ASC 958, complete lines 27, 28, 32, and 33
B33: 27 | C33: Net assets without donor restrictions | D33: =+SUMIF(SOFP!$E:$E,'Part X - Balance Sheet'!B33,SOFP!$C:$C) -> 460416 | E33: =+SUMIF(SOFP!$F:$F,'Part X - Balance Sheet'!B33,SOFP!$D:$D) -> 103743
B34: 28 | C34: Net assets with donor restrictions | D34: =+SUMIF(SOFP!$E:$E,'Part X - Balance Sheet'!B34,SOFP!$C:$C) -> 3581237 | E34: =+SUMIF(SOFP!$F:$F,'Part X - Balance Sheet'!B34,SOFP!$D:$D) -> 2336370
C35: Organizations that do not follow FASB ASC 958, complete lines 29 through 33.
B36: 29 | C36: Capital Stock or trust principal or current funds | D36: =+SUMIF(SOFP!$E:$E,'Part X - Balance Sheet'!B36,SOFP!$C:$C) -> 0 | E36: =+SUMIF(SOFP!$F:$F,'Part X - Balance Sheet'!B36,SOFP!$D:$D) -> 0
B37: 30 | C37: Paid in or Capital Surplus, or land, building, or equipment funds | D37: =+SUMIF(SOFP!$E:$E,'Part X - Balance Sheet'!B37,SOFP!$C:$C) -> 0 | E37: =+SUMIF(SOFP!$F:$F,'Part X - Balance Sheet'!B37,SOFP!$D:$D) -> 0
B38: 31 | C38: Retained Earnings, endowment, accumulated income, or other funds | D38: =+SUMIF(SOFP!$E:$E,'Part X - Balance Sheet'!B38,SOFP!$C:$C) -> 0 | E38: =+SUMIF(SOFP!$F:$F,'Part X - Balance Sheet'!B38,SOFP!$D:$D) -> 0
B39: 32 | C39: Total Net Assets or Fund Balances | D39: =SUM(D33:D38) -> 4041653 | E39: =SUM(E33:E38) -> 2440113
B40: 33 | C40: Total Liabilities and Net Assets or Fund Balances | D40: =D31+D39 -> 4745599 | E40: =E31+E39 -> 5332614
D42: =+D21-D40 -> 0 | E42: =+E21-E40 -> 0 | F42: Check

Sheet Part XI - Net Asset Recon.
A2: Schedule D, Part XI - Recon. Of Revenue per AFS with Form 990
A3: Particulars | B3: Amount
A4: Total Revenue per AFS | B4: =+B14+B10-B13 -> 10524140
A6: a. New Unrealized Gains (losses) on Investments | B6: =+SUMIF(SOR!F:F,'Part XI - Net Asset Recon.'!C6,SOR!B:B) -> 30922 | C6: Adj-UG
A7: b. Donated Services and use of facilities | B7: =+SUMIF(SOR!F:F,'Part XI - Net Asset Recon.'!C7,SOR!B:B) -> 34712 | C7: Adj-DS
A8: c. Recoveries of Prior year Grants | B8: =+SUMIF(SOR!F:F,'Part XI - Net Asset Recon.'!C8,SOR!B:B) -> 0 | C8: Adj-PY
A9: d. Other | B9: =+SUMIF(SOR!F:F,'Part XI - Net Asset Recon.'!C9,SOR!B:B) -> 0 | C9: Adj-Other
B10: =+SUM(B6:B9) -> 65634
A11: a. Investment Expenses not included on Form 990, Part VIII, line 7b | B11: =+SUMIF(SOR!F:F,'Part XI - Net Asset Recon.'!C11,SOR!B:B) -> 0 | C11: Adj-IE
A12: b. Other | B12: 0
B13: =+SUM(B11:B12) -> 0
A14: Total Revenue (Part VIII , Line 12) | B14: =+'Part VIII - Revenue'!E48 -> 10458506
A17: Schedule D, Part XII - Recon. Of Expenses per AFS with Form 990
A18: Particulars | B18: Amount
A19: Total Expenses as per AFS | B19: =+B29+B25-B28 -> 12125680
A21: a. Donated Services and use of facilities | B21: =+SUMIF(SOFE!J:J,'Part XI - Net Asset Recon.'!C21,SOFE!H:H) -> 34712 | C21: Adj-DS
A22: b. PY Adjustments | B22: =+SUMIF(SOFE!J:J,'Part XI - Net Asset Recon.'!C22,SOFE!H:H) -> 0 | C22: Adj-PY
A23: c. Other Losses | B23: =+SUMIF(SOFE!J:J,'Part XI - Net Asset Recon.'!C23,SOFE!H:H) -> 0 | C23: Adj-Other Loss
A24: d. Other | B24: =+SUMIF(SOFE!J:J,'Part XI - Net Asset Recon.'!C24,SOFE!H:H) -> 7906 | C24: Adj-Other
B25: =+SUM(B21:B24) -> 42618
A26: a. Investment Expenses not included on Form 990, Part VIII, line 7b | B26: =+SUMIF(SOFE!J:J,'Part XI - Net Asset Recon.'!C26,SOFE!H:H) -> 0 | C26: Adj-IE
A27: b. Other | B27: 0
B28: =+SUM(B26:B27) -> 0
A29: Total Expenses (Part IX , Line 25) | B29: =+'Part IX - Expenses'!C39 -> 12083062
A33: Part XI - Reconciliation of Net Assets
A34: Particulars | B34: Amount
A35: 1. Total Revenue (must equal Part VIII, Column (A), line 12) | B35: =+'Part VIII - Revenue'!E48 -> 10458506
A36: 2. Total expenses (must equal Part IX, column (A), line 25) | B36: =+'Part IX - Expenses'!C39 -> 12083062
A37: 3. Revenue less expenses. Subtract line 2 from line 1 | B37: =B35-B36 -> -1624556.4
A38: 4. Net assets or fund balances at beginning of year (must equal Part X, line 32, column (A)) | B38: =+'Part X - Balance Sheet'!D39 -> 4041653
A39: 5. Net unrealized gains (losses) on investments | B39: =+B6 -> 30922 | C39: Adj-UG
A40: 6. Donated services and use of facilities | B40: =+IF(B7=B21,B7-B21,B7) -> 0 | C40: Adj-DS
A41: 7. Investment expenses | B41: 0 | C41: Adj-IE
A42: 8. Prior period adjustments | B42: =+IF(B8=B22,B8-B22,B8) -> 0 | C42: Adj-PY
A43: 9. Other changes in net assets or fund balances | B43: =-+IF(B9=B24,B9,SUM(B9+B24)) -> -7906
A44: 10. Net assets or fund balances at end of year. Combine lines 3 through 9 (must equal Part X, line 32, column (B)) | B44: =+SUM(B37:B43) -> 2440112.6
A46: Check | B46: =+B44-'Part X - Balance Sheet'!E39 -> -0.41

Sheet Queries

Sheet TB Mapping 
A3: Account | B3: Prelim | C3: Adj's | D3: Reclass | E3: Rep | F3: Annotation | G3: Rep 06/23 | H3: %Chg
A5: 1001 First Republic Bank | B5: 0 | C5: 0 | D5: 0 | E5: 0 | G5: 235234.64 | H5: -100
A6: 1002 FRB - ICS | B6: 0 | C6: 0 | D6: 0 | E6: 0 | G6: 1990834.7 | H6: -100
A7: 1003 Chase Bank | B7: 1104428 | C7: 0 | D7: 0 | E7: 1104428 | G7: 0 | H7: 0
A8: 1010 Bank of America | B8: 0 | C8: 0 | D8: 0 | E8: 0 | G8: 516436.08 | H8: -100
A9: 1020 BOA - Money Market | B9: 0 | C9: 0 | D9: 0 | E9: 0 | G9: 79755.62 | H9: -100
A10: 1070 Petty Cash | B10: 101 | C10: 0 | D10: 0 | E10: 101 | G10: 120.27 | H10: -16
A11: 1072 Petty Cash for Refugees | B11: 3375 | C11: 0 | D11: 0 | E11: 3375 | G11: 3800 | H11: -11
A12: 1080 PayPal | B12: 10595 | C12: 0 | D12: 0 | E12: 10595 | G12: 54001.73 | H12: -80
A13: 10000 Cash and Cash Equivalents | B13: 1118499 | C13: 0 | D13: 0 | E13: 1118499 | G13: 2880183 | H13: -61
A15: 1305 Investments:RBC | B15: 277185 | C15: 0 | D15: 0 | E15: 277185 | G15: 258295.07 | H15: 7
A16: 1306 Investments:JSV Investment | B16: 172808 | C16: 0 | D16: 0 | E16: 172808 | G16: 154165 | H16: 12
A17: 1308 RBC- Endowment | B17: 525084 | C17: 0 | D17: 0 | E17: 525084 | G17: 0 | H17: 0 | J17: =+E17-525261 -> -177
A18: 11000 Investment | B18: 975077 | C18: 0 | D18: 0 | E18: 975077 | G18: 412460.07 | H18: 136
A20: 1200 Accounts Receivable | B20: 615104 | C20: 0 | D20: 0 | E20: 615104 | G20: 869889.38 | H20: -29
A21: 12100 Accounts Receivable | B21: 615104 | C21: 0 | D21: 0 | E21: 615104 | G21: 869889.38 | H21: -29
A23: 1235 Grant Rev Not Billed | B23: 1726113 | C23: 0 | D23: 0 | E23: 1726113 | G23: 0 | H23: 0
A24: 12200 Grants Receivable | B24: 1726113 | C24: 0 | D24: 0 | E24: 1726113 | G24: 0 | H24: 0
A26: 1210 Allowance on Pledges Receivable | B26: -5249 | C26: -7906 | D26: 0 | E26: -13155 | G26: -5249 | H26: 151
A27: 1215 Pledges Receivable | B27: 271178 | C27: 0 | D27: 0 | E27: 271178 | G27: 135985.42 | H27: 99
A28: 12500 Pledges Receivable | B28: 265929 | C28: -7906 | D28: 0 | E28: 258023 | G28: 130736.42 | H28: 97
A30: 1301 Benefits Receivable | B30: 0 | C30: 0 | D30: 0 | E30: 0 | G30: 3705.87 | H30: -100
A31: 12700 Benefits Receivable | B31: 0 | C31: 0 | D31: 0 | E31: 0 | G31: 3705.87 | H31: -100
A33: 1303 Deposits | B33: 29175 | C33: 0 | D33: 0 | E33: 29175 | G33: 29174.76 | H33: 0
A34: 12800 Deposit | B34: 29175 | C34: 0 | D34: 0 | E34: 29175 | G34: 29174.76 | H34: 0
... A203: 57000 Bad Debts Expenses | B203: 0 | C203: 7906 | D203: 0 | E203: 7906 | G203: 23777.21 | H203: -67
B205: 1590507 | C205: 11034 | D205: 0 | E205: 1601541 | G205: -2275351.3 | H205: -170
A207: 45747
A208: 10:15 PM

Sheet Function Exp
I1: 1060 - Security Program | K1: 1000 - Admin - Other | M1: m | O1: 3100 - L'Dor V'Dor Society | Q1: 2020 - Moca Foundation | S1: 2000 - Fundraising - Other | U1: F | W1: 4102 - CA ACS | Y1: 4103 - CA AIRS | AA1: 4201 - GG | AC1: 4203 - Match | AE1: 4202 - WF | AG1: Total 4200 - Claims Conference | AI1: 4301 - Afghan | AK1: 4303 - County - Other | AM1: 4302 - Ukraine | AO1: 4300 - County of Santa Clara - Other | AQ1: Total 4300 - County of Santa Clara | AS1: 4400 - Health Navigator (RHPP) | AU1: 4501 - ERMA | AW1: 4505 - PC | AY1: 4506 - PC REA | BA1: 4507 - PC Sup | BC1: 4508 - PC Ukraine | BE1: 4503 - R&P | BG1: 4504 - R&P Addtl | BI1: R&P Afghan Refugees & SIV | BK1: 4500 - HIAS - Other | BM1: Total 4500 - HIAS | BO1: Total 4100 - Contract | BQ1: 7010 - Center for Aging - Rest | BS1: City of Fremont | BU1: 7030 - ECH | BW1: 7040 - EFRS | BY1: 7105 - EFSP | CA1: 7060 - Holocaust | CC1: 7070 - KAVOD | CE1: 7103 - Equipped To Learn | CG1: 7101 - Berkowitz Food Fund | CI1: 7102 - EAF | CK1: 7104 - General | CM1: Total 7100 - NOAH | CO1: Older Adult Mental Health | CQ1: 7300 - Ref Resettle & Housing | CS1: Total 7000 - Restricted | CU1: p
I2: (1000 - Admin) | K2: (1000 - Admin) | M2: Total 1000 - Admin | O2: (2000 - Fundraising) | Q2: (2000 - Fundraising) | S2: (2000 - Fundraising) | U2: Total 2000 - Fundraising | W2: (4100 - Contract) | Y2: (4100 - Contract) | AA2: (4200 - Claims Conference) | AC2: (4200 - Claims Conference) | AE2: (4200 - Claims Conference) | AG2: (4100 - Contract) | AI2: (4300 - County of Santa Clara) | AK2: (4300 - County of Santa Clara) | AM2: (4300 - County of Santa Clara) | AO2: (4300 - County of Santa Clara) | AQ2: (4100 - Contract) | AS2: (4100 - Contract) | AU2: (4500 - HIAS) | AW2: (4500 - HIAS) | AY2: (4500 - HIAS) | BA2: (4500 - HIAS) | BC2: (4500 - HIAS) | BE2: (4500 - HIAS) | BG2: (4500 - HIAS) | BI2: (4500 - HIAS) | BK2: (4500 - HIAS) | BM2: (4100 - Contract) | BO2: (4000 - Program) | BQ2: (7000 - Restricted) | BS2: (7000 - Restricted) | BU2: (7000 - Restricted) | BW2: (7000 - Restricted) | BY2: (7000 - Restricted) | CA2: (7000 - Restricted) | CC2: (7000 - Restricted) | CE2: (7100 - NOAH) | CG2: (7100 - NOAH) | CI2: (7100 - NOAH) | CK2: (7100 - NOAH) | CM2: (7000 - Restricted) | CO2: (7000 - Restricted) | CQ2: (7000 - Restricted) | CS2: (4000 - Program) | CU2: Total 4000 - Program | CW2: Unclassified | CY2: TOTAL | DA2: Aging | DC2: Refugee
B3: Ordinary Income/Expense
D4: Income
E5: 4000 · Contracts | I5: 0 | K5: 0 | M5: =ROUND(SUM(I5:K5),5) -> 0 | O5: 0 | Q5: 0 | S5: 0 | U5: =ROUND(SUM(O5:S5),5) -> 0 | W5: 185471.06 | Y5: 133162.81 | AA5: 4727288.3 | AC5: 14867 | AE5: 7358.96 | AG5: =ROUND(SUM(AA5:AE5),5) -> 4749514.3 | AI5: 266334.4 | AK5: 244176.82 | AM5: 335392.94 | AO5: 809780.49 | AQ5: =ROUND(SUM(AI5:AO5),5) -> 1655684.6 | AS5: 93881.38 | AU5: 122111.69 | AW5: 105105.92 | AY5: 84203.49 | BA5: 360224.52 | BC5: 96751.88 | BE5: 586987.54 | BG5: 6943.39 | BI5: 214063.67 | BK5: 0 | BM5: =ROUND(SUM(AU5:BK5),5) -> 1576392.1 | BO5: =ROUND(SUM(W5:Y5)+AG5+SUM(AQ5:AS5)+BM5,5) -> 8394106.3 | BQ5: 0 | BS5: 0 | BU5: 0 | BW5: 0 | BY5: 0 | CA5: 0 | CC5: 0 | CE5: 0 | CG5: 0 | CI5: 0 | CK5: 0 | CM5: =ROUND(SUM(CE5:CK5),5) -> 0 | CO5: 0 | CQ5: 0 | CS5: =ROUND(SUM(BQ5:CC5)+SUM(CM5:CQ5),5) -> 0 | CU5: =ROUND(BO5+CS5,5) -> 8394106.3 | CW5: 0 | CY5: =ROUND(M5+U5+SUM(CU5:CW5),5) -> 8394106.3
E6: 4300 · Donations & Fundraising | I6: 0 | K6: 13572.42 | M6: =ROUND(SUM(I6:K6),5) -> 13572.42 | O6: 520130.01 | Q6: 0 | S6: 364215.03 | U6: =ROUND(SUM(O6:S6),5) -> 884345.04 | W6: 0 | Y6: 0 | AA6: 0 | AC6: 0 | AE6: 0 | AG6: =ROUND(SUM(AA6:AE6),5) -> 0 | AI6: 0 | AK6: 0 | AM6: 0 | AO6: 0 | AQ6: =ROUND(SUM(AI6:AO6),5) -> 0 | AS6: 0 | AU6: 0 | AW6: 0 | AY6: 0 | BA6: 0 | BC6: 0 | BE6: 100 | BG6: 0 | BI6: 0 | BK6: 441.31 | BM6: =ROUND(SUM(AU6:BK6),5) -> 541.31 | BO6: =ROUND(SUM(W6:Y6)+AG6+SUM(AQ6:AS6)+BM6,5) -> 541.31 | BQ6: 0 | BS6: 0 | BU6: 0 | BW6: 6366.69 | BY6: 0 | CA6: 0 | CC6: 0 | CE6: 3463 | CG6: 25 | CI6: 0 | CK6: 0 | CM6: =ROUND(SUM(CE6:CK6),5) -> 3488 | CO6: 207.56 | CQ6: 0 | CS6: =ROUND(SUM(BQ6:CC6)+SUM(CM6:CQ6),5) -> 10062.25 | CU6: =ROUND(BO6+CS6,5) -> 10603.56 | CW6: 0 | CY6: =ROUND(M6+U6+SUM(CU6:CW6),5) -> 908521.02
E7: 4400 · Events | I7: 0 | K7: 0 | M7: =ROUND(SUM(I7:K7),5) -> 0 | O7: 0 | Q7: 0 | S7: 146974.67 | U7: =ROUND(SUM(O7:S7),5) -> 146974.67 | W7: 0 | Y7: 0 | AA7: 0 | AC7: 0 | AE7: 0 | AG7: =ROUND(SUM(AA7:AE7),5) -> 0 | AI7: 0 | AK7: 0 | AM7: 0 | AO7: 0 | AQ7: =ROUND(SUM(AI7:AO7),5) -> 0 | AS7: 0 | AU7: 0 | AW7: 0 | AY7: 0 | BA7: 0 | BC7: 0 | BE7: 0 | BG7: 0 | BI7: 0 | BK7: 0 | BM7: =ROUND(SUM(AU7:BK7),5) -> 0 | BO7: =ROUND(SUM(W7:Y7)+AG7+SUM(AQ7:AS7)+BM7,5) -> 0 | BQ7: 664.15 | BS7: 0 | BU7: 0 | BW7: 456.58 | BY7: 0 | CA7: 4209.13 | CC7: 0 | CE7: 0 | CG7: 373.37 | CI7: 0 | CK7: 0 | CM7: =ROUND(SUM(CE7:CK7),5) -> 373.37 | CO7: 0 | CQ7: 0 | CS7: =ROUND(SUM(BQ7:CC7)+SUM(CM7:CQ7),5) -> 5703.23 | CU7: =ROUND(BO7+CS7,5) -> 5703.23 | CW7: 0 | CY7: =ROUND(M7+U7+SUM(CU7:CW7),5) -> 152677.9
E8: Counseling and Homecare Fees | I8: 0 | K8: 0 | M8: =ROUND(SUM(I8:K8),5) -> 0 | O8: 0 | Q8: 0 | S8: 0 | U8: =ROUND(SUM(O8:S8),5) -> 0 | W8: 0 | Y8: 0 | AA8: 0 | AC8: 0 | AE8: 0 | AG8: =ROUND(SUM(AA8:AE8),5) -> 0 | AI8: 0 | AK8: 0 | AM8: 0 | AO8: 0 | AQ8: =ROUND(SUM(AI8:AO8),5) -> 0 | AS8: 0 | AU8: 0 | AW8: 0 | AY8: 0 | BA8: 0 | BC8: 0 | BE8: 0 | BG8: 0 | BI8: 0 | BK8: 0 | BM8: =ROUND(SUM(AU8:BK8),5) -> 0 | BO8: =ROUND(SUM(W8:Y8)+AG8+SUM(AQ8:AS8)+BM8,5) -> 0 | BQ8: 12179.1 | BS8: 0 | BU8: 0 | BW8: 0 | BY8: 0 | CA8: 0 | CC8: 0 | CE8: 0 | CG8: 0 | CI8: 0 | CK8: 0 | CM8: =ROUND(SUM(CE8:CK8),5) -> 0 | CO8: 0 | CQ8: 0 | CS8: =ROUND(SUM(BQ8:CC8)+SUM(CM8:CQ8),5) -> 12179.1 | CU8: =ROUND(BO8+CS8,5) -> 12179.1 | CW8: 0 | CY8: =ROUND(M8+U8+SUM(CU8:CW8),5) -> 12179.1
E9: 4110 · Grants | I9: 0 | K9: 0 | M9: =ROUND(SUM(I9:K9),5) -> 0 | O9: 0 | Q9: 0 | S9: 130000 | U9: =ROUND(SUM(O9:S9),5) -> 130000 | W9: 0 | Y9: 0 | AA9: 0 | AC9: 0 | AE9: 0 | AG9: =ROUND(SUM(AA9:AE9),5) -> 0 | AI9: 0 | AK9: 0 | AM9: 0 | AO9: 0 | AQ9: =ROUND(SUM(AI9:AO9),5) -> 0 | AS9: 0 | AU9: 0 | AW9: 0 | AY9: 0 | BA9: 0 | BC9: 0 | BE9: 0 | BG9: 0 | BI9: 0 | BK9: 0 | BM9: =ROUND(SUM(AU9:BK9),5) -> 0 | BO9: =ROUND(SUM(W9:Y9)+AG9+SUM(AQ9:AS9)+BM9,5) -> 0 | BQ9: 100075 | BS9: 0 | BU9: 0 | BW9: 0 | BY9: 0 | CA9: 0 | CC9: 0 | CE9: 0 | CG9: 25000 | CI9: 0 | CK9: 0 | CM9: =ROUND(SUM(CE9:CK9),5) -> 25000 | CO9: 0 | CQ9: 0 | CS9: =ROUND(SUM(BQ9:CC9)+SUM(CM9:CQ9),5) -> 125075 | CU9: =ROUND(BO9+CS9,5) -> 125075 | CW9: 0 | CY9: =ROUND(M9+U9+SUM(CU9:CW9),5) -> 255075
E10: 4600 · Investment Income | I10: 0 | K10: 176083.77 | M10: =ROUND(SUM(I10:K10),5) -> 176083.77 | O10: 0 | Q10: 0 | S10: 0 | U10: =ROUND(SUM(O10:S10),5) -> 0 | W10: 0 | Y10: 0 | AA10: 0 | AC10: 0 | AE10: 0 | AG10: =ROUND(SUM(AA10:AE10),5) -> 0 | AI10: 0 | AK10: 0 | AM10: 0 | AO10: 0 | AQ10: =ROUND(SUM(AI10:AO10),5) -> 0 | AS10: 0 | AU10: 0 | AW10: 0 | AY10: 0 | BA10: 0 | BC10: 0 | BE10: 0 | BG10: 0 | BI10: 0 | BK10: 0 | BM10: =ROUND(SUM(AU10:BK10),5) -> 0 | BO10: =ROUND(SUM(W10:Y10)+AG10+SUM(AQ10:AS10)+BM10,5) -> 0 | BQ10: 0 | BS10: 0 | BU10: 0 | BW10: 0 | BY10: 0 | CA10: 0 | CC10: 0 | CE10: 0 | CG10: 0 | CI10: 0 | CK10: 0 | CM10: =ROUND(SUM(CE10:CK10),5) -> 0 | CO10: 0 | CQ10: 0 | CS10: =ROUND(SUM(BQ10:CC10)+SUM(CM10:CQ10),5) -> 0 | CU10: =ROUND(BO10+CS10,5) -> 0 | CW10: 0 | CY10: =ROUND(M10+U10+SUM(CU10:CW10),5) -> 176083.77
E11: 4999 · Use of Restricted Funds | I11: 31653.96 | K11: 0 | M11: =ROUND(SUM(I11:K11),5) -> 31653.96 | O11: 0 | Q11: 9388.22 | S11: 0 | U11: =ROUND(SUM(O11:S11),5) -> 9388.22 | W11: 0 | Y11: 0 | AA11: 0 | AC11: 0 | AE11: 0 | AG11: =ROUND(SUM(AA11:AE11),5) -> 0 | AI11: 0 | AK11: 0 | AM11: 0 | AO11: 0 | AQ11: =ROUND(SUM(AI11:AO11),5) -> 0 | AS11: 0 | AU11: 0 | AW11: 0 | AY11: 0 | BA11: 0 | BC11: 0 | BE11: 0 | BG11: 0 | BI11: 0 | BK11: 0 | BM11: =ROUND(SUM(AU11:BK11),5) -> 0 | BO11: =ROUND(SUM(W11:Y11)+AG11+SUM(AQ11:AS11)+BM11,5) -> 0 | BQ11: 656437.95 | BS11: 14824.25 | BU11: 76016.41 | BW11: 309217.69 | BY11: 60591.6 | CA11: 939038.84 | CC11: 72000 | CE11: 8130.95 | CG11: 1509.31 | CI11: 25538.5 | CK11: 252438.47 | CM11: =ROUND(SUM(CE11:CK11),5) -> 287617.23 | CO11: 50207.56 | CQ11: 15781.43 | CS11: =ROUND(SUM(BQ11:CC11)+SUM(CM11:CQ11),5) -> 2481733 | CU11: =ROUND(BO11+CS11,5) -> 2481733 | CW11: 0 | CY11: =ROUND(M11+U11+SUM(CU11:CW11),5) -> 2522775.1
D12: Total Income | I12: =ROUND(SUM(I4:I11),5) -> 31653.96 | K12: =ROUND(SUM(K4:K11),5) -> 189656.19 | M12: =ROUND(SUM(I12:K12),5) -> 221310.15 | O12: =ROUND(SUM(O4:O11),5) -> 520130.01 | Q12: =ROUND(SUM(Q4:Q11),5) -> 9388.22 | S12: =ROUND(SUM(S4:S11),5) -> 641189.7 | U12: =ROUND(SUM(O12:S12),5) -> 1170707.9 | W12: =ROUND(SUM(W4:W11),5) -> 185471.06 | Y12: =ROUND(SUM(Y4:Y11),5) -> 133162.81 | AA12: =ROUND(SUM(AA4:AA11),5) -> 4727288.3 | AC12: =ROUND(SUM(AC4:AC11),5) -> 14867 | AE12: =ROUND(SUM(AE4:AE11),5) -> 7358.96 | AG12: =ROUND(SUM(AA12:AE12),5) -> 4749514.3 | AI12: =ROUND(SUM(AI4:AI11),5) -> 266334.4 | AK12: =ROUND(SUM(AK4:AK11),5) -> 244176.82 | AM12: =ROUND(SUM(AM4:AM11),5) -> 335392.94 | AO12: =ROUND(SUM(AO4:AO11),5) -> 809780.49 | AQ12: =ROUND(SUM(AI12:AO12),5) -> 1655684.6 | AS12: =ROUND(SUM(AS4:AS11),5) -> 93881.38 | AU12: =ROUND(SUM(AU4:AU11),5) -> 122111.69 | AW12: =ROUND(SUM(AW4:AW11),5) -> 105105.92 | AY12: =ROUND(SUM(AY4:AY11),5) -> 84203.49 | BA12: =ROUND(SUM(BA4:BA11),5) -> 360224.52 | BC12: =ROUND(SUM(BC4:BC11),5) -> 96751.88 | BE12: =ROUND(SUM(BE4:BE11),5) -> 587087.54 | BG12: =ROUND(SUM(BG4:BG11),5) -> 6943.39 | BI12: =ROUND(SUM(BI4:BI11),5) -> 214063.67 | BK12: =ROUND(SUM(BK4:BK11),5) -> 441.31 | BM12: =ROUND(SUM(AU12:BK12),5) -> 1576933.4 | BO12: =ROUND(SUM(W12:Y12)+AG12+SUM(AQ12:AS12)+BM12,5) -> 8394647.6 | BQ12: =ROUND(SUM(BQ4:BQ11),5) -> 769356.2 | BS12: =ROUND(SUM(BS4:BS11),5) -> 14824.25 | BU12: =ROUND(SUM(BU4:BU11),5) -> 76016.41 | BW12: =ROUND(SUM(BW4:BW11),5) -> 316040.96 | BY12: =ROUND(SUM(BY4:BY11),5) -> 60591.6 | CA12: =ROUND(SUM(CA4:CA11),5) -> 943247.97 | CC12: =ROUND(SUM(CC4:CC11),5) -> 72000 | CE12: =ROUND(SUM(CE4:CE11),5) -> 11593.95 | CG12: =ROUND(SUM(CG4:CG11),5) -> 26907.68 | CI12: =ROUND(SUM(CI4:CI11),5) -> 25538.5 | CK12: =ROUND(SUM(CK4:CK11),5) -> 252438.47 | CM12: =ROUND(SUM(CE12:CK12),5) -> 316478.6 | CO12: =ROUND(SUM(CO4:CO11),5) -> 50415.12 | CQ12: =ROUND(SUM(CQ4:CQ11),5) -> 15781.43 | CS12: =ROUND(SUM(BQ12:CC12)+SUM(CM12:CQ12),5) -> 2634752.5 | CU12: =ROUND(BO12+CS12,5) -> 11029400 | CW12: =ROUND(SUM(CW4:CW11),5) -> 0 | CY12: =ROUND(M12+U12+SUM(CU12:CW12),5) -> 12421418
C13: Gross Profit | I13: =I12 -> 31653.96 | K13: =K12 -> 189656.19 | M13: =ROUND(SUM(I13:K13),5) -> 221310.15 | O13: =O12 -> 520130.01 | Q13: =Q12 -> 9388.22 | S13: =S12 -> 641189.7 | U13: =ROUND(SUM(O13:S13),5) -> 1170707.9 | W13: =W12 -> 185471.06 | Y13: =Y12 -> 133162.81 | AA13: =AA12 -> 4727288.3 | AC13: =AC12 -> 14867 | AE13: =AE12 -> 7358.96 | AG13: =ROUND(SUM(AA13:AE13),5) -> 4749514.3 | AI13: =AI12 -> 266334.4 | AK13: =AK12 -> 244176.82 | AM13: =AM12 -> 335392.94 | AO13: =AO12 -> 809780.49 | AQ13: =ROUND(SUM(AI13:AO13),5) -> 1655684.6 | AS13: =AS12 -> 93881.38 | AU13: =AU12 -> 122111.69 | AW13: =AW12 -> 105105.92 | AY13: =AY12 -> 84203.49 | BA13: =BA12 -> 360224.52 | BC13: =BC12 -> 96751.88 | BE13: =BE12 -> 587087.54 | BG13: =BG12 -> 6943.39 | BI13: =BI12 -> 214063.67 | BK13: =BK12 -> 441.31 | BM13: =ROUND(SUM(AU13:BK13),5) -> 1576933.4 | BO13: =ROUND(SUM(W13:Y13)+AG13+SUM(AQ13:AS13)+BM13,5) -> 8394647.6 | BQ13: =BQ12 -> 769356.2 | BS13: =BS12 -> 14824.25 | BU13: =BU12 -> 76016.41 | BW13: =BW12 -> 316040.96 | BY13: =BY12 -> 60591.6 | CA13: =CA12 -> 943247.97 | CC13: =CC12 -> 72000 | CE13: =CE12 -> 11593.95 | CG13: =CG12 -> 26907.68 | CI13: =CI12 -> 25538.5 | CK13: =CK12 -> 252438.47 | CM13: =ROUND(SUM(CE13:CK13),5) -> 316478.6 | CO13: =CO12 -> 50415.12 | CQ13: =CQ12 -> 15781.43 | CS13: =ROUND(SUM(BQ13:CC13)+SUM(CM13:CQ13),5) -> 2634752.5 | CU13: =ROUND(BO13+CS13,5) -> 11029400 | CW13: =CW12 -> 0 | CY13: =ROUND(M13+U13+SUM(CU13:CW13),5) -> 12421418
D14: Expense
E15: 6400 · Development Expenses
F16: 6410 · In-kind donation Expense | I16: 0 | K16: 0 | M16: =ROUND(SUM(I16:K16),5) -> 0 | O16: 0 | Q16: 0 | S16: 21247.77 | U16: =ROUND(SUM(O16:S16),5) -> 21247.77 | W16: 0 | Y16: 0 | AA16: 0 | AC16: 0 | AE16: 0 | AG16: =ROUND(SUM(AA16:AE16),5) -> 0 | AI16: 0 | AK16: 0 | AM16: 0 | AO16: 0 | AQ16: =ROUND(SUM(AI16:AO16),5) -> 0 | AS16: 0 | AU16: 0 | AW16: 0 | AY16: 0 | BA16: 0 | BC16: 0 | BE16: 0 | BG16: 0 | BI16: 0 | BK16: 0 | BM16: =ROUND(SUM(AU16:BK16),5) -> 0 | BO16: =ROUND(SUM(W16:Y16)+AG16+SUM(AQ16:AS16)+BM16,5) -> 0 | BQ16: 0 | BS16: 0 | BU16: 0 | BW16: 0 | BY16: 0 | CA16: 0 | CC16: 0 | CE16: 0 | CG16: 0 | CI16: 0 | CK16: 0 | CM16: =ROUND(SUM(CE16:CK16),5) -> 0 | CO16: 0 | CQ16: 0 | CS16: =ROUND(SUM(BQ16:CC16)+SUM(CM16:CQ16),5) -> 0 | CU16: =ROUND(BO16+CS16,5) -> 0 | CW16: 0 | CY16: =ROUND(M16+U16+SUM(CU16:CW16),5) -> 21247.77 | CZ16: 13 | DA16: =+CO16+CC16+CA16+BU16+BQ16+AG16 -> 0 | DC16: =+CQ16+BY16+BW16+BS16+BM16+AS16+AQ16+Y16+W16 -> 0
E17: Total 6400 · Development Expenses | I17: =ROUND(SUM(I15:I16),5) -> 0 | K17: =ROUND(SUM(K15:K16),5) -> 0 | M17: =ROUND(SUM(I17:K17),5) -> 0 | O17: =ROUND(SUM(O15:O16),5) -> 0 | Q17: =ROUND(SUM(Q15:Q16),5) -> 0 | S17: =ROUND(SUM(S15:S16),5) -> 21247.77 | U17: =ROUND(SUM(O17:S17),5) -> 21247.77 | W17: =ROUND(SUM(W15:W16),5) -> 0 | Y17: =ROUND(SUM(Y15:Y16),5) -> 0 | AA17: =ROUND(SUM(AA15:AA16),5) -> 0 | AC17: =ROUND(SUM(AC15:AC16),5) -> 0 | AE17: =ROUND(SUM(AE15:AE16),5) -> 0 | AG17: =ROUND(SUM(AA17:AE17),5) -> 0 | AI17: =ROUND(SUM(AI15:AI16),5) -> 0 | AK17: =ROUND(SUM(AK15:AK16),5) -> 0 | AM17: =ROUND(SUM(AM15:AM16),5) -> 0 | AO17: =ROUND(SUM(AO15:AO16),5) -> 0 | AQ17: =ROUND(SUM(AI17:AO17),5) -> 0 | AS17: =ROUND(SUM(AS15:AS16),5) -> 0 | AU17: =ROUND(SUM(AU15:AU16),5) -> 0 | AW17: =ROUND(SUM(AW15:AW16),5) -> 0 | AY17: =ROUND(SUM(AY15:AY16),5) -> 0 | BA17: =ROUND(SUM(BA15:BA16),5) -> 0 | BC17: =ROUND(SUM(BC15:BC16),5) -> 0 | BE17: =ROUND(SUM(BE15:BE16),5) -> 0 | BG17: =ROUND(SUM(BG15:BG16),5) -> 0 | BI17: =ROUND(SUM(BI15:BI16),5) -> 0 | BK17: =ROUND(SUM(BK15:BK16),5) -> 0 | BM17: =ROUND(SUM(AU17:BK17),5) -> 0 | BO17: =ROUND(SUM(W17:Y17)+AG17+SUM(AQ17:AS17)+BM17,5) -> 0 | BQ17: =ROUND(SUM(BQ15:BQ16),5) -> 0 | BS17: =ROUND(SUM(BS15:BS16),5) -> 0 | BU17: =ROUND(SUM(BU15:BU16),5) -> 0 | BW17: =ROUND(SUM(BW15:BW16),5) -> 0 | BY17: =ROUND(SUM(BY15:BY16),5) -> 0 | CA17: =ROUND(SUM(CA15:CA16),5) -> 0 | CC17: =ROUND(SUM(CC15:CC16),5) -> 0 | CE17: =ROUND(SUM(CE15:CE16),5) -> 0 | CG17: =ROUND(SUM(CG15:CG16),5) -> 0 | CI17: =ROUND(SUM(CI15:CI16),5) -> 0 | CK17: =ROUND(SUM(CK15:CK16),5) -> 0 | CM17: =ROUND(SUM(CE17:CK17),5) -> 0 | CO17: =ROUND(SUM(CO15:CO16),5) -> 0 | CQ17: =ROUND(SUM(CQ15:CQ16),5) -> 0 | CS17: =ROUND(SUM(BQ17:CC17)+SUM(CM17:CQ17),5) -> 0 | CU17: =ROUND(BO17+CS17,5) -> 0 | CW17: =ROUND(SUM(CW15:CW16),5) -> 0 | CY17: =ROUND(M17+U17+SUM(CU17:CW17),5) -> 21247.77 | DA17: =+CO17+CC17+CA17+BU17+BQ17+AG17 -> 0 | DC17: =+CQ17+BY17+BW17+BS17+BM17+AS17+AQ17+Y17+W17 -> 0
E18: 6000 · Indirect Costs | DA18: =+CO18+CC18+CA18+BU18+BQ18+AG18 -> 0 | DC18: =+CQ18+BY18+BW18+BS18+BM18+AS18+AQ18+Y18+W18 -> 0
F19: 6600 · Operating Expenses | DA19: =+CO19+CC19+CA19+BU19+BQ19+AG19 -> 0 | DC19: =+CQ19+BY19+BW19+BS19+BM19+AS19+AQ19+Y19+W19 -> 0
G20: 6602 · Advertising | I20: 0 | K20: 1074.39 | M20: =ROUND(SUM(I20:K20),5) -> 1074.39 | O20: 0 | Q20: 0 | S20: 184.77 | U20: =ROUND(SUM(O20:S20),5) -> 184.77 | W20: 0 | Y20: 0 | AA20: 0 | AC20: 0 | AE20: 0 | AG20: =ROUND(SUM(AA20:AE20),5) -> 0 | AI20: 0 | AK20: 0 | AM20: 0 | AO20: 0 | AQ20: =ROUND(SUM(AI20:AO20),5) -> 0 | AS20: 0 | AU20: 0 | AW20: 0 | AY20: 0 | BA20: 0 | BC20: 0 | BE20: 0 | BG20: 0 | BI20: 0 | BK20: 0 | BM20: =ROUND(SUM(AU20:BK20),5) -> 0 | BO20: =ROUND(SUM(W20:Y20)+AG20+SUM(AQ20:AS20)+BM20,5) -> 0 | BQ20: 1650 | BS20: 0 | BU20: 0 | BW20: 0 | BY20: 0 | CA20: 0 | CC20: 0 | CE20: 0 | CG20: 0 | CI20: 0 | CK20: 0 | CM20: =ROUND(SUM(CE20:CK20),5) -> 0 | CO20: 0 | CQ20: 0 | CS20: =ROUND(SUM(BQ20:CC20)+SUM(CM20:CQ20),5) -> 1650 | CU20: =ROUND(BO20+CS20,5) -> 1650 | CW20: 0 | CY20: =ROUND(M20+U20+SUM(CU20:CW20),5) -> 2909.16 | CZ20: 6 | DA20: =+CO20+CC20+CA20+BU20+BQ20+AG20 -> 1650 | DC20: =+CQ20+BY20+BW20+BS20+BM20+AS20+AQ20+Y20+W20 -> 0
G21: 6604 · Bank and Credit Card Charge | I21: 0 | K21: 4307.19 | M21: =ROUND(SUM(I21:K21),5) -> 4307.19 | O21: 88.82 | Q21: 0 | S21: 3184.23 | U21: =ROUND(SUM(O21:S21),5) -> 3273.05 | W21: 0 | Y21: 0 | AA21: 0 | AC21: 0 | AE21: 0 | AG21: =ROUND(SUM(AA21:AE21),5) -> 0 | AI21: 0 | AK21: 0 | AM21: 0 | AO21: 0 | AQ21: =ROUND(SUM(AI21:AO21),5) -> 0 | AS21: 0 | AU21: 0 | AW21: 0 | AY21: 0 | BA21: 0 | BC21: 0 | BE21: 0 | BG21: 0 | BI21: 0 | BK21: 0 | BM21: =ROUND(SUM(AU21:BK21),5) -> 0 | BO21: =ROUND(SUM(W21:Y21)+AG21+SUM(AQ21:AS21)+BM21,5) -> 0 | BQ21: 22.08 | BS21: 0 | BU21: 0 | BW21: 117.91 | BY21: 0 | CA21: 121.6 | CC21: 0 | CE21: 0 | CG21: 15.18 | CI21: 0 | CK21: 0 | CM21: =ROUND(SUM(CE21:CK21),5) -> 15.18 | CO21: 6.09 | CQ21: 0 | CS21: =ROUND(SUM(BQ21:CC21)+SUM(CM21:CQ21),5) -> 282.86 | CU21: =ROUND(BO21+CS21,5) -> 282.86 | CW21: 0 | CY21: =ROUND(M21+U21+SUM(CU21:CW21),5) -> 7863.1 | CZ21: 7 | DA21: =+CO21+CC21+CA21+BU21+BQ21+AG21 -> 149.77 | DC21: =+CQ21+BY21+BW21+BS21+BM21+AS21+AQ21+Y21+W21 -> 117.91
G22: 6606 · Conference and Meetings | I22: 0 | K22: 12479.17 | M22: =ROUND(SUM(I22:K22),5) -> 12479.17 | O22: 0 | Q22: 9388.22 | S22: 366.57 | U22: =ROUND(SUM(O22:S22),5) -> 9754.79 | W22: 0 | Y22: 0 | AA22: 0 | AC22: 0 | AE22: 0 | AG22: =ROUND(SUM(AA22:AE22),5) -> 0 | AI22: 0 | AK22: 0 | AM22: 0 | AO22: 0 | AQ22: =ROUND(SUM(AI22:AO22),5) -> 0 | AS22: 0 | AU22: 0 | AW22: 0 | AY22: 0 | BA22: 0 | BC22: 0 | BE22: 0 | BG22: 0 | BI22: 0 | BK22: 2379 | BM22: =ROUND(SUM(AU22:BK22),5) -> 2379 | BO22: =ROUND(SUM(W22:Y22)+AG22+SUM(AQ22:AS22)+BM22,5) -> 2379 | BQ22: 5833.93 | BS22: 0 | BU22: 0 | BW22: 0 | BY22: 0 | CA22: 138.63 | CC22: 0 | CE22: 0 | CG22: 40.54 | CI22: 0 | CK22: 0 | CM22: =ROUND(SUM(CE22:CK22),5) -> 40.54 | CO22: 162 | CQ22: 0 | CS22: =ROUND(SUM(BQ22:CC22)+SUM(CM22:CQ22),5) -> 6175.1 | CU22: =ROUND(BO22+CS22,5) -> 8554.1 | CW22: 0 | CY22: =ROUND(M22+U22+SUM(CU22:CW22),5) -> 30788.06 | CZ22: 10 | DA22: =+CO22+CC22+CA22+BU22+BQ22+AG22 -> 6134.56 | DC22: =+CQ22+BY22+BW22+BS22+BM22+AS22+AQ22+Y22+W22 -> 2379
G23: 6630 · Office Expenses | DA23: =+CO23+CC23+CA23+BU23+BQ23+AG23 -> 0 | DC23: =+CQ23+BY23+BW23+BS23+BM23+AS23+AQ23+Y23+W23 -> 0
H24: 6632 · Postage | I24: 0 | K24: 3194.36 | M24: =ROUND(SUM(I24:K24),5) -> 3194.36 | O24: 0 | Q24: 0 | S24: 2270.85 | U24: =ROUND(SUM(O24:S24),5) -> 2270.85 | W24: 0 | Y24: 60.46 | AA24: 0 | AC24: 0 | AE24: 0 | AG24: =ROUND(SUM(AA24:AE24),5) -> 0 | AI24: 0 | AK24: 0 | AM24: 0 | AO24: 0 | AQ24: =ROUND(SUM(AI24:AO24),5) -> 0 | AS24: 59.53 | AU24: 0 | AW24: 53.94 | AY24: 15.39 | BA24: 62.06 | BC24: 52 | BE24: 534.81 | BG24: 0 | BI24: 0 | BK24: 0 | BM24: =ROUND(SUM(AU24:BK24),5) -> 718.2 | BO24: =ROUND(SUM(W24:Y24)+AG24+SUM(AQ24:AS24)+BM24,5) -> 838.19 | BQ24: 931.46 | BS24: 0 | BU24: 0 | BW24: 687.26 | BY24: 0 | CA24: 0 | CC24: 0 | CE24: 0 | CG24: 0 | CI24: 0 | CK24: 249.81 | CM24: =ROUND(SUM(CE24:CK24),5) -> 249.81 | CO24: 0 | CQ24: 0 | CS24: =ROUND(SUM(BQ24:CC24)+SUM(CM24:CQ24),5) -> 1868.53 | CU24: =ROUND(BO24+CS24,5) -> 2706.72 | CW24: 0 | CY24: =ROUND(M24+U24+SUM(CU24:CW24),5) -> 8171.93 | CZ24: 7 | DA24: =+CO24+CC24+CA24+BU24+BQ24+AG24 -> 931.46 | DC24: =+CQ24+BY24+BW24+BS24+BM24+AS24+AQ24+Y24+W24 -> 1525.45
H25: 6631 · Dues and Subscriptions | I25: 0 | K25: 28851.86 | M25: =ROUND(SUM(I25:K25),5) -> 28851.86 | O25: 0 | Q25: 0 | S25: 12143.14 | U25: =ROUND(SUM(O25:S25),5) -> 12143.14 | W25: 0 | Y25: 739.49 | AA25: 0 | AC25: 0 | AE25: 0 | AG25: =ROUND(SUM(AA25:AE25),5) -> 0 | AI25: 0 | AK25: 0 | AM25: 0 | AO25: 0 | AQ25: =ROUND(SUM(AI25:AO25),5) -> 0 | AS25: 369.15 | AU25: 0 | AW25: 665.8 | AY25: 347.91 | BA25: 678.54 | BC25: 434 | BE25: 3249.89 | BG25: 0 | BI25: 0 | BK25: 0 | BM25: =ROUND(SUM(AU25:BK25),5) -> 5376.14 | BO25: =ROUND(SUM(W25:Y25)+AG25+SUM(AQ25:AS25)+BM25,5) -> 6484.78 | BQ25: 6581.76 | BS25: 0 | BU25: 0 | BW25: 4640 | BY25: 0 | CA25: 5638 | CC25: 0 | CE25: 0 | CG25: 0 | CI25: 0 | CK25: 2039.67 | CM25: =ROUND(SUM(CE25:CK25),5) -> 2039.67 | CO25: 14.97 | CQ25: 0 | CS25: =ROUND(SUM(BQ25:CC25)+SUM(CM25:CQ25),5) -> 18914.4 | CU25: =ROUND(BO25+CS25,5) -> 25399.18 | CW25: 0 | CY25: =ROUND(M25+U25+SUM(CU25:CW25),5) -> 66394.18 | CZ25: 7 | DA25: =+CO25+CC25+CA25+BU25+BQ25+AG25 -> 12234.73 | DC25: =+CQ25+BY25+BW25+BS25+BM25+AS25+AQ25+Y25+W25 -> 11124.78
H26: 6630 · Office Expenses - Other | I26: 0 | K26: 29565.03 | M26: =ROUND(SUM(I26:K26),5) -> 29565.03 | O26: 0 | Q26: 0 | S26: 5404.34 | U26: =ROUND(SUM(O26:S26),5) -> 5404.34 | W26: 682.38 | Y26: 2041.38 | AA26: 0 | AC26: 0 | AE26: 0 | AG26: =ROUND(SUM(AA26:AE26),5) -> 0 | AI26: 3202.61 | AK26: 305.87 | AM26: 0 | AO26: 435.99 | AQ26: =ROUND(SUM(AI26:AO26),5) -> 3944.47 | AS26: 109.66 | AU26: 0 | AW26: 379.28 | AY26: 35.82 | BA26: 2197.73 | BC26: 57 | BE26: 14683.14 | BG26: 0 | BI26: 0 | BK26: 0 | BM26: =ROUND(SUM(AU26:BK26),5) -> 17352.97 | BO26: =ROUND(SUM(W26:Y26)+AG26+SUM(AQ26:AS26)+BM26,5) -> 24130.86 | BQ26: 8170.7 | BS26: 0 | BU26: 0 | BW26: 7660 | BY26: 0 | CA26: 3073.83 | CC26: 0 | CE26: 0 | CG26: 0 | CI26: 8174.89 | CK26: 643.8 | CM26: =ROUND(SUM(CE26:CK26),5) -> 8818.69 | CO26: 243.33 | CQ26: 0 | CS26: =ROUND(SUM(BQ26:CC26)+SUM(CM26:CQ26),5) -> 27966.55 | CU26: =ROUND(BO26+CS26,5) -> 52097.41 | CW26: 0 | CY26: =ROUND(M26+U26+SUM(CU26:CW26),5) -> 87066.78 | CZ26: 7 | DA26: =+CO26+CC26+CA26+BU26+BQ26+AG26 -> 11487.86 | DC26: =+CQ26+BY26+BW26+BS26+BM26+AS26+AQ26+Y26+W26 -> 31790.86
G27: Total 6630 · Office Expenses | I27: =ROUND(SUM(I23:I26),5) -> 0 | K27: =ROUND(SUM(K23:K26),5) -> 61611.25 | M27: =ROUND(SUM(I27:K27),5) -> 61611.25 | O27: =ROUND(SUM(O23:O26),5) -> 0 | Q27: =ROUND(SUM(Q23:Q26),5) -> 0 | S27: =ROUND(SUM(S23:S26),5) -> 19818.33 | U27: =ROUND(SUM(O27:S27),5) -> 19818.33 | W27: =ROUND(SUM(W23:W26),5) -> 682.38 | Y27: =ROUND(SUM(Y23:Y26),5) -> 2841.33 | AA27: =ROUND(SUM(AA23:AA26),5) -> 0 | AC27: =ROUND(SUM(AC23:AC26),5) -> 0 | AE27: =ROUND(SUM(AE23:AE26),5) -> 0 | AG27: =ROUND(SUM(AA27:AE27),5) -> 0 | AI27: =ROUND(SUM(AI23:AI26),5) -> 3202.61 | AK27: =ROUND(SUM(AK23:AK26),5) -> 305.87 | AM27: =ROUND(SUM(AM23:AM26),5) -> 0 | AO27: =ROUND(SUM(AO23:AO26),5) -> 435.99 | AQ27: =ROUND(SUM(AI27:AO27),5) -> 3944.47 | AS27: =ROUND(SUM(AS23:AS26),5) -> 538.34 | AU27: =ROUND(SUM(AU23:AU26),5) -> 0 | AW27: =ROUND(SUM(AW23:AW26),5) -> 1099.02 | AY27: =ROUND(SUM(AY23:AY26),5) -> 399.12 | BA27: =ROUND(SUM(BA23:BA26),5) -> 2938.33 | BC27: =ROUND(SUM(BC23:BC26),5) -> 543 | BE27: =ROUND(SUM(BE23:BE26),5) -> 18467.84 | BG27: =ROUND(SUM(BG23:BG26),5) -> 0 | BI27: =ROUND(SUM(BI23:BI26),5) -> 0 | BK27: =ROUND(SUM(BK23:BK26),5) -> 0 | BM27: =ROUND(SUM(AU27:BK27),5) -> 23447.31 | BO27: =ROUND(SUM(W27:Y27)+AG27+SUM(AQ27:AS27)+BM27,5) -> 31453.83 | BQ27: =ROUND(SUM(BQ23:BQ26),5) -> 15683.92 | BS27: =ROUND(SUM(BS23:BS26),5) -> 0 | BU27: =ROUND(SUM(BU23:BU26),5) -> 0 | BW27: =ROUND(SUM(BW23:BW26),5) -> 12987.26 | BY27: =ROUND(SUM(BY23:BY26),5) -> 0 | CA27: =ROUND(SUM(CA23:CA26),5) -> 8711.83 | CC27: =ROUND(SUM(CC23:CC26),5) -> 0 | CE27: =ROUND(SUM(CE23:CE26),5) -> 0 | CG27: =ROUND(SUM(CG23:CG26),5) -> 0 | CI27: =ROUND(SUM(CI23:CI26),5) -> 8174.89 | CK27: =ROUND(SUM(CK23:CK26),5) -> 2933.28 | CM27: =ROUND(SUM(CE27:CK27),5) -> 11108.17 | CO27: =ROUND(SUM(CO23:CO26),5) -> 258.3 | CQ27: =ROUND(SUM(CQ23:CQ26),5) -> 0 | CS27: =ROUND(SUM(BQ27:CC27)+SUM(CM27:CQ27),5) -> 48749.48 | CU27: =ROUND(BO27+CS27,5) -> 80203.31 | CW27: =ROUND(SUM(CW23:CW26),5) -> 0 | CY27: =ROUND(M27+U27+SUM(CU27:CW27),5) -> 161632.89 | DA27: =+CO27+CC27+CA27+BU27+BQ27+AG27 -> 24654.05 | DC27: =+CQ27+BY27+BW27+BS27+BM27+AS27+AQ27+Y27+W27 -> 44441.09
G28: 6800 · Professional Services | DA28: =+CO28+CC28+CA28+BU28+BQ28+AG28 -> 0 | DC28: =+CQ28+BY28+BW28+BS28+BM28+AS28+AQ28+Y28+W28 -> 0
H29: 6804 · HR | I29: 0 | K29: 9620 | M29: =ROUND(SUM(I29:K29),5) -> 9620 | O29: 0 | Q29: 0 | S29: 0 | U29: =ROUND(SUM(O29:S29),5) -> 0 | W29: 0 | Y29: 0 | AA29: 0 | AC29: 0 | AE29: 0 | AG29: =ROUND(SUM(AA29:AE29),5) -> 0 | AI29: 0 | AK29: 0 | AM29: 0 | AO29: 0 | AQ29: =ROUND(SUM(AI29:AO29),5) -> 0 | AS29: 0 | AU29: 0 | AW29: 0 | AY29: 0 | BA29: 0 | BC29: 0 | BE29: 0 | BG29: 0 | BI29: 0 | BK29: 0 | BM29: =ROUND(SUM(AU29:BK29),5) -> 0 | BO29: =ROUND(SUM(W29:Y29)+AG29+SUM(AQ29:AS29)+BM29,5) -> 0 | BQ29: 0 | BS29: 0 | BU29: 0 | BW29: 0 | BY29: 0 | CA29: 0 | CC29: 0 | CE29: 0 | CG29: 0 | CI29: 0 | CK29: 0 | CM29: =ROUND(SUM(CE29:CK29),5) -> 0 | CO29: 0 | CQ29: 0 | CS29: =ROUND(SUM(BQ29:CC29)+SUM(CM29:CQ29),5) -> 0 | CU29: =ROUND(BO29+CS29,5) -> 0 | CW29: 0 | CY29: =ROUND(M29+U29+SUM(CU29:CW29),5) -> 9620 | DA29: =+CO29+CC29+CA29+BU29+BQ29+AG29 -> 0 | DC29: =+CQ29+BY29+BW29+BS29+BM29+AS29+AQ29+Y29+W29 -> 0
H30: 6802 · Other Services | I30: 0 | K30: 96700.6 | M30: =ROUND(SUM(I30:K30),5) -> 96700.6 | O30: 0 | Q30: 0 | S30: 32581.58 | U30: =ROUND(SUM(O30:S30),5) -> 32581.58 | W30: 0 | Y30: 0 | AA30: 0 | AC30: 0 | AE30: 0 | AG30: =ROUND(SUM(AA30:AE30),5) -> 0 | AI30: 0 | AK30: 0 | AM30: 0 | AO30: 0 | AQ30: =ROUND(SUM(AI30:AO30),5) -> 0 | AS30: 0 | AU30: 0 | AW30: 0 | AY30: 163 | BA30: 0 | BC30: 0 | BE30: 0 | BG30: 0 | BI30: 0 | BK30: 0 | BM30: =ROUND(SUM(AU30:BK30),5) -> 163 | BO30: =ROUND(SUM(W30:Y30)+AG30+SUM(AQ30:AS30)+BM30,5) -> 163 | BQ30: 4870.28 | BS30: 0 | BU30: 0 | BW30: 24113.75 | BY30: 0 | CA30: 0 | CC30: 0 | CE30: 0 | CG30: 0 | CI30: 0 | CK30: 2335.5 | CM30: =ROUND(SUM(CE30:CK30),5) -> 2335.5 | CO30: 400 | CQ30: 0 | CS30: =ROUND(SUM(BQ30:CC30)+SUM(CM30:CQ30),5) -> 31719.53 | CU30: =ROUND(BO30+CS30,5) -> 31882.53 | CW30: 0 | CY30: =ROUND(M30+U30+SUM(CU30:CW30),5) -> 161164.71 | DA30: =+CO30+CC30+CA30+BU30+BQ30+AG30 -> 5270.28 | DC30: =+CQ30+BY30+BW30+BS30+BM30+AS30+AQ30+Y30+W30 -> 24276.75
H31: 6808 · Legal | I31: 0 | K31: 3780 | M31: =ROUND(SUM(I31:K31),5) -> 3780 | O31: 0 | Q31: 0 | S31: 0 | U31: =ROUND(SUM(O31:S31),5) -> 0 | W31: 0 | Y31: 0 | AA31: 0 | AC31: 0 | AE31: 0 | AG31: =ROUND(SUM(AA31:AE31),5) -> 0 | AI31: 0 | AK31: 0 | AM31: 0 | AO31: 0 | AQ31: =ROUND(SUM(AI31:AO31),5) -> 0 | AS31: 0 | AU31: 0 | AW31: 0 | AY31: 0 | BA31: 0 | BC31: 0 | BE31: 0 | BG31: 0 | BI31: 0 | BK31: 0 | BM31: =ROUND(SUM(AU31:BK31),5) -> 0 | BO31: =ROUND(SUM(W31:Y31)+AG31+SUM(AQ31:AS31)+BM31,5) -> 0 | BQ31: 60482.5 | BS31: 0 | BU31: 0 | BW31: 0 | BY31: 0 | CA31: 0 | CC31: 0 | CE31: 0 | CG31: 0 | CI31: 0 | CK31: 0 | CM31: =ROUND(SUM(CE31:CK31),5) -> 0 | CO31: 0 | CQ31: 0 | CS31: =ROUND(SUM(BQ31:CC31)+SUM(CM31:CQ31),5) -> 60482.5 | CU31: =ROUND(BO31+CS31,5) -> 60482.5 | CW31: 0 | CY31: =ROUND(M31+U31+SUM(CU31:CW31),5) -> 64262.5 | DA31: =+CO31+CC31+CA31+BU31+BQ31+AG31 -> 60482.5 | DC31: =+CQ31+BY31+BW31+BS31+BM31+AS31+AQ31+Y31+W31 -> 0
H32: 6806 · Accounting | I32: 0 | K32: 257245 | M32: =ROUND(SUM(I32:K32),5) -> 257245 | O32: 0 | Q32: 0 | S32: 0 | U32: =ROUND(SUM(O32:S32),5) -> 0 | W32: 0 | Y32: 0 | AA32: 0 | AC32: 0 | AE32: 0 | AG32: =ROUND(SUM(AA32:AE32),5) -> 0 | AI32: 0 | AK32: 0 | AM32: 0 | AO32: 0 | AQ32: =ROUND(SUM(AI32:AO32),5) -> 0 | AS32: 0 | AU32: 0 | AW32: 0 | AY32: 0 | BA32: 0 | BC32: 0 | BE32: 0 | BG32: 0 | BI32: 0 | BK32: 0 | BM32: =ROUND(SUM(AU32:BK32),5) -> 0 | BO32: =ROUND(SUM(W32:Y32)+AG32+SUM(AQ32:AS32)+BM32,5) -> 0 | BQ32: 0 | BS32: 0 | BU32: 0 | BW32: 0 | BY32: 0 | CA32: 0 | CC32: 0 | CE32: 0 | CG32: 0 | CI32: 0 | CK32: 0 | CM32: =ROUND(SUM(CE32:CK32),5) -> 0 | CO32: 0 | CQ32: 0 | CS32: =ROUND(SUM(BQ32:CC32)+SUM(CM32:CQ32),5) -> 0 | CU32: =ROUND(BO32+CS32,5) -> 0 | CW32: 0 | CY32: =ROUND(M32+U32+SUM(CU32:CW32),5) -> 257245 | DA32: =+CO32+CC32+CA32+BU32+BQ32+AG32 -> 0 | DC32: =+CQ32+BY32+BW32+BS32+BM32+AS32+AQ32+Y32+W32 -> 0
H33: 6800 · Professional Services - Other | I33: 0 | K33: -12372 | M33: =ROUND(SUM(I33:K33),5) -> -12372 | O33: 0 | Q33: 0 | S33: 0 | U33: =ROUND(SUM(O33:S33),5) -> 0 | W33: 0 | Y33: 0 | AA33: 0 | AC33: 0 | AE33: 0 | AG33: =ROUND(SUM(AA33:AE33),5) -> 0 | AI33: 0 | AK33: 0 | AM33: 0 | AO33: 0 | AQ33: =ROUND(SUM(AI33:AO33),5) -> 0 | AS33: 0 | AU33: 0 | AW33: 0 | AY33: 0 | BA33: 0 | BC33: 0 | BE33: 0 | BG33: 0 | BI33: 0 | BK33: 0 | BM33: =ROUND(SUM(AU33:BK33),5) -> 0 | BO33: =ROUND(SUM(W33:Y33)+AG33+SUM(AQ33:AS33)+BM33,5) -> 0 | BQ33: 12372 | BS33: 0 | BU33: 0 | BW33: 0 | BY33: 0 | CA33: 0 | CC33: 0 | CE33: 0 | CG33: 0 | CI33: 0 | CK33: 0 | CM33: =ROUND(SUM(CE33:CK33),5) -> 0 | CO33: 0 | CQ33: 0 | CS33: =ROUND(SUM(BQ33:CC33)+SUM(CM33:CQ33),5) -> 12372 | CU33: =ROUND(BO33+CS33,5) -> 12372 | CW33: 0 | CY33: =ROUND(M33+U33+SUM(CU33:CW33),5) -> 0 | DA33: =+CO33+CC33+CA33+BU33+BQ33+AG33 -> 12372 | DC33: =+CQ33+BY33+BW33+BS33+BM33+AS33+AQ33+Y33+W33 -> 0
G34: Total 6800 · Professional Services | I34: =ROUND(SUM(I28:I33),5) -> 0 | K34: =ROUND(SUM(K28:K33),5) -> 354973.6 | M34: =ROUND(SUM(I34:K34),5) -> 354973.6 | O34: =ROUND(SUM(O28:O33),5) -> 0 | Q34: =ROUND(SUM(Q28:Q33),5) -> 0 | S34: =ROUND(SUM(S28:S33),5) -> 32581.58 | U34: =ROUND(SUM(O34:S34),5) -> 32581.58 | W34: =ROUND(SUM(W28:W33),5) -> 0 | Y34: =ROUND(SUM(Y28:Y33),5) -> 0 | AA34: =ROUND(SUM(AA28:AA33),5) -> 0 | AC34: =ROUND(SUM(AC28:AC33),5) -> 0 | AE34: =ROUND(SUM(AE28:AE33),5) -> 0 | AG34: =ROUND(SUM(AA34:AE34),5) -> 0 | AI34: =ROUND(SUM(AI28:AI33),5) -> 0 | AK34: =ROUND(SUM(AK28:AK33),5) -> 0 | AM34: =ROUND(SUM(AM28:AM33),5) -> 0 | AO34: =ROUND(SUM(AO28:AO33),5) -> 0 | AQ34: =ROUND(SUM(AI34:AO34),5) -> 0 | AS34: =ROUND(SUM(AS28:AS33),5) -> 0 | AU34: =ROUND(SUM(AU28:AU33),5) -> 0 | AW34: =ROUND(SUM(AW28:AW33),5) -> 0 | AY34: =ROUND(SUM(AY28:AY33),5) -> 163 | BA34: =ROUND(SUM(BA28:BA33),5) -> 0 | BC34: =ROUND(SUM(BC28:BC33),5) -> 0 | BE34: =ROUND(SUM(BE28:BE33),5) -> 0 | BG34: =ROUND(SUM(BG28:BG33),5) -> 0 | BI34: =ROUND(SUM(BI28:BI33),5) -> 0 | BK34: =ROUND(SUM(BK28:BK33),5) -> 0 | BM34: =ROUND(SUM(AU34:BK34),5) -> 163 | BO34: =ROUND(SUM(W34:Y34)+AG34+SUM(AQ34:AS34)+BM34,5) -> 163 | BQ34: =ROUND(SUM(BQ28:BQ33),5) -> 77724.78 | BS34: =ROUND(SUM(BS28:BS33),5) -> 0 | BU34: =ROUND(SUM(BU28:BU33),5) -> 0 | BW34: =ROUND(SUM(BW28:BW33),5) -> 24113.75 | BY34: =ROUND(SUM(BY28:BY33),5) -> 0 | CA34: =ROUND(SUM(CA28:CA33),5) -> 0 | CC34: =ROUND(SUM(CC28:CC33),5) -> 0 | CE34: =ROUND(SUM(CE28:CE33),5) -> 0 | CG34: =ROUND(SUM(CG28:CG33),5) -> 0 | CI34: =ROUND(SUM(CI28:CI33),5) -> 0 | CK34: =ROUND(SUM(CK28:CK33),5) -> 2335.5 | CM34: =ROUND(SUM(CE34:CK34),5) -> 2335.5 | CO34: =ROUND(SUM(CO28:CO33),5) -> 400 | CQ34: =ROUND(SUM(CQ28:CQ33),5) -> 0 | CS34: =ROUND(SUM(BQ34:CC34)+SUM(CM34:CQ34),5) -> 104574.03 | CU34: =ROUND(BO34+CS34,5) -> 104737.03 | CW34: =ROUND(SUM(CW28:CW33),5) -> 0 | CY34: =ROUND(M34+U34+SUM(CU34:CW34),5) -> 492292.21 | CZ34: 5 | DA34: =+CO34+CC34+CA34+BU34+BQ34+AG34 -> 78124.78 | DC34: =+CQ34+BY34+BW34+BS34+BM34+AS34+AQ34+Y34+W34 -> 24276.75
G35: 6636 · Travel | I35: 0 | K35: 292.14 | M35: =ROUND(SUM(I35:K35),5) -> 292.14 | O35: 0 | Q35: 0 | S35: 53.71 | U35: =ROUND(SUM(O35:S35),5) -> 53.71 | W35: 0 | Y35: 5928.39 | AA35: 594.13 | AC35: 0 | AE35: 0 | AG35: =ROUND(SUM(AA35:AE35),5) -> 594.13 | AI35: 0 | AK35: 0 | AM35: 0 | AO35: 0 | AQ35: =ROUND(SUM(AI35:AO35),5) -> 0 | AS35: 0 | AU35: 0 | AW35: 417.07 | AY35: 0 | BA35: 0 | BC35: 21.48 | BE35: 0 | BG35: 0 | BI35: 0 | BK35: 0 | BM35: =ROUND(SUM(AU35:BK35),5) -> 438.55 | BO35: =ROUND(SUM(W35:Y35)+AG35+SUM(AQ35:AS35)+BM35,5) -> 6961.07 | BQ35: 4889.28 | BS35: 0 | BU35: 0 | BW35: 1220.93 | BY35: 0 | CA35: 2276.59 | CC35: 0 | CE35: 0 | CG35: 0 | CI35: 75.62 | CK35: 107.27 | CM35: =ROUND(SUM(CE35:CK35),5) -> 182.89 | CO35: 0 | CQ35: 0 | CS35: =ROUND(SUM(BQ35:CC35)+SUM(CM35:CQ35),5) -> 8569.69 | CU35: =ROUND(BO35+CS35,5) -> 15530.76 | CW35: 0 | CY35: =ROUND(M35+U35+SUM(CU35:CW35),5) -> 15876.61 | CZ35: 10 | DA35: =+CO35+CC35+CA35+BU35+BQ35+AG35 -> 7760 | DC35: =+CQ35+BY35+BW35+BS35+BM35+AS35+AQ35+Y35+W35 -> 7587.87
G36: 6640 · Volunteer Expense | I36: 0 | K36: 2706.6 | M36: =ROUND(SUM(I36:K36),5) -> 2706.6 | O36: 0 | Q36: 0 | S36: 0 | U36: =ROUND(SUM(O36:S36),5) -> 0 | W36: 0 | Y36: 0 | AA36: 0 | AC36: 0 | AE36: 0 | AG36: =ROUND(SUM(AA36:AE36),5) -> 0 | AI36: 0 | AK36: 0 | AM36: 0 | AO36: 0 | AQ36: =ROUND(SUM(AI36:AO36),5) -> 0 | AS36: 0 | AU36: 0 | AW36: 0 | AY36: 0 | BA36: 370.55 | BC36: 0 | BE36: 0 | BG36: 0 | BI36: 0 | BK36: 0 | BM36: =ROUND(SUM(AU36:BK36),5) -> 370.55 | BO36: =ROUND(SUM(W36:Y36)+AG36+SUM(AQ36:AS36)+BM36,5) -> 370.55 | BQ36: 0 | BS36: 0 | BU36: 0 | BW36: 0 | BY36: 0 | CA36: 0 | CC36: 0 | CE36: 0 | CG36: 0 | CI36: 0 | CK36: 0 | CM36: =ROUND(SUM(CE36:CK36),5) -> 0 | CO36: 0 | CQ36: 0 | CS36: =ROUND(SUM(BQ36:CC36)+SUM(CM36:CQ36),5) -> 0 | CU36: =ROUND(BO36+CS36,5) -> 370.55 | CW36: 0 | CY36: =ROUND(M36+U36+SUM(CU36:CW36),5) -> 3077.15 | CZ36: 7 | DA36: =+CO36+CC36+CA36+BU36+BQ36+AG36 -> 0 | DC36: =+CQ36+BY36+BW36+BS36+BM36+AS36+AQ36+Y36+W36 -> 370.55
G37: 6600 · Operating Expenses - Other | I37: 0 | K37: 13.13 | M37: =ROUND(SUM(I37:K37),5) -> 13.13 | O37: 0 | Q37: 0 | S37: 0 | U37: =ROUND(SUM(O37:S37),5) -> 0 | W37: 0 | Y37: 0 | AA37: 0 | AC37: 0 | AE37: 0 | AG37: =ROUND(SUM(AA37:AE37),5) -> 0 | AI37: 0 | AK37: 0 | AM37: 0 | AO37: 0 | AQ37: =ROUND(SUM(AI37:AO37),5) -> 0 | AS37: 0 | AU37: 0 | AW37: 0 | AY37: 0 | BA37: 0 | BC37: 0 | BE37: 0 | BG37: 0 | BI37: 0 | BK37: 0 | BM37: =ROUND(SUM(AU37:BK37),5) -> 0 | BO37: =ROUND(SUM(W37:Y37)+AG37+SUM(AQ37:AS37)+BM37,5) -> 0 | BQ37: 0 | BS37: 0 | BU37: 0 | BW37: 0 | BY37: 0 | CA37: 0 | CC37: 0 | CE37: 0 | CG37: 0 | CI37: 0 | CK37: 0 | CM37: =ROUND(SUM(CE37:CK37),5) -> 0 | CO37: 0 | CQ37: 0 | CS37: =ROUND(SUM(BQ37:CC37)+SUM(CM37:CQ37),5) -> 0 | CU37: =ROUND(BO37+CS37,5) -> 0 | CW37: 0 | CY37: =ROUND(M37+U37+SUM(CU37:CW37),5) -> 13.13 | DA37: =+CO37+CC37+CA37+BU37+BQ37+AG37 -> 0 | DC37: =+CQ37+BY37+BW37+BS37+BM37+AS37+AQ37+Y37+W37 -> 0
F38: Total 6600 · Operating Expenses | I38: =ROUND(SUM(I19:I22)+I27+SUM(I34:I37),5) -> 0 | K38: =ROUND(SUM(K19:K22)+K27+SUM(K34:K37),5) -> 437457.47 | M38: =ROUND(SUM(I38:K38),5) -> 437457.47 | O38: =ROUND(SUM(O19:O22)+O27+SUM(O34:O37),5) -> 88.82 | Q38: =ROUND(SUM(Q19:Q22)+Q27+SUM(Q34:Q37),5) -> 9388.22 | S38: =ROUND(SUM(S19:S22)+S27+SUM(S34:S37),5) -> 56189.19 | U38: =ROUND(SUM(O38:S38),5) -> 65666.23 | W38: =ROUND(SUM(W19:W22)+W27+SUM(W34:W37),5) -> 682.38 | Y38: =ROUND(SUM(Y19:Y22)+Y27+SUM(Y34:Y37),5) -> 8769.72 | AA38: =ROUND(SUM(AA19:AA22)+AA27+SUM(AA34:AA37),5) -> 594.13 | AC38: =ROUND(SUM(AC19:AC22)+AC27+SUM(AC34:AC37),5) -> 0 | AE38: =ROUND(SUM(AE19:AE22)+AE27+SUM(AE34:AE37),5) -> 0 | AG38: =ROUND(SUM(AA38:AE38),5) -> 594.13 | AI38: =ROUND(SUM(AI19:AI22)+AI27+SUM(AI34:AI37),5) -> 3202.61 | AK38: =ROUND(SUM(AK19:AK22)+AK27+SUM(AK34:AK37),5) -> 305.87 | AM38: =ROUND(SUM(AM19:AM22)+AM27+SUM(AM34:AM37),5) -> 0 | AO38: =ROUND(SUM(AO19:AO22)+AO27+SUM(AO34:AO37),5) -> 435.99 | AQ38: =ROUND(SUM(AI38:AO38),5) -> 3944.47 | AS38: =ROUND(SUM(AS19:AS22)+AS27+SUM(AS34:AS37),5) -> 538.34 | AU38: =ROUND(SUM(AU19:AU22)+AU27+SUM(AU34:AU37),5) -> 0 | AW38: =ROUND(SUM(AW19:AW22)+AW27+SUM(AW34:AW37),5) -> 1516.09 | AY38: =ROUND(SUM(AY19:AY22)+AY27+SUM(AY34:AY37),5) -> 562.12 | BA38: =ROUND(SUM(BA19:BA22)+BA27+SUM(BA34:BA37),5) -> 3308.88 | BC38: =ROUND(SUM(BC19:BC22)+BC27+SUM(BC34:BC37),5) -> 564.48 | BE38: =ROUND(SUM(BE19:BE22)+BE27+SUM(BE34:BE37),5) -> 18467.84 | BG38: =ROUND(SUM(BG19:BG22)+BG27+SUM(BG34:BG37),5) -> 0 | BI38: =ROUND(SUM(BI19:BI22)+BI27+SUM(BI34:BI37),5) -> 0 | BK38: =ROUND(SUM(BK19:BK22)+BK27+SUM(BK34:BK37),5) -> 2379 | BM38: =ROUND(SUM(AU38:BK38),5) -> 26798.41 | BO38: =ROUND(SUM(W38:Y38)+AG38+SUM(AQ38:AS38)+BM38,5) -> 41327.45 | BQ38: =ROUND(SUM(BQ19:BQ22)+BQ27+SUM(BQ34:BQ37),5) -> 105803.99 | BS38: =ROUND(SUM(BS19:BS22)+BS27+SUM(BS34:BS37),5) -> 0 | BU38: =ROUND(SUM(BU19:BU22)+BU27+SUM(BU34:BU37),5) -> 0 | BW38: =ROUND(SUM(BW19:BW22)+BW27+SUM(BW34:BW37),5) -> 38439.85 | BY38: =ROUND(SUM(BY19:BY22)+BY27+SUM(BY34:BY37),5) -> 0 | CA38: =ROUND(SUM(CA19:CA22)+CA27+SUM(CA34:CA37),5) -> 11248.65 | CC38: =ROUND(SUM(CC19:CC22)+CC27+SUM(CC34:CC37),5) -> 0 | CE38: =ROUND(SUM(CE19:CE22)+CE27+SUM(CE34:CE37),5) -> 0 | CG38: =ROUND(SUM(CG19:CG22)+CG27+SUM(CG34:CG37),5) -> 55.72 | CI38: =ROUND(SUM(CI19:CI22)+CI27+SUM(CI34:CI37),5) -> 8250.51 | CK38: =ROUND(SUM(CK19:CK22)+CK27+SUM(CK34:CK37),5) -> 5376.05 | CM38: =ROUND(SUM(CE38:CK38),5) -> 13682.28 | CO38: =ROUND(SUM(CO19:CO22)+CO27+SUM(CO34:CO37),5) -> 826.39 | CQ38: =ROUND(SUM(CQ19:CQ22)+CQ27+SUM(CQ34:CQ37),5) -> 0 | CS38: =ROUND(SUM(BQ38:CC38)+SUM(CM38:CQ38),5) -> 170001.16 | CU38: =ROUND(BO38+CS38,5) -> 211328.61 | CW38: =ROUND(SUM(CW19:CW22)+CW27+SUM(CW34:CW37),5) -> 0 | CY38: =ROUND(M38+U38+SUM(CU38:CW38),5) -> 714452.31 | DA38: =+CO38+CC38+CA38+BU38+BQ38+AG38 -> 118473.16 | DC38: =+CQ38+BY38+BW38+BS38+BM38+AS38+AQ38+Y38+W38 -> 79173.17
F39: 6500 · Facility Expense | DA39: =+CO39+CC39+CA39+BU39+BQ39+AG39 -> 0 | DC39: =+CQ39+BY39+BW39+BS39+BM39+AS39+AQ39+Y39+W39 -> 0
G40: 6514 · Security | I40: 31653.96 | K40: 0 | M40: =ROUND(SUM(I40:K40),5) -> 31653.96 | O40: 0 | Q40: 0 | S40: 0 | U40: =ROUND(SUM(O40:S40),5) -> 0 | W40: 0 | Y40: 0 | AA40: 0 | AC40: 0 | AE40: 0 | AG40: =ROUND(SUM(AA40:AE40),5) -> 0 | AI40: 0 | AK40: 0 | AM40: 0 | AO40: 0 | AQ40: =ROUND(SUM(AI40:AO40),5) -> 0 | AS40: 0 | AU40: 0 | AW40: 0 | AY40: 0 | BA40: 0 | BC40: 0 | BE40: 0 | BG40: 0 | BI40: 0 | BK40: 0 | BM40: =ROUND(SUM(AU40:BK40),5) -> 0 | BO40: =ROUND(SUM(W40:Y40)+AG40+SUM(AQ40:AS40)+BM40,5) -> 0 | BQ40: 0 | BS40: 0 | BU40: 0 | BW40: 0 | BY40: 0 | CA40: 0 | CC40: 0 | CE40: 0 | CG40: 0 | CI40: 0 | CK40: 0 | CM40: =ROUND(SUM(CE40:CK40),5) -> 0 | CO40: 48540.04 | CQ40: 0 | CS40: =ROUND(SUM(BQ40:CC40)+SUM(CM40:CQ40),5) -> 48540.04 | CU40: =ROUND(BO40+CS40,5) -> 48540.04 | CW40: 0 | CY40: =ROUND(M40+U40+SUM(CU40:CW40),5) -> 80194 | CZ40: 7 | DA40: =+CO40+CC40+CA40+BU40+BQ40+AG40 -> 48540.04 | DC40: =+CQ40+BY40+BW40+BS40+BM40+AS40+AQ40+Y40+W40 -> 0
G41: 6590 · Depreciation Expense | I41: 0 | K41: 3285 | M41: =ROUND(SUM(I41:K41),5) -> 3285 | O41: 0 | Q41: 0 | S41: 0 | U41: =ROUND(SUM(O41:S41),5) -> 0 | W41: 0 | Y41: 0 | AA41: 0 | AC41: 0 | AE41: 0 | AG41: =ROUND(SUM(AA41:AE41),5) -> 0 | AI41: 0 | AK41: 0 | AM41: 0 | AO41: 0 | AQ41: =ROUND(SUM(AI41:AO41),5) -> 0 | AS41: 0 | AU41: 0 | AW41: 0 | AY41: 0 | BA41: 0 | BC41: 0 | BE41: 0 | BG41: 0 | BI41: 0 | BK41: 0 | BM41: =ROUND(SUM(AU41:BK41),5) -> 0 | BO41: =ROUND(SUM(W41:Y41)+AG41+SUM(AQ41:AS41)+BM41,5) -> 0 | BQ41: 0 | BS41: 0 | BU41: 0 | BW41: 0 | BY41: 0 | CA41: 0 | CC41: 0 | CE41: 0 | CG41: 0 | CI41: 0 | CK41: 0 | CM41: =ROUND(SUM(CE41:CK41),5) -> 0 | CO41: 0 | CQ41: 0 | CS41: =ROUND(SUM(BQ41:CC41)+SUM(CM41:CQ41),5) -> 0 | CU41: =ROUND(BO41+CS41,5) -> 0 | CW41: 0 | CY41: =ROUND(M41+U41+SUM(CU41:CW41),5) -> 3285 | CZ41: 11 | DA41: =+CO41+CC41+CA41+BU41+BQ41+AG41 -> 0 | DC41: =+CQ41+BY41+BW41+BS41+BM41+AS41+AQ41+Y41+W41 -> 0
G42: 6504 · Storage - Admin | I42: 0 | K42: 0 | M42: =ROUND(SUM(I42:K42),5) -> 0 | O42: 0 | Q42: 0 | S42: 0 | U42: =ROUND(SUM(O42:S42),5) -> 0 | W42: 0 | Y42: 0 | AA42: 0 | AC42: 0 | AE42: 0 | AG42: =ROUND(SUM(AA42:AE42),5) -> 0 | AI42: 0 | AK42: 0 | AM42: 0 | AO42: 0 | AQ42: =ROUND(SUM(AI42:AO42),5) -> 0 | AS42: 0 | AU42: 0 | AW42: 0 | AY42: 0 | BA42: 2142 | BC42: 0 | BE42: 0 | BG42: 0 | BI42: 0 | BK42: 0 | BM42: =ROUND(SUM(AU42:BK42),5) -> 2142 | BO42: =ROUND(SUM(W42:Y42)+AG42+SUM(AQ42:AS42)+BM42,5) -> 2142 | BQ42: 0 | BS42: 0 | BU42: 0 | BW42: 0 | BY42: 0 | CA42: 0 | CC42: 0 | CE42: 0 | CG42: 0 | CI42: 0 | CK42: 0 | CM42: =ROUND(SUM(CE42:CK42),5) -> 0 | CO42: 0 | CQ42: 0 | CS42: =ROUND(SUM(BQ42:CC42)+SUM(CM42:CQ42),5) -> 0 | CU42: =ROUND(BO42+CS42,5) -> 2142 | CW42: 0 | CY42: =ROUND(M42+U42+SUM(CU42:CW42),5) -> 2142 | CZ42: 7 | DA42: =+CO42+CC42+CA42+BU42+BQ42+AG42 -> 0 | DC42: =+CQ42+BY42+BW42+BS42+BM42+AS42+AQ42+Y42+W42 -> 2142
G43: 6506 · Repairs & Maint | I43: 0 | K43: 6806.21 | M43: =ROUND(SUM(I43:K43),5) -> 6806.21 | O43: 0 | Q43: 0 | S43: 244.59 | U43: =ROUND(SUM(O43:S43),5) -> 244.59 | W43: 0 | Y43: 0 | AA43: 0 | AC43: 0 | AE43: 0 | AG43: =ROUND(SUM(AA43:AE43),5) -> 0 | AI43: 0 | AK43: 0 | AM43: 0 | AO43: 0 | AQ43: =ROUND(SUM(AI43:AO43),5) -> 0 | AS43: 0 | AU43: 0 | AW43: 0 | AY43: 0 | BA43: 103 | BC43: 0 | BE43: 451 | BG43: 0 | BI43: 0 | BK43: 0 | BM43: =ROUND(SUM(AU43:BK43),5) -> 554 | BO43: =ROUND(SUM(W43:Y43)+AG43+SUM(AQ43:AS43)+BM43,5) -> 554 | BQ43: 1298.04 | BS43: 0 | BU43: 0 | BW43: 2125.36 | BY43: 0 | CA43: 0 | CC43: 0 | CE43: 0 | CG43: 0 | CI43: 0 | CK43: 276.97 | CM43: =ROUND(SUM(CE43:CK43),5) -> 276.97 | CO43: 0 | CQ43: 0 | CS43: =ROUND(SUM(BQ43:CC43)+SUM(CM43:CQ43),5) -> 3700.37 | CU43: =ROUND(BO43+CS43,5) -> 4254.37 | CW43: 0 | CY43: =ROUND(M43+U43+SUM(CU43:CW43),5) -> 11305.17 | CZ43: 7 | DA43: =+CO43+CC43+CA43+BU43+BQ43+AG43 -> 1298.04 | DC43: =+CQ43+BY43+BW43+BS43+BM43+AS43+AQ43+Y43+W43 -> 2679.36
G44: 6508 · Property Insurance | I44: 0 | K44: 882.91 | M44: =ROUND(SUM(I44:K44),5) -> 882.91 | O44: 0 | Q44: 0 | S44: 575.85 | U44: =ROUND(SUM(O44:S44),5) -> 575.85 | W44: 0 | Y44: 0 | AA44: 0 | AC44: 0 | AE44: 0 | AG44: =ROUND(SUM(AA44:AE44),5) -> 0 | AI44: 0 | AK44: 0 | AM44: 0 | AO44: 0 | AQ44: =ROUND(SUM(AI44:AO44),5) -> 0 | AS44: 0 | AU44: 0 | AW44: 0 | AY44: 0 | BA44: 0 | BC44: 0 | BE44: 0 | BG44: 0 | BI44: 0 | BK44: 0 | BM44: =ROUND(SUM(AU44:BK44),5) -> 0 | BO44: =ROUND(SUM(W44:Y44)+AG44+SUM(AQ44:AS44)+BM44,5) -> 0 | BQ44: 3375.1 | BS44: 0 | BU44: 0 | BW44: 3847.63 | BY44: 0 | CA44: 0 | CC44: 0 | CE44: 0 | CG44: 0 | CI44: 0 | CK44: 768.62 | CM44: =ROUND(SUM(CE44:CK44),5) -> 768.62 | CO44: 0 | CQ44: 0 | CS44: =ROUND(SUM(BQ44:CC44)+SUM(CM44:CQ44),5) -> 7991.35 | CU44: =ROUND(BO44+CS44,5) -> 7991.35 | CW44: 0 | CY44: =ROUND(M44+U44+SUM(CU44:CW44),5) -> 9450.11 | CZ44: 12 | DA44: =+CO44+CC44+CA44+BU44+BQ44+AG44 -> 3375.1 | DC44: =+CQ44+BY44+BW44+BS44+BM44+AS44+AQ44+Y44+W44 -> 3847.63
G45: 6510 · IT/Internet Service | I45: 0 | K45: 56404.39 | M45: =ROUND(SUM(I45:K45),5) -> 56404.39 | O45: 0 | Q45: 0 | S45: 2107.56 | U45: =ROUND(SUM(O45:S45),5) -> 2107.56 | W45: 952.89 | Y45: 647.81 | AA45: 0 | AC45: 0 | AE45: 0 | AG45: =ROUND(SUM(AA45:AE45),5) -> 0 | AI45: 0 | AK45: 3401.02 | AM45: 718.84 | AO45: 3232.51 | AQ45: =ROUND(SUM(AI45:AO45),5) -> 7352.37 | AS45: 786.09 | AU45: 0 | AW45: 2040.57 | AY45: 476.84 | BA45: 603.05 | BC45: 741.45 | BE45: 2789.3 | BG45: 0 | BI45: 0 | BK45: 0 | BM45: =ROUND(SUM(AU45:BK45),5) -> 6651.21 | BO45: =ROUND(SUM(W45:Y45)+AG45+SUM(AQ45:AS45)+BM45,5) -> 16390.37 | BQ45: 17024.37 | BS45: 0 | BU45: 0 | BW45: 7132.42 | BY45: 0 | CA45: 2013.88 | CC45: 0 | CE45: 0 | CG45: 0 | CI45: 0 | CK45: 3081.76 | CM45: =ROUND(SUM(CE45:CK45),5) -> 3081.76 | CO45: 841.13 | CQ45: 0 | CS45: =ROUND(SUM(BQ45:CC45)+SUM(CM45:CQ45),5) -> 30093.56 | CU45: =ROUND(BO45+CS45,5) -> 46483.93 | CW45: 0 | CY45: =ROUND(M45+U45+SUM(CU45:CW45),5) -> 104995.88 | CZ45: 8 | DA45: =+CO45+CC45+CA45+BU45+BQ45+AG45 -> 19879.38 | DC45: =+CQ45+BY45+BW45+BS45+BM45+AS45+AQ45+Y45+W45 -> 23522.79
G46: 6512 · Occupancy | I46: 0 | K46: 13237.21 | M46: =ROUND(SUM(I46:K46),5) -> 13237.21 | O46: 0 | Q46: 0 | S46: 7414.28 | U46: =ROUND(SUM(O46:S46),5) -> 7414.28 | W46: 0 | Y46: 14033.6 | AA46: 0 | AC46: 0 | AE46: 0 | AG46: =ROUND(SUM(AA46:AE46),5) -> 0 | AI46: 0 | AK46: 0 | AM46: 0 | AO46: 0 | AQ46: =ROUND(SUM(AI46:AO46),5) -> 0 | AS46: 0 | AU46: 0 | AW46: 2019.88 | AY46: 703.72 | BA46: 14803.98 | BC46: 0 | BE46: 7357.71 | BG46: 0 | BI46: 0 | BK46: 0 | BM46: =ROUND(SUM(AU46:BK46),5) -> 24885.29 | BO46: =ROUND(SUM(W46:Y46)+AG46+SUM(AQ46:AS46)+BM46,5) -> 38918.89 | BQ46: 125122.66 | BS46: 0 | BU46: 0 | BW46: 45848.54 | BY46: 0 | CA46: 0 | CC46: 0 | CE46: 0 | CG46: 0 | CI46: 0 | CK46: 47415.43 | CM46: =ROUND(SUM(CE46:CK46),5) -> 47415.43 | CO46: 0 | CQ46: 0 | CS46: =ROUND(SUM(BQ46:CC46)+SUM(CM46:CQ46),5) -> 218386.63 | CU46: =ROUND(BO46+CS46,5) -> 257305.52 | CW46: 0 | CY46: =ROUND(M46+U46+SUM(CU46:CW46),5) -> 277957.01 | CZ46: 9 | DA46: =+CO46+CC46+CA46+BU46+BQ46+AG46 -> 125122.66 | DC46: =+CQ46+BY46+BW46+BS46+BM46+AS46+AQ46+Y46+W46 -> 84767.43
F47: Total 6500 · Facility Expense | I47: =ROUND(SUM(I39:I46),5) -> 31653.96 | K47: =ROUND(SUM(K39:K46),5) -> 80615.72 | M47: =ROUND(SUM(I47:K47),5) -> 112269.68 | O47: =ROUND(SUM(O39:O46),5) -> 0 | Q47: =ROUND(SUM(Q39:Q46),5) -> 0 | S47: =ROUND(SUM(S39:S46),5) -> 10342.28 | U47: =ROUND(SUM(O47:S47),5) -> 10342.28 | W47: =ROUND(SUM(W39:W46),5) -> 952.89 | Y47: =ROUND(SUM(Y39:Y46),5) -> 14681.41 | AA47: =ROUND(SUM(AA39:AA46),5) -> 0 | AC47: =ROUND(SUM(AC39:AC46),5) -> 0 | AE47: =ROUND(SUM(AE39:AE46),5) -> 0 | AG47: =ROUND(SUM(AA47:AE47),5) -> 0 | AI47: =ROUND(SUM(AI39:AI46),5) -> 0 | AK47: =ROUND(SUM(AK39:AK46),5) -> 3401.02 | AM47: =ROUND(SUM(AM39:AM46),5) -> 718.84 | AO47: =ROUND(SUM(AO39:AO46),5) -> 3232.51 | AQ47: =ROUND(SUM(AI47:AO47),5) -> 7352.37 | AS47: =ROUND(SUM(AS39:AS46),5) -> 786.09 | AU47: =ROUND(SUM(AU39:AU46),5) -> 0 | AW47: =ROUND(SUM(AW39:AW46),5) -> 4060.45 | AY47: =ROUND(SUM(AY39:AY46),5) -> 1180.56 | BA47: =ROUND(SUM(BA39:BA46),5) -> 17652.03 | BC47: =ROUND(SUM(BC39:BC46),5) -> 741.45 | BE47: =ROUND(SUM(BE39:BE46),5) -> 10598.01 | BG47: =ROUND(SUM(BG39:BG46),5) -> 0 | BI47: =ROUND(SUM(BI39:BI46),5) -> 0 | BK47: =ROUND(SUM(BK39:BK46),5) -> 0 | BM47: =ROUND(SUM(AU47:BK47),5) -> 34232.5 | BO47: =ROUND(SUM(W47:Y47)+AG47+SUM(AQ47:AS47)+BM47,5) -> 58005.26 | BQ47: =ROUND(SUM(BQ39:BQ46),5) -> 146820.17 | BS47: =ROUND(SUM(BS39:BS46),5) -> 0 | BU47: =ROUND(SUM(BU39:BU46),5) -> 0 | BW47: =ROUND(SUM(BW39:BW46),5) -> 58953.95 | BY47: =ROUND(SUM(BY39:BY46),5) -> 0 | CA47: =ROUND(SUM(CA39:CA46),5) -> 2013.88 | CC47: =ROUND(SUM(CC39:CC46),5) -> 0 | CE47: =ROUND(SUM(CE39:CE46),5) -> 0 | CG47: =ROUND(SUM(CG39:CG46),5) -> 0 | CI47: =ROUND(SUM(CI39:CI46),5) -> 0 | CK47: =ROUND(SUM(CK39:CK46),5) -> 51542.78 | CM47: =ROUND(SUM(CE47:CK47),5) -> 51542.78 | CO47: =ROUND(SUM(CO39:CO46),5) -> 49381.17 | CQ47: =ROUND(SUM(CQ39:CQ46),5) -> 0 | CS47: =ROUND(SUM(BQ47:CC47)+SUM(CM47:CQ47),5) -> 308711.95 | CU47: =ROUND(BO47+CS47,5) -> 366717.21 | CW47: =ROUND(SUM(CW39:CW46),5) -> 0 | CY47: =ROUND(M47+U47+SUM(CU47:CW47),5) -> 489329.17 | DA47: =+CO47+CC47+CA47+BU47+BQ47+AG47 -> 198215.22 | DC47: =+CQ47+BY47+BW47+BS47+BM47+AS47+AQ47+Y47+W47 -> 116959.21
F48: 6010 · Personnel - Indirect | DA48: =+CO48+CC48+CA48+BU48+BQ48+AG48 -> 0 | DC48: =+CQ48+BY48+BW48+BS48+BM48+AS48+AQ48+Y48+W48 -> 0
G49: 6110 · Indirect Fringe Benefits | DA49: =+CO49+CC49+CA49+BU49+BQ49+AG49 -> 0 | DC49: =+CQ49+BY49+BW49+BS49+BM49+AS49+AQ49+Y49+W49 -> 0
H50: 6118 · Indirect - Retirement Benefits | I50: 0 | K50: -1371.89 | M50: =ROUND(SUM(I50:K50),5) -> -1371.89 | O50: 0 | Q50: 0 | S50: 1816.19 | U50: =ROUND(SUM(O50:S50),5) -> 1816.19 | W50: 1464.9 | Y50: 2151.47 | AA50: 0 | AC50: 0 | AE50: 0 | AG50: =ROUND(SUM(AA50:AE50),5) -> 0 | AI50: 1490.02 | AK50: 4582.93 | AM50: 3625.4 | AO50: 8042.82 | AQ50: =ROUND(SUM(AI50:AO50),5) -> 17741.17 | AS50: 609 | AU50: 0 | AW50: 1160.67 | AY50: 600.48 | BA50: 2041.79 | BC50: 1430 | BE50: 7326.79 | BG50: 0 | BI50: 0 | BK50: 0 | BM50: =ROUND(SUM(AU50:BK50),5) -> 12559.73 | BO50: =ROUND(SUM(W50:Y50)+AG50+SUM(AQ50:AS50)+BM50,5) -> 34526.27 | BQ50: 11927.17 | BS50: 0 | BU50: 611.61 | BW50: 10507.7 | BY50: 0 | CA50: 16352.73 | CC50: 0 | CE50: 0 | CG50: 0 | CI50: 0 | CK50: 3321.33 | CM50: =ROUND(SUM(CE50:CK50),5) -> 3321.33 | CO50: 0 | CQ50: 0 | CS50: =ROUND(SUM(BQ50:CC50)+SUM(CM50:CQ50),5) -> 42720.54 | CU50: =ROUND(BO50+CS50,5) -> 77246.81 | CW50: 15133.87 | CY50: =ROUND(M50+U50+SUM(CU50:CW50),5) -> 92824.98 | CZ50: 3 | DA50: =+CO50+CC50+CA50+BU50+BQ50+AG50 -> 28891.51 | DC50: =+CQ50+BY50+BW50+BS50+BM50+AS50+AQ50+Y50+W50 -> 45033.97
H51: 6117 · Indirect - Benefits Insurance | I51: 0 | K51: 19630.42 | M51: =ROUND(SUM(I51:K51),5) -> 19630.42 | O51: 0 | Q51: 0 | S51: 10256.31 | U51: =ROUND(SUM(O51:S51),5) -> 10256.31 | W51: 7741.32 | Y51: 9228.85 | AA51: 0 | AC51: 0 | AE51: 0 | AG51: =ROUND(SUM(AA51:AE51),5) -> 0 | AI51: 7313.57 | AK51: 16474.69 | AM51: 18275.99 | AO51: 35157.16 | AQ51: =ROUND(SUM(AI51:AO51),5) -> 77221.41 | AS51: 2685 | AU51: 0 | AW51: 7425.58 | AY51: 3482.03 | BA51: 8154.6 | BC51: 5622 | BE51: 32112.71 | BG51: 0 | BI51: 0 | BK51: 0 | BM51: =ROUND(SUM(AU51:BK51),5) -> 56796.92 | BO51: =ROUND(SUM(W51:Y51)+AG51+SUM(AQ51:AS51)+BM51,5) -> 153673.5 | BQ51: 68136.28 | BS51: 0 | BU51: 3514.74 | BW51: 47391 | BY51: 0 | CA51: 59027.77 | CC51: 0 | CE51: 0 | CG51: 0 | CI51: 0 | CK51: 19395.48 | CM51: =ROUND(SUM(CE51:CK51),5) -> 19395.48 | CO51: 0 | CQ51: 0 | CS51: =ROUND(SUM(BQ51:CC51)+SUM(CM51:CQ51),5) -> 197465.27 | CU51: =ROUND(BO51+CS51,5) -> 351138.77 | CW51: 0 | CY51: =ROUND(M51+U51+SUM(CU51:CW51),5) -> 381025.5 | CZ51: 3 | DA51: =+CO51+CC51+CA51+BU51+BQ51+AG51 -> 130678.79 | DC51: =+CQ51+BY51+BW51+BS51+BM51+AS51+AQ51+Y51+W51 -> 201064.5
H52: 6116 · Indirect - Workers Comp Ins | I52: 0 | K52: 47156.07 | M52: =ROUND(SUM(I52:K52),5) -> 47156.07 | O52: 0 | Q52: 0 | S52: 1790.37 | U52: =ROUND(SUM(O52:S52),5) -> 1790.37 | W52: 0 | Y52: 0 | AA52: 0 | AC52: 0 | AE52: 0 | AG52: =ROUND(SUM(AA52:AE52),5) -> 0 | AI52: 0 | AK52: 0 | AM52: 0 | AO52: 0 | AQ52: =ROUND(SUM(AI52:AO52),5) -> 0 | AS52: 0 | AU52: 0 | AW52: 0 | AY52: 0 | BA52: 0 | BC52: 0 | BE52: 0 | BG52: 0 | BI52: 0 | BK52: 0 | BM52: =ROUND(SUM(AU52:BK52),5) -> 0 | BO52: =ROUND(SUM(W52:Y52)+AG52+SUM(AQ52:AS52)+BM52,5) -> 0 | BQ52: 11830.45 | BS52: 0 | BU52: 590.71 | BW52: 9565.05 | BY52: 0 | CA52: 0 | CC52: 0 | CE52: 0 | CG52: 0 | CI52: 0 | CK52: 3313.73 | CM52: =ROUND(SUM(CE52:CK52),5) -> 3313.73 | CO52: 0 | CQ52: 0 | CS52: =ROUND(SUM(BQ52:CC52)+SUM(CM52:CQ52),5) -> 25299.94 | CU52: =ROUND(BO52+CS52,5) -> 25299.94 | CW52: 0 | CY52: =ROUND(M52+U52+SUM(CU52:CW52),5) -> 74246.38 | CZ52: 3 | DA52: =+CO52+CC52+CA52+BU52+BQ52+AG52 -> 12421.16 | DC52: =+CQ52+BY52+BW52+BS52+BM52+AS52+AQ52+Y52+W52 -> 9565.05
H53: 6115 · Indirect - Payroll Taxes | I53: 0 | K53: 12635.07 | M53: =ROUND(SUM(I53:K53),5) -> 12635.07 | O53: 0 | Q53: 0 | S53: 7261.89 | U53: =ROUND(SUM(O53:S53),5) -> 7261.89 | W53: 4976.75 | Y53: 6716.02 | AA53: 0 | AC53: 0 | AE53: 0 | AG53: =ROUND(SUM(AA53:AE53),5) -> 0 | AI53: 4791.28 | AK53: 10466.57 | AM53: 11965.15 | AO53: 26445.14 | AQ53: =ROUND(SUM(AI53:AO53),5) -> 53668.14 | AS53: 1904 | AU53: 0 | AW53: 4767.46 | AY53: 2189.09 | BA53: 5601 | BC53: 4364 | BE53: 23816.07 | BG53: 0 | BI53: 0 | BK53: 0 | BM53: =ROUND(SUM(AU53:BK53),5) -> 40737.62 | BO53: =ROUND(SUM(W53:Y53)+AG53+SUM(AQ53:AS53)+BM53,5) -> 108002.53 | BQ53: 47473.32 | BS53: 0 | BU53: 2480.02 | BW53: 39456.96 | BY53: 0 | CA53: 41523.12 | CC53: 0 | CE53: 0 | CG53: 0 | CI53: 0 | CK53: 13408.46 | CM53: =ROUND(SUM(CE53:CK53),5) -> 13408.46 | CO53: 0 | CQ53: 0 | CS53: =ROUND(SUM(BQ53:CC53)+SUM(CM53:CQ53),5) -> 144341.88 | CU53: =ROUND(BO53+CS53,5) -> 252344.41 | CW53: 0 | CY53: =ROUND(M53+U53+SUM(CU53:CW53),5) -> 272241.37 | CZ53: 2 | DA53: =+CO53+CC53+CA53+BU53+BQ53+AG53 -> 91476.46 | DC53: =+CQ53+BY53+BW53+BS53+BM53+AS53+AQ53+Y53+W53 -> 147459.49
G54: Total 6110 · Indirect Fringe Benefits | I54: =ROUND(SUM(I49:I53),5) -> 0 | K54: =ROUND(SUM(K49:K53),5) -> 78049.67 | M54: =ROUND(SUM(I54:K54),5) -> 78049.67 | O54: =ROUND(SUM(O49:O53),5) -> 0 | Q54: =ROUND(SUM(Q49:Q53),5) -> 0 | S54: =ROUND(SUM(S49:S53),5) -> 21124.76 | U54: =ROUND(SUM(O54:S54),5) -> 21124.76 | W54: =ROUND(SUM(W49:W53),5) -> 14182.97 | Y54: =ROUND(SUM(Y49:Y53),5) -> 18096.34 | AA54: =ROUND(SUM(AA49:AA53),5) -> 0 | AC54: =ROUND(SUM(AC49:AC53),5) -> 0 | AE54: =ROUND(SUM(AE49:AE53),5) -> 0 | AG54: =ROUND(SUM(AA54:AE54),5) -> 0 | AI54: =ROUND(SUM(AI49:AI53),5) -> 13594.87 | AK54: =ROUND(SUM(AK49:AK53),5) -> 31524.19 | AM54: =ROUND(SUM(AM49:AM53),5) -> 33866.54 | AO54: =ROUND(SUM(AO49:AO53),5) -> 69645.12 | AQ54: =ROUND(SUM(AI54:AO54),5) -> 148630.72 | AS54: =ROUND(SUM(AS49:AS53),5) -> 5198 | AU54: =ROUND(SUM(AU49:AU53),5) -> 0 | AW54: =ROUND(SUM(AW49:AW53),5) -> 13353.71 | AY54: =ROUND(SUM(AY49:AY53),5) -> 6271.6 | BA54: =ROUND(SUM(BA49:BA53),5) -> 15797.39 | BC54: =ROUND(SUM(BC49:BC53),5) -> 11416 | BE54: =ROUND(SUM(BE49:BE53),5) -> 63255.57 | BG54: =ROUND(SUM(BG49:BG53),5) -> 0 | BI54: =ROUND(SUM(BI49:BI53),5) -> 0 | BK54: =ROUND(SUM(BK49:BK53),5) -> 0 | BM54: =ROUND(SUM(AU54:BK54),5) -> 110094.27 | BO54: =ROUND(SUM(W54:Y54)+AG54+SUM(AQ54:AS54)+BM54,5) -> 296202.3 | BQ54: =ROUND(SUM(BQ49:BQ53),5) -> 139367.22 | BS54: =ROUND(SUM(BS49:BS53),5) -> 0 | BU54: =ROUND(SUM(BU49:BU53),5) -> 7197.08 | BW54: =ROUND(SUM(BW49:BW53),5) -> 106920.71 | BY54: =ROUND(SUM(BY49:BY53),5) -> 0 | CA54: =ROUND(SUM(CA49:CA53),5) -> 116903.62 | CC54: =ROUND(SUM(CC49:CC53),5) -> 0 | CE54: =ROUND(SUM(CE49:CE53),5) -> 0 | CG54: =ROUND(SUM(CG49:CG53),5) -> 0 | CI54: =ROUND(SUM(CI49:CI53),5) -> 0 | CK54: =ROUND(SUM(CK49:CK53),5) -> 39439 | CM54: =ROUND(SUM(CE54:CK54),5) -> 39439 | CO54: =ROUND(SUM(CO49:CO53),5) -> 0 | CQ54: =ROUND(SUM(CQ49:CQ53),5) -> 0 | CS54: =ROUND(SUM(BQ54:CC54)+SUM(CM54:CQ54),5) -> 409827.63 | CU54: =ROUND(BO54+CS54,5) -> 706029.93 | CW54: =ROUND(SUM(CW49:CW53),5) -> 15133.87 | CY54: =ROUND(M54+U54+SUM(CU54:CW54),5) -> 820338.23 | DA54: =+CO54+CC54+CA54+BU54+BQ54+AG54 -> 263467.92 | DC54: =+CQ54+BY54+BW54+BS54+BM54+AS54+AQ54+Y54+W54 -> 403123.01
G55: 6011 · Indirect Wages | I55: 0 | K55: 352108.33 | M55: =ROUND(SUM(I55:K55),5) -> 352108.33 | O55: 0 | Q55: 0 | S55: 201392.13 | U55: =ROUND(SUM(O55:S55),5) -> 201392.13 | W55: 138797.57 | Y55: 90473.09 | AA55: 84088.62 | AC55: 78548.5 | AE55: 0 | AG55: =ROUND(SUM(AA55:AE55),5) -> 162637.12 | AI55: 64736.6 | AK55: 153238.54 | AM55: 157411.26 | AO55: 333825 | AQ55: =ROUND(SUM(AI55:AO55),5) -> 709211.4 | AS55: 62472.61 | AU55: 0 | AW55: 68056 | AY55: 42647.24 | BA55: 91019.21 | BC55: 57083 | BE55: 344060.63 | BG55: 0 | BI55: 0 | BK55: 0 | BM55: =ROUND(SUM(AU55:BK55),5) -> 602866.08 | BO55: =ROUND(SUM(W55:Y55)+AG55+SUM(AQ55:AS55)+BM55,5) -> 1766457.9 | BQ55: 342536.77 | BS55: 0 | BU55: 68819.33 | BW55: 15327.88 | BY55: 0 | CA55: 484180.25 | CC55: 0 | CE55: 0 | CG55: 0 | CI55: 0 | CK55: 149929.28 | CM55: =ROUND(SUM(CE55:CK55),5) -> 149929.28 | CO55: 0 | CQ55: 0 | CS55: =ROUND(SUM(BQ55:CC55)+SUM(CM55:CQ55),5) -> 1060793.5 | CU55: =ROUND(BO55+CS55,5) -> 2827251.4 | CW55: 0 | CY55: =ROUND(M55+U55+SUM(CU55:CW55),5) -> 3380751.8 | CZ55: 1 | DA55: =+CO55+CC55+CA55+BU55+BQ55+AG55 -> 1058173.5 | DC55: =+CQ55+BY55+BW55+BS55+BM55+AS55+AQ55+Y55+W55 -> 1619148.6
G56: 6135 · Staffing & Hiring | I56: 0 | K56: 3524 | M56: =ROUND(SUM(I56:K56),5) -> 3524 | O56: 0 | Q56: 0 | S56: 100 | U56: =ROUND(SUM(O56:S56),5) -> 100 | W56: 0 | Y56: 0 | AA56: 0 | AC56: 0 | AE56: 0 | AG56: =ROUND(SUM(AA56:AE56),5) -> 0 | AI56: 0 | AK56: 0 | AM56: 0 | AO56: 0 | AQ56: =ROUND(SUM(AI56:AO56),5) -> 0 | AS56: 0 | AU56: 0 | AW56: 0 | AY56: 0 | BA56: 0 | BC56: 0 | BE56: 0 | BG56: 0 | BI56: 0 | BK56: 0 | BM56: =ROUND(SUM(AU56:BK56),5) -> 0 | BO56: =ROUND(SUM(W56:Y56)+AG56+SUM(AQ56:AS56)+BM56,5) -> 0 | BQ56: 766 | BS56: 0 | BU56: 0 | BW56: 0 | BY56: 0 | CA56: 0 | CC56: 0 | CE56: 0 | CG56: 0 | CI56: 0 | CK56: 468 | CM56: =ROUND(SUM(CE56:CK56),5) -> 468 | CO56: 0 | CQ56: 0 | CS56: =ROUND(SUM(BQ56:CC56)+SUM(CM56:CQ56),5) -> 1234 | CU56: =ROUND(BO56+CS56,5) -> 1234 | CW56: 0 | CY56: =ROUND(M56+U56+SUM(CU56:CW56),5) -> 4858 | CZ56: 5 | DA56: =+CO56+CC56+CA56+BU56+BQ56+AG56 -> 766 | DC56: =+CQ56+BY56+BW56+BS56+BM56+AS56+AQ56+Y56+W56 -> 0
F57: Total 6010 · Personnel - Indirect | I57: =ROUND(I48+SUM(I54:I56),5) -> 0 | K57: =ROUND(K48+SUM(K54:K56),5) -> 433682 | M57: =ROUND(SUM(I57:K57),5) -> 433682 | O57: =ROUND(O48+SUM(O54:O56),5) -> 0 | Q57: =ROUND(Q48+SUM(Q54:Q56),5) -> 0 | S57: =ROUND(S48+SUM(S54:S56),5) -> 222616.89 | U57: =ROUND(SUM(O57:S57),5) -> 222616.89 | W57: =ROUND(W48+SUM(W54:W56),5) -> 152980.54 | Y57: =ROUND(Y48+SUM(Y54:Y56),5) -> 108569.43 | AA57: =ROUND(AA48+SUM(AA54:AA56),5) -> 84088.62 | AC57: =ROUND(AC48+SUM(AC54:AC56),5) -> 78548.5 | AE57: =ROUND(AE48+SUM(AE54:AE56),5) -> 0 | AG57: =ROUND(SUM(AA57:AE57),5) -> 162637.12 | AI57: =ROUND(AI48+SUM(AI54:AI56),5) -> 78331.47 | AK57: =ROUND(AK48+SUM(AK54:AK56),5) -> 184762.73 | AM57: =ROUND(AM48+SUM(AM54:AM56),5) -> 191277.8 | AO57: =ROUND(AO48+SUM(AO54:AO56),5) -> 403470.12 | AQ57: =ROUND(SUM(AI57:AO57),5) -> 857842.12 | AS57: =ROUND(AS48+SUM(AS54:AS56),5) -> 67670.61 | AU57: =ROUND(AU48+SUM(AU54:AU56),5) -> 0 | AW57: =ROUND(AW48+SUM(AW54:AW56),5) -> 81409.71 | AY57: =ROUND(AY48+SUM(AY54:AY56),5) -> 48918.84 | BA57: =ROUND(BA48+SUM(BA54:BA56),5) -> 106816.6 | BC57: =ROUND(BC48+SUM(BC54:BC56),5) -> 68499 | BE57: =ROUND(BE48+SUM(BE54:BE56),5) -> 407316.2 | BG57: =ROUND(BG48+SUM(BG54:BG56),5) -> 0 | BI57: =ROUND(BI48+SUM(BI54:BI56),5) -> 0 | BK57: =ROUND(BK48+SUM(BK54:BK56),5) -> 0 | BM57: =ROUND(SUM(AU57:BK57),5) -> 712960.35 | BO57: =ROUND(SUM(W57:Y57)+AG57+SUM(AQ57:AS57)+BM57,5) -> 2062660.2 | BQ57: =ROUND(BQ48+SUM(BQ54:BQ56),5) -> 482669.99 | BS57: =ROUND(BS48+SUM(BS54:BS56),5) -> 0 | BU57: =ROUND(BU48+SUM(BU54:BU56),5) -> 76016.41 | BW57: =ROUND(BW48+SUM(BW54:BW56),5) -> 122248.59 | BY57: =ROUND(BY48+SUM(BY54:BY56),5) -> 0 | CA57: =ROUND(CA48+SUM(CA54:CA56),5) -> 601083.87 | CC57: =ROUND(CC48+SUM(CC54:CC56),5) -> 0 | CE57: =ROUND(CE48+SUM(CE54:CE56),5) -> 0 | CG57: =ROUND(CG48+SUM(CG54:CG56),5) -> 0 | CI57: =ROUND(CI48+SUM(CI54:CI56),5) -> 0 | CK57: =ROUND(CK48+SUM(CK54:CK56),5) -> 189836.28 | CM57: =ROUND(SUM(CE57:CK57),5) -> 189836.28 | CO57: =ROUND(CO48+SUM(CO54:CO56),5) -> 0 | CQ57: =ROUND(CQ48+SUM(CQ54:CQ56),5) -> 0 | CS57: =ROUND(SUM(BQ57:CC57)+SUM(CM57:CQ57),5) -> 1471855.1 | CU57: =ROUND(BO57+CS57,5) -> 3534515.3 | CW57: =ROUND(CW48+SUM(CW54:CW56),5) -> 15133.87 | CY57: =ROUND(M57+U57+SUM(CU57:CW57),5) -> 4205948.1 | DA57: =+CO57+CC57+CA57+BU57+BQ57+AG57 -> 1322407.4 | DC57: =+CQ57+BY57+BW57+BS57+BM57+AS57+AQ57+Y57+W57 -> 2022271.6
E58: Total 6000 · Indirect Costs | I58: =ROUND(I18+I38+I47+I57,5) -> 31653.96 | K58: =ROUND(K18+K38+K47+K57,5) -> 951755.19 | M58: =ROUND(SUM(I58:K58),5) -> 983409.15 | O58: =ROUND(O18+O38+O47+O57,5) -> 88.82 | Q58: =ROUND(Q18+Q38+Q47+Q57,5) -> 9388.22 | S58: =ROUND(S18+S38+S47+S57,5) -> 289148.36 | U58: =ROUND(SUM(O58:S58),5) -> 298625.4 | W58: =ROUND(W18+W38+W47+W57,5) -> 154615.81 | Y58: =ROUND(Y18+Y38+Y47+Y57,5) -> 132020.56 | AA58: =ROUND(AA18+AA38+AA47+AA57,5) -> 84682.75 | AC58: =ROUND(AC18+AC38+AC47+AC57,5) -> 78548.5 | AE58: =ROUND(AE18+AE38+AE47+AE57,5) -> 0 | AG58: =ROUND(SUM(AA58:AE58),5) -> 163231.25 | AI58: =ROUND(AI18+AI38+AI47+AI57,5) -> 81534.08 | AK58: =ROUND(AK18+AK38+AK47+AK57,5) -> 188469.62 | AM58: =ROUND(AM18+AM38+AM47+AM57,5) -> 191996.64 | AO58: =ROUND(AO18+AO38+AO47+AO57,5) -> 407138.62 | AQ58: =ROUND(SUM(AI58:AO58),5) -> 869138.96 | AS58: =ROUND(AS18+AS38+AS47+AS57,5) -> 68995.04 | AU58: =ROUND(AU18+AU38+AU47+AU57,5) -> 0 | AW58: =ROUND(AW18+AW38+AW47+AW57,5) -> 86986.25 | AY58: =ROUND(AY18+AY38+AY47+AY57,5) -> 50661.52 | BA58: =ROUND(BA18+BA38+BA47+BA57,5) -> 127777.51 | BC58: =ROUND(BC18+BC38+BC47+BC57,5) -> 69804.93 | BE58: =ROUND(BE18+BE38+BE47+BE57,5) -> 436382.05 | BG58: =ROUND(BG18+BG38+BG47+BG57,5) -> 0 | BI58: =ROUND(BI18+BI38+BI47+BI57,5) -> 0 | BK58: =ROUND(BK18+BK38+BK47+BK57,5) -> 2379 | BM58: =ROUND(SUM(AU58:BK58),5) -> 773991.26 | BO58: =ROUND(SUM(W58:Y58)+AG58+SUM(AQ58:AS58)+BM58,5) -> 2161992.9 | BQ58: =ROUND(BQ18+BQ38+BQ47+BQ57,5) -> 735294.15 | BS58: =ROUND(BS18+BS38+BS47+BS57,5) -> 0 | BU58: =ROUND(BU18+BU38+BU47+BU57,5) -> 76016.41 | BW58: =ROUND(BW18+BW38+BW47+BW57,5) -> 219642.39 | BY58: =ROUND(BY18+BY38+BY47+BY57,5) -> 0 | CA58: =ROUND(CA18+CA38+CA47+CA57,5) -> 614346.4 | CC58: =ROUND(CC18+CC38+CC47+CC57,5) -> 0 | CE58: =ROUND(CE18+CE38+CE47+CE57,5) -> 0 | CG58: =ROUND(CG18+CG38+CG47+CG57,5) -> 55.72 | CI58: =ROUND(CI18+CI38+CI47+CI57,5) -> 8250.51 | CK58: =ROUND(CK18+CK38+CK47+CK57,5) -> 246755.11 | CM58: =ROUND(SUM(CE58:CK58),5) -> 255061.34 | CO58: =ROUND(CO18+CO38+CO47+CO57,5) -> 50207.56 | CQ58: =ROUND(CQ18+CQ38+CQ47+CQ57,5) -> 0 | CS58: =ROUND(SUM(BQ58:CC58)+SUM(CM58:CQ58),5) -> 1950568.2 | CU58: =ROUND(BO58+CS58,5) -> 4112561.1 | CW58: =ROUND(CW18+CW38+CW47+CW57,5) -> 15133.87 | CY58: =ROUND(M58+U58+SUM(CU58:CW58),5) -> 5409729.5 | DA58: =+CO58+CC58+CA58+BU58+BQ58+AG58 -> 1639095.8 | DC58: =+CQ58+BY58+BW58+BS58+BM58+AS58+AQ58+Y58+W58 -> 2218404
E59: 5000 · Direct Costs | DA59: =+CO59+CC59+CA59+BU59+BQ59+AG59 -> 0 | DC59: =+CQ59+BY59+BW59+BS59+BM59+AS59+AQ59+Y59+W59 -> 0
F60: 5200 · Emergency Assistance | I60: 0 | K60: 1585.18 | M60: =ROUND(SUM(I60:K60),5) -> 1585.18 | O60: 0 | Q60: 0 | S60: 0 | U60: =ROUND(SUM(O60:S60),5) -> 0 | W60: 7080 | Y60: 0 | AA60: 4472663.3 | AC60: 0 | AE60: 7358.96 | AG60: =ROUND(SUM(AA60:AE60),5) -> 4480022.2 | AI60: 326734.59 | AK60: 91091.7 | AM60: 135507.97 | AO60: 161797.44 | AQ60: =ROUND(SUM(AI60:AO60),5) -> 715131.7 | AS60: 12800.64 | AU60: 192909.29 | AW60: 11859.6 | AY60: 29897.89 | BA60: 229858.2 | BC60: 20634.88 | BE60: 175964.15 | BG60: 13325.23 | BI60: 142124.88 | BK60: 0 | BM60: =ROUND(SUM(AU60:BK60),5) -> 816574.12 | BO60: =ROUND(SUM(W60:Y60)+AG60+SUM(AQ60:AS60)+BM60,5) -> 6031608.7 | BQ60: 559.98 | BS60: 10957.32 | BU60: 0 | BW60: 97549.5 | BY60: 60591.6 | CA60: 328901.57 | CC60: 72000 | CE60: 11593.95 | CG60: 26851.96 | CI60: 20003.99 | CK60: 5683.36 | CM60: =ROUND(SUM(CE60:CK60),5) -> 64133.26 | CO60: 0 | CQ60: 15781.43 | CS60: =ROUND(SUM(BQ60:CC60)+SUM(CM60:CQ60),5) -> 650474.66 | CU60: =ROUND(BO60+CS60,5) -> 6682083.4 | CW60: 0 | CY60: =ROUND(M60+U60+SUM(CU60:CW60),5) -> 6683668.5 | CZ60: 4 | DA60: =+CO60+CC60+CA60+BU60+BQ60+AG60 -> 4881483.8 | DC60: =+CQ60+BY60+BW60+BS60+BM60+AS60+AQ60+Y60+W60 -> 1736466.3
E61: Total 5000 · Direct Costs | I61: =ROUND(SUM(I59:I60),5) -> 0 | K61: =ROUND(SUM(K59:K60),5) -> 1585.18 | M61: =ROUND(SUM(I61:K61),5) -> 1585.18 | O61: =ROUND(SUM(O59:O60),5) -> 0 | Q61: =ROUND(SUM(Q59:Q60),5) -> 0 | S61: =ROUND(SUM(S59:S60),5) -> 0 | U61: =ROUND(SUM(O61:S61),5) -> 0 | W61: =ROUND(SUM(W59:W60),5) -> 7080 | Y61: =ROUND(SUM(Y59:Y60),5) -> 0 | AA61: =ROUND(SUM(AA59:AA60),5) -> 4472663.3 | AC61: =ROUND(SUM(AC59:AC60),5) -> 0 | AE61: =ROUND(SUM(AE59:AE60),5) -> 7358.96 | AG61: =ROUND(SUM(AA61:AE61),5) -> 4480022.2 | AI61: =ROUND(SUM(AI59:AI60),5) -> 326734.59 | AK61: =ROUND(SUM(AK59:AK60),5) -> 91091.7 | AM61: =ROUND(SUM(AM59:AM60),5) -> 135507.97 | AO61: =ROUND(SUM(AO59:AO60),5) -> 161797.44 | AQ61: =ROUND(SUM(AI61:AO61),5) -> 715131.7 | AS61: =ROUND(SUM(AS59:AS60),5) -> 12800.64 | AU61: =ROUND(SUM(AU59:AU60),5) -> 192909.29 | AW61: =ROUND(SUM(AW59:AW60),5) -> 11859.6 | AY61: =ROUND(SUM(AY59:AY60),5) -> 29897.89 | BA61: =ROUND(SUM(BA59:BA60),5) -> 229858.2 | BC61: =ROUND(SUM(BC59:BC60),5) -> 20634.88 | BE61: =ROUND(SUM(BE59:BE60),5) -> 175964.15 | BG61: =ROUND(SUM(BG59:BG60),5) -> 13325.23 | BI61: =ROUND(SUM(BI59:BI60),5) -> 142124.88 | BK61: =ROUND(SUM(BK59:BK60),5) -> 0 | BM61: =ROUND(SUM(AU61:BK61),5) -> 816574.12 | BO61: =ROUND(SUM(W61:Y61)+AG61+SUM(AQ61:AS61)+BM61,5) -> 6031608.7 | BQ61: =ROUND(SUM(BQ59:BQ60),5) -> 559.98 | BS61: =ROUND(SUM(BS59:BS60),5) -> 10957.32 | BU61: =ROUND(SUM(BU59:BU60),5) -> 0 | BW61: =ROUND(SUM(BW59:BW60),5) -> 97549.5 | BY61: =ROUND(SUM(BY59:BY60),5) -> 60591.6 | CA61: =ROUND(SUM(CA59:CA60),5) -> 328901.57 | CC61: =ROUND(SUM(CC59:CC60),5) -> 72000 | CE61: =ROUND(SUM(CE59:CE60),5) -> 11593.95 | CG61: =ROUND(SUM(CG59:CG60),5) -> 26851.96 | CI61: =ROUND(SUM(CI59:CI60),5) -> 20003.99 | CK61: =ROUND(SUM(CK59:CK60),5) -> 5683.36 | CM61: =ROUND(SUM(CE61:CK61),5) -> 64133.26 | CO61: =ROUND(SUM(CO59:CO60),5) -> 0 | CQ61: =ROUND(SUM(CQ59:CQ60),5) -> 15781.43 | CS61: =ROUND(SUM(BQ61:CC61)+SUM(CM61:CQ61),5) -> 650474.66 | CU61: =ROUND(BO61+CS61,5) -> 6682083.4 | CW61: =ROUND(SUM(CW59:CW60),5) -> 0 | CY61: =ROUND(M61+U61+SUM(CU61:CW61),5) -> 6683668.5 | DA61: =+CO61+CC61+CA61+BU61+BQ61+AG61 -> 4881483.8 | DC61: =+CQ61+BY61+BW61+BS61+BM61+AS61+AQ61+Y61+W61 -> 1736466.3
D62: Total Expense | I62: =ROUND(I14+I17+I58+I61,5) -> 31653.96 | K62: =ROUND(K14+K17+K58+K61,5) -> 953340.37 | M62: =ROUND(SUM(I62:K62),5) -> 984994.33 | O62: =ROUND(O14+O17+O58+O61,5) -> 88.82 | Q62: =ROUND(Q14+Q17+Q58+Q61,5) -> 9388.22 | S62: =ROUND(S14+S17+S58+S61,5) -> 310396.13 | U62: =ROUND(SUM(O62:S62),5) -> 319873.17 | W62: =ROUND(W14+W17+W58+W61,5) -> 161695.81 | Y62: =ROUND(Y14+Y17+Y58+Y61,5) -> 132020.56 | AA62: =ROUND(AA14+AA17+AA58+AA61,5) -> 4557346 | AC62: =ROUND(AC14+AC17+AC58+AC61,5) -> 78548.5 | AE62: =ROUND(AE14+AE17+AE58+AE61,5) -> 7358.96 | AG62: =ROUND(SUM(AA62:AE62),5) -> 4643253.5 | AI62: =ROUND(AI14+AI17+AI58+AI61,5) -> 408268.67 | AK62: =ROUND(AK14+AK17+AK58+AK61,5) -> 279561.32 | AM62: =ROUND(AM14+AM17+AM58+AM61,5) -> 327504.61 | AO62: =ROUND(AO14+AO17+AO58+AO61,5) -> 568936.06 | AQ62: =ROUND(SUM(AI62:AO62),5) -> 1584270.7 | AS62: =ROUND(AS14+AS17+AS58+AS61,5) -> 81795.68 | AU62: =ROUND(AU14+AU17+AU58+AU61,5) -> 192909.29 | AW62: =ROUND(AW14+AW17+AW58+AW61,5) -> 98845.85 | AY62: =ROUND(AY14+AY17+AY58+AY61,5) -> 80559.41 | BA62: =ROUND(BA14+BA17+BA58+BA61,5) -> 357635.71 | BC62: =ROUND(BC14+BC17+BC58+BC61,5) -> 90439.81 | BE62: =ROUND(BE14+BE17+BE58+BE61,5) -> 612346.2 | BG62: =ROUND(BG14+BG17+BG58+BG61,5) -> 13325.23 | BI62: =ROUND(BI14+BI17+BI58+BI61,5) -> 142124.88 | BK62: =ROUND(BK14+BK17+BK58+BK61,5) -> 2379 | BM62: =ROUND(SUM(AU62:BK62),5) -> 1590565.4 | BO62: =ROUND(SUM(W62:Y62)+AG62+SUM(AQ62:AS62)+BM62,5) -> 8193601.6 | BQ62: =ROUND(BQ14+BQ17+BQ58+BQ61,5) -> 735854.13 | BS62: =ROUND(BS14+BS17+BS58+BS61,5) -> 10957.32 | BU62: =ROUND(BU14+BU17+BU58+BU61,5) -> 76016.41 | BW62: =ROUND(BW14+BW17+BW58+BW61,5) -> 317191.89 | BY62: =ROUND(BY14+BY17+BY58+BY61,5) -> 60591.6 | CA62: =ROUND(CA14+CA17+CA58+CA61,5) -> 943247.97 | CC62: =ROUND(CC14+CC17+CC58+CC61,5) -> 72000 | CE62: =ROUND(CE14+CE17+CE58+CE61,5) -> 11593.95 | CG62: =ROUND(CG14+CG17+CG58+CG61,5) -> 26907.68 | CI62: =ROUND(CI14+CI17+CI58+CI61,5) -> 28254.5 | CK62: =ROUND(CK14+CK17+CK58+CK61,5) -> 252438.47 | CM62: =ROUND(SUM(CE62:CK62),5) -> 319194.6 | CO62: =ROUND(CO14+CO17+CO58+CO61,5) -> 50207.56 | CQ62: =ROUND(CQ14+CQ17+CQ58+CQ61,5) -> 15781.43 | CS62: =ROUND(SUM(BQ62:CC62)+SUM(CM62:CQ62),5) -> 2601042.9 | CU62: =ROUND(BO62+CS62,5) -> 10794644 | CW62: =ROUND(CW14+CW17+CW58+CW61,5) -> 15133.87 | CY62: =ROUND(M62+U62+SUM(CU62:CW62),5) -> 12114646 | DA62: =+CO62+CC62+CA62+BU62+BQ62+AG62 -> 6520579.6 | DC62: =+CQ62+BY62+BW62+BS62+BM62+AS62+AQ62+Y62+W62 -> 3954870.3
B63: Net Ordinary Income | I63: =ROUND(I3+I13-I62,5) -> 0 | K63: =ROUND(K3+K13-K62,5) -> -763684.18 | M63: =ROUND(SUM(I63:K63),5) -> -763684.18 | O63: =ROUND(O3+O13-O62,5) -> 520041.19 | Q63: =ROUND(Q3+Q13-Q62,5) -> 0 | S63: =ROUND(S3+S13-S62,5) -> 330793.57 | U63: =ROUND(SUM(O63:S63),5) -> 850834.76 | W63: =ROUND(W3+W13-W62,5) -> 23775.25 | Y63: =ROUND(Y3+Y13-Y62,5) -> 1142.25 | AA63: =ROUND(AA3+AA13-AA62,5) -> 169942.29 | AC63: =ROUND(AC3+AC13-AC62,5) -> -63681.5 | AE63: =ROUND(AE3+AE13-AE62,5) -> 0 | AG63: =ROUND(SUM(AA63:AE63),5) -> 106260.79 | AI63: =ROUND(AI3+AI13-AI62,5) -> -141934.27 | AK63: =ROUND(AK3+AK13-AK62,5) -> -35384.5 | AM63: =ROUND(AM3+AM13-AM62,5) -> 7888.33 | AO63: =ROUND(AO3+AO13-AO62,5) -> 240844.43 | AQ63: =ROUND(SUM(AI63:AO63),5) -> 71413.99 | AS63: =ROUND(AS3+AS13-AS62,5) -> 12085.7 | AU63: =ROUND(AU3+AU13-AU62,5) -> -70797.6 | AW63: =ROUND(AW3+AW13-AW62,5) -> 6260.07 | AY63: =ROUND(AY3+AY13-AY62,5) -> 3644.08 | BA63: =ROUND(BA3+BA13-BA62,5) -> 2588.81 | BC63: =ROUND(BC3+BC13-BC62,5) -> 6312.07 | BE63: =ROUND(BE3+BE13-BE62,5) -> -25258.66 | BG63: =ROUND(BG3+BG13-BG62,5) -> -6381.84 | BI63: =ROUND(BI3+BI13-BI62,5) -> 71938.79 | BK63: =ROUND(BK3+BK13-BK62,5) -> -1937.69 | BM63: =ROUND(SUM(AU63:BK63),5) -> -13631.97 | BO63: =ROUND(SUM(W63:Y63)+AG63+SUM(AQ63:AS63)+BM63,5) -> 201046.01 | BQ63: =ROUND(BQ3+BQ13-BQ62,5) -> 33502.07 | BS63: =ROUND(BS3+BS13-BS62,5) -> 3866.93 | BU63: =ROUND(BU3+BU13-BU62,5) -> 0 | BW63: =ROUND(BW3+BW13-BW62,5) -> -1150.93 | BY63: =ROUND(BY3+BY13-BY62,5) -> 0 | CA63: =ROUND(CA3+CA13-CA62,5) -> 0 | CC63: =ROUND(CC3+CC13-CC62,5) -> 0 | CE63: =ROUND(CE3+CE13-CE62,5) -> 0 | CG63: =ROUND(CG3+CG13-CG62,5) -> 0 | CI63: =ROUND(CI3+CI13-CI62,5) -> -2716 | CK63: =ROUND(CK3+CK13-CK62,5) -> 0 | CM63: =ROUND(SUM(CE63:CK63),5) -> -2716 | CO63: =ROUND(CO3+CO13-CO62,5) -> 207.56 | CQ63: =ROUND(CQ3+CQ13-CQ62,5) -> 0 | CS63: =ROUND(SUM(BQ63:CC63)+SUM(CM63:CQ63),5) -> 33709.63 | CU63: =ROUND(BO63+CS63,5) -> 234755.64 | CW63: =ROUND(CW3+CW13-CW62,5) -> -15133.87 | CY63: =ROUND(M63+U63+SUM(CU63:CW63),5) -> 306772.35 | DA63: =+CO63+CC63+CA63+BU63+BQ63+AG63 -> 139970.42 | DC63: =+CQ63+BY63+BW63+BS63+BM63+AS63+AQ63+Y63+W63 -> 97501.22
B64: Other Income/Expense | DA64: =+CO64+CC64+CA64+BU64+BQ64+AG64 -> 0 | DC64: =+CQ64+BY64+BW64+BS64+BM64+AS64+AQ64+Y64+W64 -> 0
C65: Other Income | DA65: =+CO65+CC65+CA65+BU65+BQ65+AG65 -> 0 | DC65: =+CQ65+BY65+BW65+BS65+BM65+AS65+AQ65+Y65+W65 -> 0
D66: 7010 · Restricted Activities | DA66: =+CO66+CC66+CA66+BU66+BQ66+AG66 -> 0 | DC66: =+CQ66+BY66+BW66+BS66+BM66+AS66+AQ66+Y66+W66 -> 0
E67: 7012 · Restricted Contributions | I67: 33000 | K67: 0 | M67: =ROUND(SUM(I67:K67),5) -> 33000 | O67: 4450 | Q67: 37100 | S67: 0 | U67: =ROUND(SUM(O67:S67),5) -> 41550 | W67: 0 | Y67: 0 | AA67: 0 | AC67: 0 | AE67: 0 | AG67: =ROUND(SUM(AA67:AE67),5) -> 0 | AI67: 0 | AK67: 0 | AM67: 0 | AO67: 0 | AQ67: =ROUND(SUM(AI67:AO67),5) -> 0 | AS67: 0 | AU67: 0 | AW67: 0 | AY67: 0 | BA67: 0 | BC67: 0 | BE67: 0 | BG67: 0 | BI67: 0 | BK67: 0 | BM67: =ROUND(SUM(AU67:BK67),5) -> 0 | BO67: =ROUND(SUM(W67:Y67)+AG67+SUM(AQ67:AS67)+BM67,5) -> 0 | BQ67: 123325.83 | BS67: 0 | BU67: 75000 | BW67: 107128.42 | BY67: 56500 | CA67: 26097.32 | CC67: 0 | CE67: 18397.53 | CG67: 30558.46 | CI67: 16251.99 | CK67: 63181.65 | CM67: =ROUND(SUM(CE67:CK67),5) -> 128389.63 | CO67: 0 | CQ67: 27136.32 | CS67: =ROUND(SUM(BQ67:CC67)+SUM(CM67:CQ67),5) -> 543577.52 | CU67: =ROUND(BO67+CS67,5) -> 543577.52 | CW67: 0 | CY67: =ROUND(M67+U67+SUM(CU67:CW67),5) -> 618127.52 | DA67: =+CO67+CC67+CA67+BU67+BQ67+AG67 -> 224423.15 | DC67: =+CQ67+BY67+BW67+BS67+BM67+AS67+AQ67+Y67+W67 -> 190764.74
E68: 7014 · Releases From Restrictions | I68: -31653.96 | K68: 0 | M68: =ROUND(SUM(I68:K68),5) -> -31653.96 | O68: 0 | Q68: -9388.22 | S68: 0 | U68: =ROUND(SUM(O68:S68),5) -> -9388.22 | W68: 0 | Y68: 0 | AA68: 0 | AC68: 0 | AE68: 0 | AG68: =ROUND(SUM(AA68:AE68),5) -> 0 | AI68: 0 | AK68: 0 | AM68: 0 | AO68: 0 | AQ68: =ROUND(SUM(AI68:AO68),5) -> 0 | AS68: 0 | AU68: 0 | AW68: 0 | AY68: 0 | BA68: 0 | BC68: 0 | BE68: 0 | BG68: 0 | BI68: 0 | BK68: 0 | BM68: =ROUND(SUM(AU68:BK68),5) -> 0 | BO68: =ROUND(SUM(W68:Y68)+AG68+SUM(AQ68:AS68)+BM68,5) -> 0 | BQ68: -656437.95 | BS68: -14824.25 | BU68: -76016.41 | BW68: -309217.69 | BY68: -60591.6 | CA68: -939038.84 | CC68: -72000 | CE68: -8130.95 | CG68: -1509.31 | CI68: -25538.5 | CK68: -252438.47 | CM68: =ROUND(SUM(CE68:CK68),5) -> -287617.23 | CO68: -50207.56 | CQ68: -15781.43 | CS68: =ROUND(SUM(BQ68:CC68)+SUM(CM68:CQ68),5) -> -2481733 | CU68: =ROUND(BO68+CS68,5) -> -2481733 | CW68: 0 | CY68: =ROUND(M68+U68+SUM(CU68:CW68),5) -> -2522775.1 | DA68: =+CO68+CC68+CA68+BU68+BQ68+AG68 -> -1793700.8 | DC68: =+CQ68+BY68+BW68+BS68+BM68+AS68+AQ68+Y68+W68 -> -400414.97
D69: Total 7010 · Restricted Activities | I69: =ROUND(SUM(I66:I68),5) -> 1346.04 | K69: =ROUND(SUM(K66:K68),5) -> 0 | M69: =ROUND(SUM(I69:K69),5) -> 1346.04 | O69: =ROUND(SUM(O66:O68),5) -> 4450 | Q69: =ROUND(SUM(Q66:Q68),5) -> 27711.78 | S69: =ROUND(SUM(S66:S68),5) -> 0 | U69: =ROUND(SUM(O69:S69),5) -> 32161.78 | W69: =ROUND(SUM(W66:W68),5) -> 0 | Y69: =ROUND(SUM(Y66:Y68),5) -> 0 | AA69: =ROUND(SUM(AA66:AA68),5) -> 0 | AC69: =ROUND(SUM(AC66:AC68),5) -> 0 | AE69: =ROUND(SUM(AE66:AE68),5) -> 0 | AG69: =ROUND(SUM(AA69:AE69),5) -> 0 | AI69: =ROUND(SUM(AI66:AI68),5) -> 0 | AK69: =ROUND(SUM(AK66:AK68),5) -> 0 | AM69: =ROUND(SUM(AM66:AM68),5) -> 0 | AO69: =ROUND(SUM(AO66:AO68),5) -> 0 | AQ69: =ROUND(SUM(AI69:AO69),5) -> 0 | AS69: =ROUND(SUM(AS66:AS68),5) -> 0 | AU69: =ROUND(SUM(AU66:AU68),5) -> 0 | AW69: =ROUND(SUM(AW66:AW68),5) -> 0 | AY69: =ROUND(SUM(AY66:AY68),5) -> 0 | BA69: =ROUND(SUM(BA66:BA68),5) -> 0 | BC69: =ROUND(SUM(BC66:BC68),5) -> 0 | BE69: =ROUND(SUM(BE66:BE68),5) -> 0 | BG69: =ROUND(SUM(BG66:BG68),5) -> 0 | BI69: =ROUND(SUM(BI66:BI68),5) -> 0 | BK69: =ROUND(SUM(BK66:BK68),5) -> 0 | BM69: =ROUND(SUM(AU69:BK69),5) -> 0 | BO69: =ROUND(SUM(W69:Y69)+AG69+SUM(AQ69:AS69)+BM69,5) -> 0 | BQ69: =ROUND(SUM(BQ66:BQ68),5) -> -533112.12 | BS69: =ROUND(SUM(BS66:BS68),5) -> -14824.25 | BU69: =ROUND(SUM(BU66:BU68),5) -> -1016.41 | BW69: =ROUND(SUM(BW66:BW68),5) -> -202089.27 | BY69: =ROUND(SUM(BY66:BY68),5) -> -4091.6 | CA69: =ROUND(SUM(CA66:CA68),5) -> -912941.52 | CC69: =ROUND(SUM(CC66:CC68),5) -> -72000 | CE69: =ROUND(SUM(CE66:CE68),5) -> 10266.58 | CG69: =ROUND(SUM(CG66:CG68),5) -> 29049.15 | CI69: =ROUND(SUM(CI66:CI68),5) -> -9286.51 | CK69: =ROUND(SUM(CK66:CK68),5) -> -189256.82 | CM69: =ROUND(SUM(CE69:CK69),5) -> -159227.6 | CO69: =ROUND(SUM(CO66:CO68),5) -> -50207.56 | CQ69: =ROUND(SUM(CQ66:CQ68),5) -> 11354.89 | CS69: =ROUND(SUM(BQ69:CC69)+SUM(CM69:CQ69),5) -> -1938155.4 | CU69: =ROUND(BO69+CS69,5) -> -1938155.4 | CW69: =ROUND(SUM(CW66:CW68),5) -> 0 | CY69: =ROUND(M69+U69+SUM(CU69:CW69),5) -> -1904647.6 | DA69: =+CO69+CC69+CA69+BU69+BQ69+AG69 -> -1569277.6 | DC69: =+CQ69+BY69+BW69+BS69+BM69+AS69+AQ69+Y69+W69 -> -209650.23
C70: Total Other Income | I70: =ROUND(I65+I69,5) -> 1346.04 | K70: =ROUND(K65+K69,5) -> 0 | M70: =ROUND(SUM(I70:K70),5) -> 1346.04 | O70: =ROUND(O65+O69,5) -> 4450 | Q70: =ROUND(Q65+Q69,5) -> 27711.78 | S70: =ROUND(S65+S69,5) -> 0 | U70: =ROUND(SUM(O70:S70),5) -> 32161.78 | W70: =ROUND(W65+W69,5) -> 0 | Y70: =ROUND(Y65+Y69,5) -> 0 | AA70: =ROUND(AA65+AA69,5) -> 0 | AC70: =ROUND(AC65+AC69,5) -> 0 | AE70: =ROUND(AE65+AE69,5) -> 0 | AG70: =ROUND(SUM(AA70:AE70),5) -> 0 | AI70: =ROUND(AI65+AI69,5) -> 0 | AK70: =ROUND(AK65+AK69,5) -> 0 | AM70: =ROUND(AM65+AM69,5) -> 0 | AO70: =ROUND(AO65+AO69,5) -> 0 | AQ70: =ROUND(SUM(AI70:AO70),5) -> 0 | AS70: =ROUND(AS65+AS69,5) -> 0 | AU70: =ROUND(AU65+AU69,5) -> 0 | AW70: =ROUND(AW65+AW69,5) -> 0 | AY70: =ROUND(AY65+AY69,5) -> 0 | BA70: =ROUND(BA65+BA69,5) -> 0 | BC70: =ROUND(BC65+BC69,5) -> 0 | BE70: =ROUND(BE65+BE69,5) -> 0 | BG70: =ROUND(BG65+BG69,5) -> 0 | BI70: =ROUND(BI65+BI69,5) -> 0 | BK70: =ROUND(BK65+BK69,5) -> 0 | BM70: =ROUND(SUM(AU70:BK70),5) -> 0 | BO70: =ROUND(SUM(W70:Y70)+AG70+SUM(AQ70:AS70)+BM70,5) -> 0 | BQ70: =ROUND(BQ65+BQ69,5) -> -533112.12 | BS70: =ROUND(BS65+BS69,5) -> -14824.25 | BU70: =ROUND(BU65+BU69,5) -> -1016.41 | BW70: =ROUND(BW65+BW69,5) -> -202089.27 | BY70: =ROUND(BY65+BY69,5) -> -4091.6 | CA70: =ROUND(CA65+CA69,5) -> -912941.52 | CC70: =ROUND(CC65+CC69,5) -> -72000 | CE70: =ROUND(CE65+CE69,5) -> 10266.58 | CG70: =ROUND(CG65+CG69,5) -> 29049.15 | CI70: =ROUND(CI65+CI69,5) -> -9286.51 | CK70: =ROUND(CK65+CK69,5) -> -189256.82 | CM70: =ROUND(SUM(CE70:CK70),5) -> -159227.6 | CO70: =ROUND(CO65+CO69,5) -> -50207.56 | CQ70: =ROUND(CQ65+CQ69,5) -> 11354.89 | CS70: =ROUND(SUM(BQ70:CC70)+SUM(CM70:CQ70),5) -> -1938155.4 | CU70: =ROUND(BO70+CS70,5) -> -1938155.4 | CW70: =ROUND(CW65+CW69,5) -> 0 | CY70: =ROUND(M70+U70+SUM(CU70:CW70),5) -> -1904647.6

Sheet SOR
A3: Particulars | B3: Amount (CY) | C3: Related | D3: Unrelated | E3: Excluded in 512-514 | F3: 990 Mapping (CY) | G3: Amount (LY) | H3: 990 Mapping (LY)
A4: Contracts and awards | B4: 8394106 | F4: Refer to Below Working | G4: 3754153 | H4: Refer to Below Working
A5: Grants | B5: 873128 | F5: 1f | G5: 3994993 | H5: Refer to Below Working
A6: Donations | B6: 873809 | F6: 1f | G6: 421406 | H6: Refer to Below Working
A7: Contribution of non-financial asset | B7: 34712 | F7: Adj-DS | G7: 58835 | H7: 1g
A8: Special Events | B8: 152678 | F8: Refer to Below Working | G8: 145827 | H8: Refer to Below Working
A9: Program fees | B9: 12254 | C9: =B9 -> 12254 | F9: 2a | G9: 42558 | H9: 2a
A10: Investment income, net | B10: 45367 | F10: Refer to Below Working | G10: 23463 | H10: Refer to Below Working
A11: Other income | B11: 138086 | F11: Refer to Below Working | G11: 12581 | H11: 3
A13: Total (As per Audit Report) | B13: =SUM(B4:B12) -> 10524140 | C13: =SUM(C4:C12) -> 12254 | D13: =SUM(D4:D12) -> 0 | E13: =SUM(E4:E12) -> 0 | G13: =SUM(G4:G12) -> 8453816
A14: * If you have bifurcated any head below, Don't Map in the above statement, Mapping should be done below only
A15: * DO NOT USE CUT (CRTL+X) | B15: =+B13-B48-B7 -> 10458506 | C15: 10458506
A17: Contracts and awards
A18: HIAS(Per GL) | B18: 1576392 | F18: 1f | G18: 1107619 | H18: 1f
A19: Claims Conference (Per Gl) | B19: 4734647 | F19: 1f
A20: Remaining Contracts and Awards | B20: =+B4-B18-B19 -> 2083067 | F20: 1e | G20: 2646534 | H20: 1e
A21: Total | B21: =SUM(B18:B20) -> 8394106 | G21: =SUM(G18:G20) -> 3754153
A24: Grants
A25: Government Contributors(Per GL Code- 4002) | G25: 2665464 | H25: 1e
A26: Government Non-Cash Contribution | G26: 25000 | H26: 1g
A27: Stock Donation | G27: 3300 | H27: 1g
A28: Remaining Contributors | G28: 1301229 | H28: 1f
A29: Total | G29: =SUM(G25:G28) -> 3994993
A32: Donations
A33: Stock Donation | G33: 501 | H33: 1g
A34: Remaining Donations | G34: 420905 | H34: 1f
A35: Total | G35: =SUM(G33:G34) -> 421406
A38: Special Events
A39: Fundraising Events
A40: Gross Receipts | B40: =-'TB Mapping '!E107 -> 200842 | G40: 179757
A41: Less: Contribution | B41: =-'TB Mapping '!E109 -> 152678 | F41: 1c | G41: 145827 | H41: 1c
A42: Gross income | B42: =+B40-B41 -> 48164 | F42: 8a | G42: 33930 | H42: 8a
A43: Event expenses | B43: ='TB Mapping '!E108 -> 48164 | F43: 8b | G43: 33930 | H43: 8b
A44: Net income | B44: =+B42-B43 -> 0 | G44: =+G42-G43 -> 0
A47: Investment income, net
A48: Unrealized Gain | B48: 30922 | F48: Adj-UG | G48: 6850 | H48: Adj-UG
A49: Interest Income | B49: =+B10-B48 -> 14445 | E49: =+B49 -> 14445 | F49: 3 | G49: 16777 | H49: 3
A50: Realized Loss | G50: -164 | H50: Refer to Below Working
B51: =SUM(B48:B50) -> 45367
A54: Gross Amount from sale of assets other than Inventory | G54: 103637 | H54: 7a-S
A55: Cost or Other basis and sales expenses | G55: 103801 | H55: 7b-S
A56: Realized Loss | G56: =+G54-G55 -> -164
A59: Other income
A60: Interest Income | B60: =-'TB Mapping '!E118 -> 10329 | E60: =+B60 -> 10329 | F60: 3
A61: Other Income | B61: =-'TB Mapping '!E119 -> 127757 | C61: =+B61 -> 127757 | F61: 11a
A62: Total | B62: =SUM(B60:B61) -> 138086

Sheet SOFE
B2: PROGRAM SERVICES | F2: SUPPORTING SERVICES
A3: Particulars | B3: Adult & Family Services | C3: Refugee Services | D3: Aging Services | E3: PROGRAM SERVICES | F3: Management | G3: Fundraising | H3: Total (CY) | I3: Total (LY) | J3: 990 Mapping (CY) | K3: 990 Mapping (LY)
A4: Salaries and wages | B4: 149929 | C4: 1619149 | D4: 1058173 | E4: =+SUM(B4:D4) -> 2827251 | F4: 352109 | G4: 201392 | H4: =+SUM(E4:G4) -> 3380752 | I4: 2539369 | J4: Refer to below Working | K4: Refer to below Working
A5: Employee benefits | B5: 26031 | C5: 255664 | D5: 171991 | E5: =+SUM(B5:D5) -> 453686 | F5: 80548 | G5: 13863 | H5: =+SUM(E5:G5) -> 548097 | I5: 278359 | J5: Refer to below Working | K5: Refer to below Working
A6: Payroll taxes | B6: 13408 | C6: 147459 | D6: 91476 | E6: =+SUM(B6:D6) -> 252343 | F6: 12636 | G6: 7262 | H6: =+SUM(E6:G6) -> 272241 | I6: 197666 | J6: Refer to below Working | K6: Refer to below Working
A7: Advertising | C7: 0 | D7: 1650 | E7: =+SUM(B7:D7) -> 1650 | F7: 1074 | G7: 185 | H7: =+SUM(E7:G7) -> 2909 | I7: 5810 | J7: 12 | K7: 12
A8: Professional services | B8: 2804 | C8: 24277 | D8: 78891 | E8: =+SUM(B8:D8) -> 105972 | F8: 358497 | G8: 32682 | H8: =+SUM(E8:G8) -> 497151 | I8: 375453 | J8: Refer to below Working | K8: Refer to below Working
A9: Depreciation | C9: 0 | D9: 0 | E9: =+SUM(B9:D9) -> 0 | F9: 3285 | G9: 0 | H9: =+SUM(E9:G9) -> 3285 | I9: 4529 | J9: 22 | K9: 22
A10: Interest | B10: 444 | C10: 5501 | D10: 9069 | E10: =+SUM(B10:D10) -> 15014 | F10: 1391 | G10: 445 | H10: =+SUM(E10:G10) -> 16850 | I10: 2345 | J10: 20 | K10: 20
A11: Lease amoritization | B11: 4743 | C11: 58771 | D11: 96899 | E11: =+SUM(B11:D11) -> 160413 | F11: 14862 | G11: 4753 | H11: =+SUM(E11:G11) -> 180028 | I11: 25155 | J11: 22 | K11: 22
A12: Office expenses | B12: 11400 | C12: 49751 | D12: 74642 | E12: =+SUM(B12:D12) -> 135793 | F12: 107098 | G12: 23336 | H12: =+SUM(E12:G12) -> 266227 | I12: 139576 | J12: Refer to below Working | K12: Refer to below Working
A13: IT services | B13: 3082 | C13: 23523 | D13: 19879 | E13: =+SUM(B13:D13) -> 46484 | F13: 56404 | G13: 2108 | H13: =+SUM(E13:G13) -> 104996 | I13: 37237 | J13: 14 | K13: 14
A14: Occupancy | B14: 42310 | C14: 21517 | D14: 20839 | E14: =+SUM(B14:D14) -> 84666 | F14: -2758 | G14: 2298 | H14: =+SUM(E14:G14) -> 84206 | I14: 108136 | J14: 16 | K14: 16
A15: In KindDonation Expenses | B15: 0 | C15: 0 | D15: 0 | E15: =+SUM(B15:D15) -> 0 | F15: 0 | G15: 21248 | H15: =+SUM(E15:G15) -> 21248 | J15: Adj-DS
A16: Bad debts expense | C16: 0 | D16: 0 | E16: =+SUM(B16:D16) -> 0 | F16: 0 | G16: 7906 | H16: =+SUM(E16:G16) -> 7906 | I16: 23777 | J16: Adj-Other | K16: Adj-Other
A17: Conferences and meetings | B17: 223 | C17: 9967 | D17: 13895 | E17: =+SUM(B17:D17) -> 24085 | F17: 12771 | G17: 9809 | H17: =+SUM(E17:G17) -> 46665 | I17: 20116 | J17: Refer to below Working | K17: Refer to below Working
A18: Grants | B18: 64133 | C18: 1736466 | D18: 4881484 | E18: =+SUM(B18:D18) -> 6682083 | F18: 1586 | G18: 0 | H18: =+SUM(E18:G18) -> 6683669 | I18: 2412563 | J18: Refer to below Working | K18: Refer to below Working
A19: Insurance | B19: 769 | C19: 3848 | D19: 3375 | E19: =+SUM(B19:D19) -> 7992 | F19: 882 | G19: 576 | H19: =+SUM(E19:G19) -> 9450 | I19: 8374 | J19: 23 | K19: 23
E20: =+SUM(B20:D20) -> 0 | H20: =+SUM(E20:G20) -> 0
A21: TOTAL (As Per Audit Report) | B21: =+SUM(B4:B20) -> 319276 | C21: =+SUM(C4:C20) -> 3955893 | D21: =SUM(D4:D20) -> 6522263 | E21: =SUM(E4:E20) -> 10797432 | F21: =SUM(F4:F20) -> 1000385 | G21: =SUM(G4:G20) -> 327863 | H21: =SUM(H4:H20) -> 12125680 | I21: =SUM(I4:I20) -> 6178465
A22: * If you have bifurcated any head below, Don't Map in the above statement, Mapping should be done below only
A23: * DO NOT USE CUT (CRTL+X) | G23: =+G21-G16-G15 -> 298709 | H23: =+H21-H16-H15 -> 12096526
A25: Total Salaries and Benefits
A26: Compensation to Officer | E26: =+Compensation!G9 -> 186012.93 | F26: =+Compensation!H9 -> 24663.458 | G26: =+Compensation!I9 -> 12077.404 | H26: =+SUM(E26:G26) -> 222753.79 | I26: 330716 | J26: 5 | K26: 5
A27: Other Salaries | E27: =+Compensation!L5 -> 2669445.2 | F27: =+Compensation!M5 -> 332455.69 | G27: =+Compensation!N5+0.16 -> 190151.27 | H27: =+SUM(E27:G27) -> 3192052.2 | I27: 2245736 | J27: 7 | K27: 7
A28: Pension | E28: =+Compensation!L6 -> 69453.697 | F28: =+Compensation!M6 -> 12373.591 | G28: =+Compensation!N6 -> 1632.9621 | H28: =+SUM(E28:G28) -> 83460.25 | I28: 15873 | J28: 8 | K28: 8
A29: Other Benefits | E29: =+Compensation!L7 -> 356024.94 | F29: =+Compensation!M7 -> 63164.242 | G29: =+Compensation!N7+0.22 -> 11393.617 | H29: =+SUM(E29:G29) -> 430582.8 | I29: 225403 | J29: 9 | K29: 9
A30: Payroll Taxes | E30: =+Compensation!L8 -> 252343 | F30: =+Compensation!M8 -> 12636 | G30: =+Compensation!N8 -> 7262 | H30: =+SUM(E30:G30) -> 272241 | I30: 197666 | J30: 10 | K30: 10
A31: Total | E31: =SUM(E26:E30) -> 3533279.8 | F31: =SUM(F26:F30) -> 445292.98 | G31: =SUM(G26:G30) -> 222517.25 | H31: =SUM(H26:H30) -> 4201090 | I31: =SUM(I26:I30) -> 3015394
A34: Professional services
A35: Accounting | E35: 0 | F35: ='Function Exp'!M32 -> 257245 | G35: ='Function Exp'!U32 -> 0 | H35: =+SUM(E35:G35) -> 257245 | I35: 150800 | J35: 11c | K35: 11c
A36: Legal | E36: ='Function Exp'!CU31+0.5 -> 60483 | F36: ='Function Exp'!M31 -> 3780 | G36: 0 | H36: =+SUM(E36:G36) -> 64263 | I36: 29969.5 | J36: 11b | K36: 11b
A37: Payroll fees and other administration | E37: 0 | F37: ='Function Exp'!M29 -> 9620 | G37: 0 | H37: =+SUM(E37:G37) -> 9620 | I37: 320 | J37: 11g | K37: 11g
A38: Staffing and Hiring | E38: ='Function Exp'!CU56 -> 1234 | F38: ='Function Exp'!M56 -> 3524 | G38: ='Function Exp'!U56 -> 100 | H38: =+SUM(E38:G38) -> 4858 | I38: 34855 | J38: 11g | K38: 11g
A39: Other services | E39: ='Function Exp'!CU30+0.47 -> 31883 | F39: ='Function Exp'!M30-0.6 -> 96700 | G39: ='Function Exp'!U30+0.42 -> 32582 | H39: =+SUM(E39:G39) -> 161165 | I39: 159507.58 | J39: Refer to below Working | K39: 11g
A40: Professional Services - Other | E40: =+'Function Exp'!CU33 -> 12372 | F40: =+'Function Exp'!M33 -> -12372 | G40: =+'Function Exp'!U33 -> 0 | H40: =SUM(E40:G40) -> 0 | J40: 11g
A41: Total | E41: =SUM(E35:E40) -> 105972 | F41: =SUM(F35:F40) -> 358497 | G41: =SUM(G35:G40) -> 32682 | H41: =SUM(H35:H40) -> 497151 | I41: =SUM(I35:I39) -> 375452.08
A44: Other services
A45: Harshwal & Company LLP (As per GL) | E45: =+H45/H39*E39 -> 9990.3298 | F45: =+H45/H39*F39 -> 30300.313 | G45: =+H45/H39*G39 -> 10209.357 | H45: 50500 | J45: 11c
A46: Other Services | E46: =+E39-E45 -> 21892.67 | F46: =+F39-F45 -> 66399.687 | G46: =+G39-G45 -> 22372.643 | H46: =+H39-H45 -> 110665 | J46: 11g
A47: Total | E47: =SUM(E45:E46) -> 31883 | F47: =SUM(F45:F46) -> 96700 | G47: =SUM(G45:G46) -> 32582 | H47: =SUM(H45:H46) -> 161165
A50: Office expenses | E50: 3.5973089 | F50: 54.777251 | G50: 41.62544
A51: (Bank and Credit Card Charge) | E51: =+H51*E50/100 -> 204.90632 | F51: =+H51*F50/100 -> 3120.167 | G51: =+H51*G50/100 -> 2371.0267 | H51: =7863.1-2167 -> 5696.1 | I51: 5942 | J51: 13
A52: Less - Investment Management Fees(Per Audit Report- Investment Note) | E52: =+$H$52*E50/100 -> 77.953685 | F52: =+$H$52*F50/100 -> 1187.023 | G52: =+$H$52*G50/100 -> 902.02329 | H52: 2167 | I52: 2070 | J52: 11f | K52: 11f
A53: In-kind donated services (per Gl) | F53: 13464 | H53: =SUM(E53:G53) -> 13464 | J53: Adj-DS
A54: Remaining Office Expenses | E54: =+E55-E51-E52-E53 -> 135510.14 | F54: =+F55-F51-F52-F53 -> 89326.81 | G54: =+G55-G51-G52-G53 -> 20062.95 | H54: =SUM(E54:G54) -> 244899.9 | I54: =+I55-I52 -> 137506 | J54: 13 | K54: 13
A55: Total | B55: =B12 -> 11400 | C55: =C12 -> 49751 | D55: =D12 -> 74642 | E55: =E12 -> 135793 | F55: =F12 -> 107098 | G55: =G12 -> 23336 | H55: =H12 -> 266227 | I55: =+I12 -> 139576
A58: Conferences and meetings
A59: Operating Expenses:6380 . Travel | E59: ='Function Exp'!CU35+0.24 -> 15531 | F59: ='Function Exp'!M35 -> 292.14 | G59: ='Function Exp'!U35+0.29 -> 54 | H59: =+SUM(E59:G59) -> 15877.14 | I59: 8526.18 | J59: 17 | K59: 17
A60: Operating Expenses:Conference and Meetings | E60: ='Function Exp'!CU22 -> 8554.1 | F60: ='Function Exp'!M22 -> 12479.17 | G60: =SUM('Function Exp'!U22)+0.21 -> 9755 | H60: =+SUM(E60:G60) -> 30788.27 | I60: 11590.21 | J60: 19 | K60: 19
A61: Total | E61: =SUM(E59:E60) -> 24085.1 | F61: =SUM(F59:F60) -> 12771.31 | G61: =SUM(G59:G60) -> 9809 | H61: =SUM(H59:H60) -> 46665.41 | I61: =SUM(I59:I60) -> 20116.39
A64: Grants
A65: Grants & other assistance to domestic individuals | E65: =+E18 -> 6682083 | F65: 0 | G65: 0 | H65: =+SUM(E65:G65) -> 6682083 | I65: 2346370 | J65: 2 | K65: 2
A66: Other Grants | E66: 0 | F66: =+F18 -> 1586 | G66: 0 | H66: =+SUM(E66:G66) -> 1586 | I66: 66193 | J66: 24a | K66: 24a
A67: Total | E67: =SUM(E65:E66) -> 6682083 | F67: =SUM(F65:F66) -> 1586 | G67: =SUM(G65:G66) -> 0 | H67: =SUM(H65:H66) -> 6683669 | I67: =SUM(I65:I66) -> 2412563

Sheet Compensation
A1: Compensation Working
A3: Total Salaries and Benefits (as per audit report) | G3: Officer, Director Salaries and Benefits | L3: Remaining Salaries and Benefits
B4: Program Exp | C4: Management & General | D4: Fundraising | E4: Total | G4: Program Exp | H4: Management & General | I4: Fundraising | J4: Total | L4: Program Exp | M4: Management & General | N4: Fundraising | O4: Total
A5: Salaries | B5: =+SOFE!E4 -> 2827251 | C5: =+SOFE!F4 -> 352109 | D5: =+SOFE!G4 -> 201392 | E5: =SUM(B5:D5) -> 3380752 | G5: =+$J$5/$E$5*B5 -> 157805.8 | H5: =+$J$5/$E$5*C5 -> 19653.31 | I5: =+$J$5/$E$5*D5 -> 11240.893 | J5: =+B15 -> 188700 | L5: =+B5-G5 -> 2669445.2 | M5: =+C5-H5 -> 332455.69 | N5: =+D5-I5 -> 190151.11 | O5: =+SUM(L5:N5) -> 3192052
A6: Pension Plan | B6: ='Function Exp'!CU50 -> 77246.81 | C6: ='Function Exp'!CW50+'Function Exp'!M50 -> 13761.98 | D6: ='Function Exp'!U50 -> 1816.19 | E6: =SUM(B6:D6) -> 92824.98 | G6: =+$J$6/$E$6*B6 -> 7793.1126 | H6: =+$J$6/$E$6*C6 -> 1388.3895 | I6: =+$J$6/$E$6*D6 -> 183.22793 | J6: =+D15 -> 9364.73 | L6: =+B6-G6 -> 69453.697 | M6: =+C6-H6 -> 12373.591 | N6: =+D6-I6 -> 1632.9621 | O6: =+SUM(L6:N6) -> 83460.25
A7: Other Benefits | B7: =SUM('Function Exp'!CU51:CU52)+0.25 -> 376438.96 | C7: =SUM('Function Exp'!M51:M52)-0.25-0.24 -> 66786 | D7: =SUM('Function Exp'!U51:U52) -> 12046.68 | E7: =SUM(B7:D7) -> 455271.64 | G7: =+$J$7/$E$7*B7 -> 20414.019 | H7: =+$J$7/$E$7*C7 -> 3621.7577 | I7: =+$J$7/$E$7*D7 -> 653.28296 | J7: =+C15 -> 24689.06 | L7: =+B7-G7 -> 356024.94 | M7: =+C7-H7 -> 63164.242 | N7: =+D7-I7 -> 11393.397 | O7: =+SUM(L7:N7) -> 430582.58
A8: Payroll Taxes | B8: =+SOFE!E6 -> 252343 | C8: =+SOFE!F6 -> 12636 | D8: =+SOFE!G6 -> 7262 | E8: =SUM(B8:D8) -> 272241 | L8: =+B8-G8 -> 252343 | M8: =+C8-H8 -> 12636 | N8: =+D8-I8 -> 7262 | O8: =+SUM(L8:N8) -> 272241
A9: Total | B9: =+SUM(B5:B8) -> 3533279.8 | C9: =+SUM(C5:C8) -> 445292.98 | D9: =+SUM(D5:D8) -> 222516.87 | E9: =+SUM(E5:E8) -> 4201089.6 | G9: =+SUM(G5:G8) -> 186012.93 | H9: =+SUM(H5:H8) -> 24663.458 | I9: =+SUM(I5:I8) -> 12077.404 | J9: =+SUM(J5:J8) -> 222753.79 | L9: =+SUM(L5:L8) -> 3347266.8 | M9: =+SUM(M5:M8) -> 420629.52 | N9: =+SUM(N5:N8) -> 210439.47 | O9: =+SUM(O5:O8) -> 3978335.8
A12: Schedule Template
A13: Officer | B13: Base Contribution | C13: Benefits | D13: Pension Plan | E13: Total
A14: Frazer, Susan | B14: 188700 | C14: =22790.02+1899.04 -> 24689.06 | D14: 9364.73 | E14: =SUM(B14:D14) -> 222753.79
B15: =SUM(B14:B14) -> 188700 | C15: =SUM(C14:C14) -> 24689.06 | D15: =SUM(D14:D14) -> 9364.73 | E15: =SUM(E14:E14) -> 222753.79

Sheet CA Rollforward
A1: * DO NOT USE CUT (CRTL+X)

Sheet SOFP
B2: STATEMENT OF FINANCIAL POSITION
B3: Particulars | C3: 2023 | D3: 2024 | E3: 990 Mapping (LY) | F3: 990 Mapping (CY)
B4: Assets
B5: Current assets
B6: Cash & Cash Equivalents | C6: 2880183 | D6: 1118499 | E6: Refer to Below working | F6: Refer to below Working
B7: Account Receivables | C7: 869889 | D7: 615104 | E7: 3 | F7: 3
B8: Grant Receivable | D8: 1726113 | F8: 3
B9: Pledges Receivable, net of allowance | C9: 31000 | D9: 154588 | E9: 3 | F9: 3
B10: Benefits Receivable | C10: 3706 | D10: 0 | E10: 4
B11: Security Deposits | C11: 29175 | D11: 29175 | E11: 15 | F11: 15
B12: Inventory | C12: 3210 | D12: 2361 | E12: 8 | F12: 8
B13: Prepaid expenses | C13: 63626 | D13: 45259 | E13: 9 | F13: 9
B14: Total current assets | C14: =+SUM(C6:C13) -> 3880789 | D14: =SUM(D6:D13) -> 3691099
B16: Noncurrent assets
B17: Investments | C17: 412460 | D17: 975077 | E17: 12 | F17: 12
B18: Pledges Receivable, net of current portion | C18: 99736 | D18: 103435 | E18: 3 | F18: 3
B19: Property and Equipment, net | C19: =+C50 -> 9724 | D19: =+D50 -> 6439 | E19: Refer to below Working | F19: Refer to below Working
B20: Operating lease rights of use assets, net | C20: 342890 | D20: =D69 -> 556564 | E20: Refer to below Working | F20: Refer to below Working
B21: Total noncurrent assets | C21: =SUM(C17:C20) -> 864810 | D21: =SUM(D17:D20) -> 1641515
B23: Total Assets | C23: =+C21+C14 -> 4745599 | D23: =D14+D21 -> 5332614
B25: LIABILITIES AND NET ASSETS
B26: LIABILITIES
B27: Current liabilities
B28: Accounts payable & accrued liabilities | C28: 277031 | D28: 1073155 | E28: 17 | F28: 17
B29: Accrued personnel liabilities | C29: 80707 | D29: 194127 | E29: 17 | F29: 17
B30: Deferrd revenue | C30: 0 | D30: 1054229 | F30: 19
B31: Other Liability | C31: 3318 | D31: 11298 | E31: 17 | F31: 17
B32: Operating lease liabilities | C32: 154536 | D32: 220287 | E32: 25 | F32: 25
B33: Total current liabilities | C33: =+SUM(C28:C32) -> 515592 | D33: =SUM(D28:D32) -> 2553096
B34: Non-Current liabilities
B35: Operating lease liabilities, net of current portion | C35: 188354 | D35: 339405 | E35: 25 | F35: 25
B36: Total Non-current liabilities | C36: =+C35 -> 188354 | D36: =+D35 -> 339405
B37: Total Liabilities | C37: =SUM(C33+C36) -> 703946 | D37: =SUM(D33+D36) -> 2892501
B39: NET ASSETS
B40: Without donor restrictions | C40: 460416 | D40: 103743 | E40: 27 | F40: 27
B41: With donor restrictions | C41: 3581237 | D41: 2336370 | E41: 28 | F41: 28
B42: Total Net Assets | C42: =+C40+C41 -> 4041653 | D42: =+D40+D41 -> 2440113
B43: Total liabilities and net assets | C43: =C37+C42 -> 4745599 | D43: =D37+D42 -> 5332614
B44: * If you have bifurcated any head below, Don't Map in the above statement, Mapping should be done below only
B45: * DO NOT USE CUT (CRTL+X)
B47: Fixed Assets:
B48: Cost | C48: 40391 | D48: ='TB Mapping '!E42 -> 40391 | E48: 10a | F48: 10a
B49: less: Accumulated Depreciation | C49: 30667 | D49: =-'TB Mapping '!E45 -> 33952 | E49: 10b | F49: 10b
B50: Net Fixed Assets | C50: =+C48-C49 -> 9724 | D50: =+D48-D49 -> 6439
B53: Cash & Cash Equivalents
B54: Bank of America | C54: 516436.07 | D54: 0 | E54: 1
B55: BOA - Money Market | C55: 79755.62 | D55: 0 | E55: 2
B56: BOA-CD Account | C56: 0 | D56: 0
B57: First Republic Bank | C57: 235234.64 | E57: 1
B58: FRB - ICS | C58: 1990834.7 | E58: 2
B59: Chase Bank | C59: 0 | D59: ='TB Mapping '!E7 -> 1104428 | F59: 1
B60: PayPal | C60: 54001.73 | D60: ='TB Mapping '!E12 -> 10595 | E60: 1 | F60: 1
B61: Petty Cash | C61: 120.27 | D61: ='TB Mapping '!E10 -> 101 | E61: 1 | F61: 1
B62: Petty Cash for Refugees | C62: 3800 | D62: ='TB Mapping '!E11 -> 3375 | E62: 1 | F62: 1
B63: Total | C63: =SUM(C54:C62) -> 2880183 | D63: =SUM(D54:D62) -> 1118499
B66: Operating lease rights of use assets, net
B67: Operating lease rights of use assets | C67: 368045 | D67: =+'TB Mapping '!E48 -> 761747
B68: Accumulated Amortization | C68: 25155 | D68: =-'TB Mapping '!E49 -> 205183
B69: Operating lease rights of use assets, net | C69: =+C67-C68 -> 342890 | D69: =+D67-D68 -> 556564 | E69: 14 | F69: 14
